Workbook

Sheet 00_审核入口
A1: 00 · 审核入口
A2: 先读这一页，再看01逐品结论。蓝色为可录入区；空白=未知。冻结结论必须由更新后的证据重新生成，改单元格不等于重新批准。 | F2: 46280.89
A4: 项目 | B4: 本轮结果 | C4: 含义及限制 | D4: 建议行动
A5: 运行时间 | B5: 2026-09-15T21:21:21+08:00 | C5: 以来源自身观测日期判断新鲜度 | D5: 不可用运行时间替换历史数据日期
A6: 历史候选记录 | B6: 22 | C6: 尚待准确规格/SPU复核；不能全部视为独立已验证商品 | D6: 见01与02
A7: 证据充分可测品 | B7: 0 | C7: 当前所有正式成本缺失；真实成功盈利数也为0 | D7: 不采购、不投放、不上架
A8: 原始市场记录 | B8: 220 | C8: 原始采集并非本轮新增，币种与窗口异常 | D8: 见07与08
A9: 1688历史货源记录 | B9: 600 | C9: 起价及整条offer，不是当前同SKU报价 | D9: 见06；0价不能当免费
A10: 利润门槛 | B10: 20% 且 15元 | C10: 完全成本预计利润/商品收入；条件，不是保证 | D10: 基准、采购上限、压力三项一起审
A11: 单品测试总成本 | B11: ≤500 CNY | C11: 含采购、物流、平台费、推广、样品、售后等 | D11: 不能仅限制采购额
A12: 一分钟审一款的前提 | B12: 标准化证据已完整 | C12: 目标每日人工60分钟；首次建库与等待报价另计 | D12: 先做3天计时试跑
A13: 验收缺口 | B13: 未达到≥10个成功选品 | C13: 市场有效窗口、同SKU报价、运费费用及现金资料不全 | D13: 补齐数据后重跑；不以历史候选充数

Sheet 01_逐品结论
A1: 01 · 逐品结论
A2: 逐款列明冻结的证据与结论；方向性推断不是需求、质量、同款、利润或授权事实。真实经营成功只能由成熟实单对账证明。
A4: ID | B4: 产品方向 | C4: 本轮结论 | D4: 事实证据 | E4: 判断说明（推断） | F4: 拟验证差异 | G4: 缺口与风险 | H4: 补证顺序 | I4: 市场链接 | J4: 1688线索 | K4: 预计利润CNY | L4: 利润率 | M4: 测试成本CNY
A5: C01 | B5: 多尺寸拉链洗衣网袋套装 | C5: 待补证 | D5: 历史2026-09-10记录：价格原值75（币种未确认）；销量字段4957（窗口未核实）；1688历史起价0.6元；MOQ=1；代发原字段=True；未同SKU核验。 | E5: 洗衣防缠绕是明确可描述的使用场景，套装有机会分摊每单固定费；要用同规格成交与实物测试证实。 | F5: 细网、拉链保护套、明确尺寸与件数 | G5: PH/PHP与30天SKU销量；准确SKU规格及货源报价；包装计费重与运费；本店完整费项、活动、税与汇率；当前现金/未决损失；样品/合规/图权。比较网眼、拉链包边、尺寸和套装件数，不借竞品品牌。 | H5: A 优先补证：拉链开合与机洗测试；套装件数逐件对齐；取得主货源、完整成本后再判。 | I5: https://shopee.ph/product/1220516363/27528479375 | J5: https://detail.1688.com/offer/625255182969.html
A6: C02 | B6: 行李箱衣物分装收纳套装 | C6: 待补证 | D6: 历史2026-09-10记录：价格原值243（币种未确认）；销量字段68（窗口未核实）；1688历史起价7.8元；MOQ=1；代发原字段=False；未同SKU核验。 | E6: 衣物分装可与洗漱/鞋袋服务同类旅行客户；体积重和单件代发可能否定经济性。 | F6: 分区标签、尺寸图、套装清单 | G6: PH/PHP与30天SKU销量；准确SKU规格及货源报价；包装计费重与运费；本店完整费项、活动、税与汇率；当前现金/未决损失；样品/合规/图权。现有7.8元为历史起价且代发原字段为false，不能认定支持当前模式。 | H6: A 优先补证：体积重量；普通分装与压缩功能分开核实；取得主货源、完整成本后再判。 | I6: https://shopee.ph/product/550121387/14529056693 | J6: https://detail.1688.com/offer/847068328975.html
A7: C03 | B7: 挂钩式旅行洗漱收纳包 | C7: 待补证 | D7: 历史2026-09-10记录：价格原值110（币种未确认）；销量字段3470（窗口未核实）；未取得该方向可配对的1688货源证据。 | E7: 空洗漱包无需搭售化妆品，可突出悬挂和分仓；这是结构优势假设。 | F7: 可展开分区、挂钩、干湿收纳场景 | G7: PH/PHP与30天SKU销量；准确SKU规格及货源报价；包装计费重与运费；本店完整费项、活动、税与汇率；当前现金/未决损失；样品/合规/图权。主货源空缺，需核实挂钩强度、空包包装重；不含液体、不直接称防水。 | H7: A 优先补证：挂钩强度、拉链、湿擦测试；不带液体；取得主货源、完整成本后再判。 | I7: https://shopee.ph/product/1338796953/24944345450
A8: C04 | B8: 抽绳鞋子防尘收纳袋 | C8: 待补证 | D8: 历史2026-09-10记录：价格原值15（币种未确认）；销量字段102（窗口未核实）；未取得该方向可配对的1688货源证据。 | E8: 结构简单但低价方向容易被固定处理费和国际运费吃掉利润；可研究多件组合。 | F8: 多件组合、可辨识鞋型尺寸 | G8: PH/PHP与30天SKU销量；准确SKU规格及货源报价；包装计费重与运费；本店完整费项、活动、税与汇率；当前现金/未决损失；样品/合规/图权。多件组合会改变SKU和竞品可比性，不能拿单只销量配整套定价。 | H8: B 暂缓单卖：低客单单卖成本；抽绳牢度与布料厚度；取得主货源、完整成本后再判。 | I8: https://shopee.ph/product/699515539/25544554587
A9: C05 | B9: 衣柜悬挂手袋收纳袋 | C9: 待补证 | D9: 历史2026-09-10记录：价格原值168（币种未确认）；销量字段750（窗口未核实）；未取得该方向可配对的1688货源证据。 | E9: 能服务衣柜整理场景；悬挂袋的大包装体积可能使跨境物流不合算。 | F9: 袋位可见、适配衣柜尺寸 | G9: PH/PHP与30天SKU销量；准确SKU规格及货源报价；包装计费重与运费；本店完整费项、活动、税与汇率；当前现金/未决损失；样品/合规/图权。先取得折叠包装尺寸，再核承重和缝线；图片视觉轻薄不等于计费轻。 | H9: B 先看体积：承重、缝线、折叠包装体积；取得主货源、完整成本后再判。 | I9: https://shopee.ph/product/419236915/6185455937
A10: C06 | B10: 发夹与发圈挂式整理架 | C10: 待补证 | D10: 历史2026-09-10记录：价格原值40（币种未确认）；销量字段528（窗口未核实）；未取得该方向可配对的1688货源证据。 | E10: 有发饰整理用途，但低价竞争和挂装问题可能抬高售后成本。 | F10: 按发夹/发圈分区、展示实物尺寸 | G10: PH/PHP与30天SKU销量；准确SKU规格及货源报价；包装计费重与运费；本店完整费项、活动、税与汇率；当前现金/未决损失；样品/合规/图权。只研究成人收纳用途和无侵权图案；不能推断儿童用品准入。 | H10: B 低优先：挂钩数量、组装难度、素材版权；取得主货源、完整成本后再判。 | I10: https://shopee.ph/product/739548616/26901266092
A11: C07 | B11: 自粘桌面理线夹套装 | C11: 待补证 | D11: 历史2026-09-10记录：价格原值78（币种未确认）；销量字段923（窗口未核实）；1688历史起价0.4元；MOQ=2；代发原字段=True；未同SKU核验。 | E11: 桌面理线需求线索存在，但自粘属性、Choice样本及品牌字段冲突降低可比性。 | F11: 孔径清楚、安装说明、组合数量 | G11: PH/PHP与30天SKU销量；准确SKU规格及货源报价；包装计费重与运费；本店完整费项、活动、税与汇率；当前现金/未决损失；样品/合规/图权。背胶/成分和承运未知；先明确是否符合不做化学相关产品的边界。 | H11: C 属性待核：胶黏耐湿热、可适配线径；参考样本为Choice Global且品牌字段有冲突；取得主货源、完整成本后再判。 | I11: https://shopee.ph/product/196214868/24474649589 | J11: https://detail.1688.com/offer/723994327186.html
A12: C08 | B12: 厨房电器电源线绕线器 | C12: 待补证 | D12: 历史2026-09-10记录：价格原值39（币种未确认）；销量字段1223（窗口未核实）；未取得该方向可配对的1688货源证据。 | E12: 被动绕线工具可整理电器外部线材；背胶失效和靠近热源使用可能增加投诉。 | F12: 突出适配表面与安装位置 | G12: PH/PHP与30天SKU销量；准确SKU规格及货源报价；包装计费重与运费；本店完整费项、活动、税与汇率；当前现金/未决损失；样品/合规/图权。先证实无带电组件、胶黏属性、适配表面；不做电气安全承诺。 | H12: C 属性待核：脱胶与热源距离；不宣称防火或电气保护；取得主货源、完整成本后再判。 | I12: https://shopee.ph/product/1209340734/27308021764
A13: C09 | B13: 螺旋式线材整理保护管 | C13: 待补证 | D13: 历史2026-09-10记录：价格原值105（币种未确认）；销量字段522（窗口未核实）；未取得该方向可配对的1688货源证据。 | E13: 被动整理套管可按长度/直径区分用途；规格错配与安装难度可能拉低转化。 | F13: 按内径和长度售卖 | G13: PH/PHP与30天SKU销量；准确SKU规格及货源报价；包装计费重与运费；本店完整费项、活动、税与汇率；当前现金/未决损失；样品/合规/图权。核实每米/每卷单位，排除电气绝缘或阻燃认证诉求。 | H13: B 规格优先：规格与材质核实；不宣称防猫咬或绝缘认证；取得主货源、完整成本后再判。 | I13: https://shopee.ph/product/284375657/14488134409
A14: C10 | B14: 衣物粘毛滚筒加替换芯 | C14: 待补证 | D14: 历史2026-09-10记录：价格原值15（币种未确认）；销量字段2969（窗口未核实）；未取得该方向可配对的1688货源证据。 | E14: 替换芯可能形成后续需求，但本轮没有真实复购数据，不能计复购率。 | F14: 滚筒与替换芯组合、撕取演示 | G14: PH/PHP与30天SKU销量；准确SKU规格及货源报价；包装计费重与运费；本店完整费项、活动、税与汇率；当前现金/未决损失；样品/合规/图权。粘胶相关属性和剩余纸张数、撕取效果未核；先确认经营边界。 | H14: C 属性待核：纸张数、粘力、实际毛发清理测试；取得主货源、完整成本后再判。 | I14: https://shopee.ph/product/279498155/15750813899
A15: C11 | B15: 硅胶排水口毛发过滤片 | C15: 待补证 | D15: 历史2026-09-10记录：价格原值49（币种未确认）；销量字段647（窗口未核实）；未取得该方向可配对的1688货源证据。 | E15: 浴室排水口过滤是可验证的场景；低客单、孔径不匹配和排水慢可能否定方案。 | F15: 按孔径与排水口形状组合 | G15: PH/PHP与30天SKU销量；准确SKU规格及货源报价；包装计费重与运费；本店完整费项、活动、税与汇率；当前现金/未决损失；样品/合规/图权。只研究浴室非食品接触用途；不可声称抗菌或除臭。 | H15: B 低优先：排水速度、贴合度；不作杀菌除臭承诺；取得主货源、完整成本后再判。 | I15: https://shopee.ph/product/970194884/19694647631
A16: C12 | B16: 挂式塑料袋收纳袋 | C16: 待补证 | D16: 历史2026-09-10记录：价格原值27（币种未确认）；销量字段4053（窗口未核实）；未取得该方向可配对的1688货源证据。 | E16: 上装下抽可演示使用价值，但低价方向需验证组合后仍有市场需求。 | F16: 上装下抽、尺寸与悬挂方式清楚 | G16: PH/PHP与30天SKU销量；准确SKU规格及货源报价；包装计费重与运费；本店完整费项、活动、税与汇率；当前现金/未决损失；样品/合规/图权。需主货源、袋口和挂带样品检查；无证据不推导高转化。 | H16: B 暂缓单卖：低单价竞争；抽取顺畅、挂带强度；取得主货源、完整成本后再判。 | I16: https://shopee.ph/product/419236915/41276257375
A17: C13 | B17: 可重复使用粘扣理线带套装 | C17: 待补证 | D17: 历史2026-09-11记录：价格原值100（币种未确认）；销量字段149（窗口未核实）；1688历史起价0.03元；MOQ=1；代发原字段=True；未同SKU核验。 | E17: 不带胶的可重复绑带符合被动理线方向，套装有机会覆盖固定费。 | F17: 50条套装为竞品标题规格；自有销售套数和尺寸待确认 | G17: PH/PHP与30天SKU销量；准确SKU规格及货源报价；包装计费重与运费；本店完整费项、活动、税与汇率；当前现金/未决损失；样品/合规/图权。0.03元为历史起价，不是50条整套报价；自粘一词需确认是钩毛还是背胶。 | H17: A 优先补证：绑扎力度、反复开合、整套数量；不带胶、不宣称电气绝缘；取得主货源、完整成本后再判。 | I17: https://shopee.ph/product/264585346/20569033063 | J17: https://detail.1688.com/offer/594370725177.html
A18: C14 | B18: 网眼拉链旅行收纳包 | C18: 待补证 | D18: 历史2026-09-11记录：价格原值44（币种未确认）；销量字段677（窗口未核实）；1688历史起价1.13元；MOQ=1；代发原字段=False；未同SKU核验。 | E18: 网眼空包易做尺寸和可见性演示，可与旅行整理共享目标客群。 | F18: 网眼材质、拉链开合；长宽与单套数量待确认 | G18: PH/PHP与30天SKU销量；准确SKU规格及货源报价；包装计费重与运费；本店完整费项、活动、税与汇率；当前现金/未决损失；样品/合规/图权。1.13元历史起价且代发字段false；单件供货、尺寸、包重重新核实。 | H18: A 优先补证：拉链、接缝、网眼耐磨；只售空包；取得主货源、完整成本后再判。 | I18: https://shopee.ph/product/1229056552/25525886150 | J18: https://detail.1688.com/offer/965458977775.html
A19: C15 | B19: 五合一可折叠裤架 | C19: 待补证 | D19: 历史2026-09-11记录：价格原值69（币种未确认）；销量字段3423（窗口未核实）；1688历史起价8.5元；MOQ=1；代发原字段=True；未同SKU核验。 | E19: 折叠裤架有空间利用卖点，但金属杆、体积和关节质量可能不适合轻小跨境。 | F19: 五杆折叠结构；材质、尺寸与包装重待确认 | G19: PH/PHP与30天SKU销量；准确SKU规格及货源报价；包装计费重与运费；本店完整费项、活动、税与汇率；当前现金/未决损失；样品/合规/图权。历史8.5元不是当前SKU报价；包装超过500g即不符合当前门槛。 | H19: B 重量先筛：杆件毛刺、负重与折叠连接处；先排除超过500g；取得主货源、完整成本后再判。 | I19: https://shopee.ph/product/998991383/16595257849 | J19: https://detail.1688.com/offer/732898036456.html
A20: C16 | B20: 双层线材旅行收纳包 | C20: 待补证 | D20: 历史2026-09-11记录：价格原值105（币种未确认）；销量字段327（窗口未核实）；未取得该方向可配对的1688货源证据。 | E20: 双层空包可以表达线材分仓；不含任何带电配件时可研究相邻旅行需求。 | F20: 双层空收纳包；不含电线、电源或其他带电配件 | G20: PH/PHP与30天SKU销量；准确SKU规格及货源报价；包装计费重与运费；本店完整费项、活动、税与汇率；当前现金/未决损失；样品/合规/图权。主货源缺失；图中的充电器等不能默认属于套装，不复制防水宣称。 | H20: A 优先补证：分仓尺寸、拉链、空包净重；不可复制防水宣传；取得主货源、完整成本后再判。 | I20: https://shopee.ph/product/514999607/25305669141
A21: C17 | B21: 便携首饰分格收纳盒 | C21: 待补证 | D21: 历史2026-09-11记录：价格原值136（币种未确认）；销量字段415（窗口未核实）；未取得该方向可配对的1688货源证据。 | E21: 首饰分格有收纳用途，但硬盒体积和内衬质量可能增加成本与售后。 | F21: 耳环、戒指及项链分格；盒体材质与尺寸待确认 | G21: PH/PHP与30天SKU销量；准确SKU规格及货源报价；包装计费重与运费；本店完整费项、活动、税与汇率；当前现金/未决损失；样品/合规/图权。不含首饰，确认盒体尺寸、分隔固定、划伤测试及外观权利。 | H21: B 客单待核：隔断固定、合页/拉链、防刮；不含首饰；取得主货源、完整成本后再判。 | I21: https://shopee.ph/product/38727052/27810028091
A22: C18 | B22: 门背免打孔挂钩架 | C22: 待补证 | D22: 历史2026-09-11记录：价格原值169（币种未确认）；销量字段826（窗口未核实）；未取得该方向可配对的1688货源证据。 | E22: 挂门结构可避免胶粘，但门厚/门缝差异增加不适配风险。 | F22: 挂门式结构；门厚、挂钩数量及材质待确认 | G22: PH/PHP与30天SKU销量；准确SKU规格及货源报价；包装计费重与运费；本店完整费项、活动、税与汇率；当前现金/未决损失；样品/合规/图权。先测门厚范围、承重、防刮和包装重；不是宣称适配全部家庭。 | H22: B 适配先筛：门缝适配、防刮垫、承重、计费重量；不用胶；取得主货源、完整成本后再判。 | I22: https://shopee.ph/product/375375228/28740303369
A23: C19 | B23: 十夹式小件晾晒衣架 | C23: 待补证 | D23: 历史2026-09-11记录：价格原值82（币种未确认）；销量字段387（窗口未核实）；未取得该方向可配对的1688货源证据。 | E23: 小件晾晒用途明确；夹力、弹簧锈蚀和毛刺需要样品证据。 | F23: 标题为单个10夹；实物夹数、尺寸、材质待确认 | G23: PH/PHP与30天SKU销量；准确SKU规格及货源报价；包装计费重与运费；本店完整费项、活动、税与汇率；当前现金/未决损失；样品/合规/图权。每个10夹的准确件数、材质、包重与备用货源都缺。 | H23: B 质量先筛：夹力、夹齿毛刺、弹簧锈蚀和包装后重量；取得主货源、完整成本后再判。 | I23: https://shopee.ph/product/370984810/12536138081
A24: C20 | B24: 悬挂文件分袋整理袋 | C24: 待补证 | D24: 历史2026-09-11记录：价格原值99（币种未确认）；销量字段494（窗口未核实）；未取得该方向可配对的1688货源证据。 | E24: 空文件整理袋可拓展桌面收纳客群；跨不同用途的销量不能合并。 | F24: 布质多袋悬挂结构待实物确认；口袋尺寸适配A4需测量 | G24: PH/PHP与30天SKU销量；准确SKU规格及货源报价；包装计费重与运费；本店完整费项、活动、税与汇率；当前现金/未决损失；样品/合规/图权。A4适配须实际测量，文件袋不能用内衣收纳款销量替代。 | H24: B 规格先筛：仅空整理袋；不附书籍，不沿用内衣收纳不同规格销量；取得主货源、完整成本后再判。 | I24: https://shopee.ph/product/1344635572/43306697837
A25: C21 | B25: 桌面穿线孔盖 | C25: 待补证 | D25: 历史2026-09-11记录：价格原值72（币种未确认）；销量字段166（窗口未核实）；未取得该方向可配对的1688货源证据。 | E25: 孔盖属于被动整理配件，但购买依赖开孔尺寸，错配可能导致高退货。 | F25: 矩形ABS桌面孔盖；开孔尺寸与安装结构待确认 | G25: PH/PHP与30天SKU销量；准确SKU规格及货源报价；包装计费重与运费；本店完整费项、活动、税与汇率；当前现金/未决损失；样品/合规/图权。先验证常见尺寸的真实需求，排除受保护品牌/设计。 | H25: C 暂缓：尺寸匹配投诉风险；每种开孔规格单独验证；只售被动孔盖；取得主货源、完整成本后再判。 | I25: https://shopee.ph/product/1157080722/25286970958
A26: C22 | B26: 编织式线材整理套管 | C26: 待补证 | D26: 历史2026-09-11记录：价格原值313（币种未确认）；销量字段360（窗口未核实）；未取得该方向可配对的1688货源证据。 | E26: 编织套管可以研究被动收束用途，但长度和直径单位容易错配。 | F26: 竞品标题20米PET编织结构；直径、截段及单位待确认 | G26: PH/PHP与30天SKU销量；准确SKU规格及货源报价；包装计费重与运费；本店完整费项、活动、税与汇率；当前现金/未决损失；样品/合规/图权。20米竞品标题不能对应1米采购起价，绝缘/阻燃/防咬宣称须排除。 | H26: C 暂缓：承运/属性边界待核；仅考虑被动整理用途，绝缘阻燃等主张不采纳；取得主货源、完整成本后再判。 | I26: https://shopee.ph/product/969657190/22135470144

Sheet 02_逐项证据门槛
A1: 02 · 逐项证据门槛
A2: 达到数字门槛与证据有效是两件事。未核实、不适用和不通过分别记录；不生成虚假的总体通过率。
A4: ID | B4: 产品 | C4: 维度 | D4: 实际值/已知状态 | E4: 判定门槛 | F4: 符合程度 | G4: 解释及影响 | H4: 证据定位
A5: C01 | B5: 多尺寸拉链洗衣网袋套装 | C5: 数据质量 | D5: 原销量日=1970-01-01; PH查询/THB字典冲突 | E5: PH/PHP与明确30天SKU口径有效 | F5: 待补证 | G5: 不能用于定价、月销量、市场规模或利润事实 | H5: evidence/2026-09-10-candidates.json#/0
A6: C01 | B6: 多尺寸拉链洗衣网袋套装 | C6: 需求 | D6: 相关关键词原始样本20条；有效可比样本0；单条原始销量字段4957 | E6: ≥10可比商品/5店；30天合计≥300件；3店各≥30件 | F6: 待补证 | G6: 原始样本未证同规格和有效窗口，无法比较达标程度 | H6: evidence/2026-09-10-raw-observations.json#/market/1/result/content/0/text→JSON/data/2
A7: C01 | B7: 多尺寸拉链洗衣网袋套装 | C7: 竞争与价格 | D7: 价格原值75，币种未确认；本地/跨境可比组未完成 | E7: CR3≤70%；2跨境店各≥30件；到手价≤跨境中位数110% | F7: 待补证 | G7: 未计算价格分布或集中度，不能把单个畅销链接当入场证据 | H7: evidence/2026-09-10-candidates.json#/0
A8: C01 | B8: 多尺寸拉链洗衣网袋套装 | C8: 趋势与质量 | D8: 暂无可用3期趋势；样品未验 | E8: 同规格3期观察；样品确认差异点与重要质量项 | F8: 待补证 | G8: 拉链开合与机洗测试；套装件数逐件对齐 | H8: evidence/2026-09-10-candidates.json#/0
A9: C01 | B9: 多尺寸拉链洗衣网袋套装 | C9: 1688货源 | D9: 1688历史起价0.6元；MOQ=1；代发原字段=True；未同SKU核验 | E9: 24h内逐SKU报价；可单件代发；MOQ兼容；库存≥10套；备货≤48h | F9: 仅线索 | G9: 比较网眼、拉链包边、尺寸和套装件数，不借竞品品牌。 | H9: evidence/2026-09-10-raw-observations.json#/suppliers/0/result/content/0/text→JSON/data/5
A10: C01 | B10: 多尺寸拉链洗衣网袋套装 | C10: 物流履约 | D10: 包装尺寸/实重/体积重、净运费和各段时长未知 | E10: 计费重≤500g；物流≤收入25%；平台截止前24h缓冲 | F10: 待补证 | G10: 无运费无法算真实采购上限；目测尺寸不作证据 | H10: evidence/2026-09-10-candidates.json#/0
A11: C01 | B11: 多尺寸拉链洗衣网袋套装 | C11: 完全成本 | D11: 利润/利润率/最高采购价/压力利润均未知 | E11: ≥20%且≥15元；组合压力≥0；报价≤采购上限 | F11: 无法计算 | G11: 03和04保留空白，不用公共示例费率补齐实际成本 | H11: 03_逐品成本 / 04_费用明细
A12: C01 | B12: 多尺寸拉链洗衣网袋套装 | C12: 500元与资金 | D12: 测试单量、单品总成本、今日现金及未决损失未知 | E12: 单品累计总成本≤500；全店应急≥5000、月损失≤4000 | F12: 待补证 | G12: 启动20,000元不是今天余额；候选不能独立重复用同一现金 | H12: 05_500元与现金
A13: C01 | B13: 多尺寸拉链洗衣网袋套装 | C13: 合规与权利 | D13: 暂无逐SKU合规/图权/样品通过记录 | E13: 禁限售/认证/承运/品牌外观/图片授权均明确通过 | F13: 待补证 | G13: 普通空收纳用途仅为方向筛选，不等于合规结论；比较网眼、拉链包边、尺寸和套装件数，不借竞品品牌。 | H13: O03/O04；evidence/2026-09-10-candidates.json#/0
A14: C02 | B14: 行李箱衣物分装收纳套装 | C14: 数据质量 | D14: 原销量日=1970-01-01; PH查询/THB字典冲突 | E14: PH/PHP与明确30天SKU口径有效 | F14: 待补证 | G14: 不能用于定价、月销量、市场规模或利润事实 | H14: evidence/2026-09-10-candidates.json#/1
A15: C02 | B15: 行李箱衣物分装收纳套装 | C15: 需求 | D15: 相关关键词原始样本20条；有效可比样本0；单条原始销量字段68 | E15: ≥10可比商品/5店；30天合计≥300件；3店各≥30件 | F15: 待补证 | G15: 原始样本未证同规格和有效窗口，无法比较达标程度 | H15: evidence/2026-09-10-raw-observations.json#/market/3/result/content/0/text→JSON/data/6
... A202: C22 | B202: 编织式线材整理套管 | C202: 合规与权利 | D202: 暂无逐SKU合规/图权/样品通过记录 | E202: 禁限售/认证/承运/品牌外观/图片授权均明确通过 | F202: 待补证 | G202: 普通空收纳用途仅为方向筛选，不等于合规结论；20米竞品标题不能对应1米采购起价，绝缘/阻燃/防咬宣称须排除。 | H202: O03/O04；evidence/2026-09-11-candidates.json#/9

Sheet 03_逐品成本
A1: 03 · 逐品成本
A2: 一个销售单元=确定SKU一单（可以是套装）。成本预测不是已实现利润；仅填写准确报价和04全部费用，缺项不计算。报价观测≤24h另由Skill检查。修改后需重新生成审核结论。
A4: ID | B4: 产品 | C4: 券后商品PHP | D4: 额外补贴PHP | E4: CNY每PHP | F4: SKU采购价CNY | G4: 采购数量/套 | H4: 采购联动附加率 | I4: 样品拍摄等固定测试费 | J4: 测试计划单量 | K4: SKU报价证据 | L4: 报价截止 | M4: 费用口径审核 | N4: 费用完整 | O4: 其他成本CNY | P4: 压力其他成本 | Q4: 商品收入CNY | R4: 采购成本CNY | S4: 单件完全成本 | T4: 预计利润CNY | U4: 预计利润率 | V4: 采购上限CNY | W4: 组合压力利润 | X4: 测试总成本 | Y4: 500元最多测试单量 | Z4: 成本判定
A5: C01 | B5: 多尺寸拉链洗衣网袋套装 | M5: 待核实 | N5: =IF(COUNTIF('04_费用明细'!N5:N22,"完整")=18,"完整","待补证") -> 待补证 | O5: =IF(N5="完整",SUM('04_费用明细'!L5:L22),"") | P5: =IF(N5="完整",SUM('04_费用明细'!M5:M22),"") | Q5: =IF(AND(COUNT(C5:J5)=8,C5>0,D5>=0,E5>0,F5>=0,G5>0,G5=INT(G5),H5>=0,I5>=0,J5>0,J5=INT(J5),K5<>"",ISNUMBER(L5),L5>='00_审核入口'!$F$2,M5="已核实",N5="完整"),ROUND(ROUND((C5+D5)*E5,10),2),"") | R5: =IF(AND(COUNT(C5:J5)=8,C5>0,D5>=0,E5>0,F5>=0,G5>0,G5=INT(G5),H5>=0,I5>=0,J5>0,J5=INT(J5),K5<>"",ISNUMBER(L5),L5>='00_审核入口'!$F$2,M5="已核实",N5="完整"),ROUND(ROUND(F5*G5*(1+H5),10),2),"") | S5: =IF(AND(COUNT(C5:J5)=8,C5>0,D5>=0,E5>0,F5>=0,G5>0,G5=INT(G5),H5>=0,I5>=0,J5>0,J5=INT(J5),K5<>"",ISNUMBER(L5),L5>='00_审核入口'!$F$2,M5="已核实",N5="完整"),R5+O5,"") | T5: =IF(AND(COUNT(C5:J5)=8,C5>0,D5>=0,E5>0,F5>=0,G5>0,G5=INT(G5),H5>=0,I5>=0,J5>0,J5=INT(J5),K5<>"",ISNUMBER(L5),L5>='00_审核入口'!$F$2,M5="已核实",N5="完整"),Q5-S5,"") | U5: =IF(AND(COUNT(C5:J5)=8,C5>0,D5>=0,E5>0,F5>=0,G5>0,G5=INT(G5),H5>=0,I5>=0,J5>0,J5=INT(J5),K5<>"",ISNUMBER(L5),L5>='00_审核入口'!$F$2,M5="已核实",N5="完整"),IF(Q5>0,T5/Q5,""),"") | V5: =IF(AND(COUNT(C5:J5)=8,C5>0,D5>=0,E5>0,F5>=0,G5>0,G5=INT(G5),H5>=0,I5>=0,J5>0,J5=INT(J5),K5<>"",ISNUMBER(L5),L5>='00_审核入口'!$F$2,M5="已核实",N5="完整"),IF(Q5-O5-ROUNDUP(MAX(15,0.2*Q5),2)<0,"无非负可行采购价",ROUNDDOWN((Q5-O5-ROUNDUP(MAX(15,0.2*Q5),2)+0.005-0.0000000001)/(G5*(1+H5)),2)),"") | W5: =IF(AND(COUNT(C5:J5)=8,C5>0,D5>=0,E5>0,F5>=0,G5>0,G5=INT(G5),H5>=0,I5>=0,J5>0,J5=INT(J5),K5<>"",ISNUMBER(L5),L5>='00_审核入口'!$F$2,M5="已核实",N5="完整"),ROUND(ROUND((C5+D5)*E5*0.95,10),2)-ROUND(ROUND(F5*1.1*G5*(1+H5),10),2)-P5,"") | X5: =IF(AND(COUNT(C5:J5)=8,C5>0,D5>=0,E5>0,F5>=0,G5>0,G5=INT(G5),H5>=0,I5>=0,J5>0,J5=INT(J5),K5<>"",ISNUMBER(L5),L5>='00_审核入口'!$F$2,M5="已核实",N5="完整"),ROUND(I5+J5*S5,2),"") | Y5: =IF(AND(COUNT(C5:J5)=8,C5>0,D5>=0,E5>0,F5>=0,G5>0,G5=INT(G5),H5>=0,I5>=0,J5>0,J5=INT(J5),K5<>"",ISNUMBER(L5),L5>='00_审核入口'!$F$2,M5="已核实",N5="完整"),IF(S5>0,MAX(0,INT((500-I5)/S5)),""),"") | Z5: =IF(AND(COUNT(C5:J5)=8,C5>0,D5>=0,E5>0,F5>=0,G5>0,G5=INT(G5),H5>=0,I5>=0,J5>0,J5=INT(J5),K5<>"",ISNUMBER(L5),L5>='00_审核入口'!$F$2,M5="已核实",N5="完整"),IF(AND(T5>=15,U5>=0.2,W5>=0,X5<=500),"成本条件通过","成本条件不通过"),"待补证") -> 待补证
A6: C02 | B6: 行李箱衣物分装收纳套装 | M6: 待核实 | N6: =IF(COUNTIF('04_费用明细'!N23:N40,"完整")=18,"完整","待补证") -> 待补证 | O6: =IF(N6="完整",SUM('04_费用明细'!L23:L40),"") | P6: =IF(N6="完整",SUM('04_费用明细'!M23:M40),"") | Q6: =IF(AND(COUNT(C6:J6)=8,C6>0,D6>=0,E6>0,F6>=0,G6>0,G6=INT(G6),H6>=0,I6>=0,J6>0,J6=INT(J6),K6<>"",ISNUMBER(L6),L6>='00_审核入口'!$F$2,M6="已核实",N6="完整"),ROUND(ROUND((C6+D6)*E6,10),2),"") | R6: =IF(AND(COUNT(C6:J6)=8,C6>0,D6>=0,E6>0,F6>=0,G6>0,G6=INT(G6),H6>=0,I6>=0,J6>0,J6=INT(J6),K6<>"",ISNUMBER(L6),L6>='00_审核入口'!$F$2,M6="已核实",N6="完整"),ROUND(ROUND(F6*G6*(1+H6),10),2),"") | S6: =IF(AND(COUNT(C6:J6)=8,C6>0,D6>=0,E6>0,F6>=0,G6>0,G6=INT(G6),H6>=0,I6>=0,J6>0,J6=INT(J6),K6<>"",ISNUMBER(L6),L6>='00_审核入口'!$F$2,M6="已核实",N6="完整"),R6+O6,"") | T6: =IF(AND(COUNT(C6:J6)=8,C6>0,D6>=0,E6>0,F6>=0,G6>0,G6=INT(G6),H6>=0,I6>=0,J6>0,J6=INT(J6),K6<>"",ISNUMBER(L6),L6>='00_审核入口'!$F$2,M6="已核实",N6="完整"),Q6-S6,"") | U6: =IF(AND(COUNT(C6:J6)=8,C6>0,D6>=0,E6>0,F6>=0,G6>0,G6=INT(G6),H6>=0,I6>=0,J6>0,J6=INT(J6),K6<>"",ISNUMBER(L6),L6>='00_审核入口'!$F$2,M6="已核实",N6="完整"),IF(Q6>0,T6/Q6,""),"") | V6: =IF(AND(COUNT(C6:J6)=8,C6>0,D6>=0,E6>0,F6>=0,G6>0,G6=INT(G6),H6>=0,I6>=0,J6>0,J6=INT(J6),K6<>"",ISNUMBER(L6),L6>='00_审核入口'!$F$2,M6="已核实",N6="完整"),IF(Q6-O6-ROUNDUP(MAX(15,0.2*Q6),2)<0,"无非负可行采购价",ROUNDDOWN((Q6-O6-ROUNDUP(MAX(15,0.2*Q6),2)+0.005-0.0000000001)/(G6*(1+H6)),2)),"") | W6: =IF(AND(COUNT(C6:J6)=8,C6>0,D6>=0,E6>0,F6>=0,G6>0,G6=INT(G6),H6>=0,I6>=0,J6>0,J6=INT(J6),K6<>"",ISNUMBER(L6),L6>='00_审核入口'!$F$2,M6="已核实",N6="完整"),ROUND(ROUND((C6+D6)*E6*0.95,10),2)-ROUND(ROUND(F6*1.1*G6*(1+H6),10),2)-P6,"") | X6: =IF(AND(COUNT(C6:J6)=8,C6>0,D6>=0,E6>0,F6>=0,G6>0,G6=INT(G6),H6>=0,I6>=0,J6>0,J6=INT(J6),K6<>"",ISNUMBER(L6),L6>='00_审核入口'!$F$2,M6="已核实",N6="完整"),ROUND(I6+J6*S6,2),"") | Y6: =IF(AND(COUNT(C6:J6)=8,C6>0,D6>=0,E6>0,F6>=0,G6>0,G6=INT(G6),H6>=0,I6>=0,J6>0,J6=INT(J6),K6<>"",ISNUMBER(L6),L6>='00_审核入口'!$F$2,M6="已核实",N6="完整"),IF(S6>0,MAX(0,INT((500-I6)/S6)),""),"") | Z6: =IF(AND(COUNT(C6:J6)=8,C6>0,D6>=0,E6>0,F6>=0,G6>0,G6=INT(G6),H6>=0,I6>=0,J6>0,J6=INT(J6),K6<>"",ISNUMBER(L6),L6>='00_审核入口'!$F$2,M6="已核实",N6="完整"),IF(AND(T6>=15,U6>=0.2,W6>=0,X6<=500),"成本条件通过","成本条件不通过"),"待补证") -> 待补证
A7: C03 | B7: 挂钩式旅行洗漱收纳包 | M7: 待核实 | N7: =IF(COUNTIF('04_费用明细'!N41:N58,"完整")=18,"完整","待补证") -> 待补证 | O7: =IF(N7="完整",SUM('04_费用明细'!L41:L58),"") | P7: =IF(N7="完整",SUM('04_费用明细'!M41:M58),"") | Q7: =IF(AND(COUNT(C7:J7)=8,C7>0,D7>=0,E7>0,F7>=0,G7>0,G7=INT(G7),H7>=0,I7>=0,J7>0,J7=INT(J7),K7<>"",ISNUMBER(L7),L7>='00_审核入口'!$F$2,M7="已核实",N7="完整"),ROUND(ROUND((C7+D7)*E7,10),2),"") | R7: =IF(AND(COUNT(C7:J7)=8,C7>0,D7>=0,E7>0,F7>=0,G7>0,G7=INT(G7),H7>=0,I7>=0,J7>0,J7=INT(J7),K7<>"",ISNUMBER(L7),L7>='00_审核入口'!$F$2,M7="已核实",N7="完整"),ROUND(ROUND(F7*G7*(1+H7),10),2),"") | S7: =IF(AND(COUNT(C7:J7)=8,C7>0,D7>=0,E7>0,F7>=0,G7>0,G7=INT(G7),H7>=0,I7>=0,J7>0,J7=INT(J7),K7<>"",ISNUMBER(L7),L7>='00_审核入口'!$F$2,M7="已核实",N7="完整"),R7+O7,"") | T7: =IF(AND(COUNT(C7:J7)=8,C7>0,D7>=0,E7>0,F7>=0,G7>0,G7=INT(G7),H7>=0,I7>=0,J7>0,J7=INT(J7),K7<>"",ISNUMBER(L7),L7>='00_审核入口'!$F$2,M7="已核实",N7="完整"),Q7-S7,"") | U7: =IF(AND(COUNT(C7:J7)=8,C7>0,D7>=0,E7>0,F7>=0,G7>0,G7=INT(G7),H7>=0,I7>=0,J7>0,J7=INT(J7),K7<>"",ISNUMBER(L7),L7>='00_审核入口'!$F$2,M7="已核实",N7="完整"),IF(Q7>0,T7/Q7,""),"") | V7: =IF(AND(COUNT(C7:J7)=8,C7>0,D7>=0,E7>0,F7>=0,G7>0,G7=INT(G7),H7>=0,I7>=0,J7>0,J7=INT(J7),K7<>"",ISNUMBER(L7),L7>='00_审核入口'!$F$2,M7="已核实",N7="完整"),IF(Q7-O7-ROUNDUP(MAX(15,0.2*Q7),2)<0,"无非负可行采购价",ROUNDDOWN((Q7-O7-ROUNDUP(MAX(15,0.2*Q7),2)+0.005-0.0000000001)/(G7*(1+H7)),2)),"") | W7: =IF(AND(COUNT(C7:J7)=8,C7>0,D7>=0,E7>0,F7>=0,G7>0,G7=INT(G7),H7>=0,I7>=0,J7>0,J7=INT(J7),K7<>"",ISNUMBER(L7),L7>='00_审核入口'!$F$2,M7="已核实",N7="完整"),ROUND(ROUND((C7+D7)*E7*0.95,10),2)-ROUND(ROUND(F7*1.1*G7*(1+H7),10),2)-P7,"") | X7: =IF(AND(COUNT(C7:J7)=8,C7>0,D7>=0,E7>0,F7>=0,G7>0,G7=INT(G7),H7>=0,I7>=0,J7>0,J7=INT(J7),K7<>"",ISNUMBER(L7),L7>='00_审核入口'!$F$2,M7="已核实",N7="完整"),ROUND(I7+J7*S7,2),"") | Y7: =IF(AND(COUNT(C7:J7)=8,C7>0,D7>=0,E7>0,F7>=0,G7>0,G7=INT(G7),H7>=0,I7>=0,J7>0,J7=INT(J7),K7<>"",ISNUMBER(L7),L7>='00_审核入口'!$F$2,M7="已核实",N7="完整"),IF(S7>0,MAX(0,INT((500-I7)/S7)),""),"") | Z7: =IF(AND(COUNT(C7:J7)=8,C7>0,D7>=0,E7>0,F7>=0,G7>0,G7=INT(G7),H7>=0,I7>=0,J7>0,J7=INT(J7),K7<>"",ISNUMBER(L7),L7>='00_审核入口'!$F$2,M7="已核实",N7="完整"),IF(AND(T7>=15,U7>=0.2,W7>=0,X7<=500),"成本条件通过","成本条件不通过"),"待补证") -> 待补证
A8: C04 | B8: 抽绳鞋子防尘收纳袋 | M8: 待核实 | N8: =IF(COUNTIF('04_费用明细'!N59:N76,"完整")=18,"完整","待补证") -> 待补证 | O8: =IF(N8="完整",SUM('04_费用明细'!L59:L76),"") | P8: =IF(N8="完整",SUM('04_费用明细'!M59:M76),"") | Q8: =IF(AND(COUNT(C8:J8)=8,C8>0,D8>=0,E8>0,F8>=0,G8>0,G8=INT(G8),H8>=0,I8>=0,J8>0,J8=INT(J8),K8<>"",ISNUMBER(L8),L8>='00_审核入口'!$F$2,M8="已核实",N8="完整"),ROUND(ROUND((C8+D8)*E8,10),2),"") | R8: =IF(AND(COUNT(C8:J8)=8,C8>0,D8>=0,E8>0,F8>=0,G8>0,G8=INT(G8),H8>=0,I8>=0,J8>0,J8=INT(J8),K8<>"",ISNUMBER(L8),L8>='00_审核入口'!$F$2,M8="已核实",N8="完整"),ROUND(ROUND(F8*G8*(1+H8),10),2),"") | S8: =IF(AND(COUNT(C8:J8)=8,C8>0,D8>=0,E8>0,F8>=0,G8>0,G8=INT(G8),H8>=0,I8>=0,J8>0,J8=INT(J8),K8<>"",ISNUMBER(L8),L8>='00_审核入口'!$F$2,M8="已核实",N8="完整"),R8+O8,"") | T8: =IF(AND(COUNT(C8:J8)=8,C8>0,D8>=0,E8>0,F8>=0,G8>0,G8=INT(G8),H8>=0,I8>=0,J8>0,J8=INT(J8),K8<>"",ISNUMBER(L8),L8>='00_审核入口'!$F$2,M8="已核实",N8="完整"),Q8-S8,"") | U8: =IF(AND(COUNT(C8:J8)=8,C8>0,D8>=0,E8>0,F8>=0,G8>0,G8=INT(G8),H8>=0,I8>=0,J8>0,J8=INT(J8),K8<>"",ISNUMBER(L8),L8>='00_审核入口'!$F$2,M8="已核实",N8="完整"),IF(Q8>0,T8/Q8,""),"") | V8: =IF(AND(COUNT(C8:J8)=8,C8>0,D8>=0,E8>0,F8>=0,G8>0,G8=INT(G8),H8>=0,I8>=0,J8>0,J8=INT(J8),K8<>"",ISNUMBER(L8),L8>='00_审核入口'!$F$2,M8="已核实",N8="完整"),IF(Q8-O8-ROUNDUP(MAX(15,0.2*Q8),2)<0,"无非负可行采购价",ROUNDDOWN((Q8-O8-ROUNDUP(MAX(15,0.2*Q8),2)+0.005-0.0000000001)/(G8*(1+H8)),2)),"") | W8: =IF(AND(COUNT(C8:J8)=8,C8>0,D8>=0,E8>0,F8>=0,G8>0,G8=INT(G8),H8>=0,I8>=0,J8>0,J8=INT(J8),K8<>"",ISNUMBER(L8),L8>='00_审核入口'!$F$2,M8="已核实",N8="完整"),ROUND(ROUND((C8+D8)*E8*0.95,10),2)-ROUND(ROUND(F8*1.1*G8*(1+H8),10),2)-P8,"") | X8: =IF(AND(COUNT(C8:J8)=8,C8>0,D8>=0,E8>0,F8>=0,G8>0,G8=INT(G8),H8>=0,I8>=0,J8>0,J8=INT(J8),K8<>"",ISNUMBER(L8),L8>='00_审核入口'!$F$2,M8="已核实",N8="完整"),ROUND(I8+J8*S8,2),"") | Y8: =IF(AND(COUNT(C8:J8)=8,C8>0,D8>=0,E8>0,F8>=0,G8>0,G8=INT(G8),H8>=0,I8>=0,J8>0,J8=INT(J8),K8<>"",ISNUMBER(L8),L8>='00_审核入口'!$F$2,M8="已核实",N8="完整"),IF(S8>0,MAX(0,INT((500-I8)/S8)),""),"") | Z8: =IF(AND(COUNT(C8:J8)=8,C8>0,D8>=0,E8>0,F8>=0,G8>0,G8=INT(G8),H8>=0,I8>=0,J8>0,J8=INT(J8),K8<>"",ISNUMBER(L8),L8>='00_审核入口'!$F$2,M8="已核实",N8="完整"),IF(AND(T8>=15,U8>=0.2,W8>=0,X8<=500),"成本条件通过","成本条件不通过"),"待补证") -> 待补证
A9: C05 | B9: 衣柜悬挂手袋收纳袋 | M9: 待核实 | N9: =IF(COUNTIF('04_费用明细'!N77:N94,"完整")=18,"完整","待补证") -> 待补证 | O9: =IF(N9="完整",SUM('04_费用明细'!L77:L94),"") | P9: =IF(N9="完整",SUM('04_费用明细'!M77:M94),"") | Q9: =IF(AND(COUNT(C9:J9)=8,C9>0,D9>=0,E9>0,F9>=0,G9>0,G9=INT(G9),H9>=0,I9>=0,J9>0,J9=INT(J9),K9<>"",ISNUMBER(L9),L9>='00_审核入口'!$F$2,M9="已核实",N9="完整"),ROUND(ROUND((C9+D9)*E9,10),2),"") | R9: =IF(AND(COUNT(C9:J9)=8,C9>0,D9>=0,E9>0,F9>=0,G9>0,G9=INT(G9),H9>=0,I9>=0,J9>0,J9=INT(J9),K9<>"",ISNUMBER(L9),L9>='00_审核入口'!$F$2,M9="已核实",N9="完整"),ROUND(ROUND(F9*G9*(1+H9),10),2),"") | S9: =IF(AND(COUNT(C9:J9)=8,C9>0,D9>=0,E9>0,F9>=0,G9>0,G9=INT(G9),H9>=0,I9>=0,J9>0,J9=INT(J9),K9<>"",ISNUMBER(L9),L9>='00_审核入口'!$F$2,M9="已核实",N9="完整"),R9+O9,"") | T9: =IF(AND(COUNT(C9:J9)=8,C9>0,D9>=0,E9>0,F9>=0,G9>0,G9=INT(G9),H9>=0,I9>=0,J9>0,J9=INT(J9),K9<>"",ISNUMBER(L9),L9>='00_审核入口'!$F$2,M9="已核实",N9="完整"),Q9-S9,"") | U9: =IF(AND(COUNT(C9:J9)=8,C9>0,D9>=0,E9>0,F9>=0,G9>0,G9=INT(G9),H9>=0,I9>=0,J9>0,J9=INT(J9),K9<>"",ISNUMBER(L9),L9>='00_审核入口'!$F$2,M9="已核实",N9="完整"),IF(Q9>0,T9/Q9,""),"") | V9: =IF(AND(COUNT(C9:J9)=8,C9>0,D9>=0,E9>0,F9>=0,G9>0,G9=INT(G9),H9>=0,I9>=0,J9>0,J9=INT(J9),K9<>"",ISNUMBER(L9),L9>='00_审核入口'!$F$2,M9="已核实",N9="完整"),IF(Q9-O9-ROUNDUP(MAX(15,0.2*Q9),2)<0,"无非负可行采购价",ROUNDDOWN((Q9-O9-ROUNDUP(MAX(15,0.2*Q9),2)+0.005-0.0000000001)/(G9*(1+H9)),2)),"") | W9: =IF(AND(COUNT(C9:J9)=8,C9>0,D9>=0,E9>0,F9>=0,G9>0,G9=INT(G9),H9>=0,I9>=0,J9>0,J9=INT(J9),K9<>"",ISNUMBER(L9),L9>='00_审核入口'!$F$2,M9="已核实",N9="完整"),ROUND(ROUND((C9+D9)*E9*0.95,10),2)-ROUND(ROUND(F9*1.1*G9*(1+H9),10),2)-P9,"") | X9: =IF(AND(COUNT(C9:J9)=8,C9>0,D9>=0,E9>0,F9>=0,G9>0,G9=INT(G9),H9>=0,I9>=0,J9>0,J9=INT(J9),K9<>"",ISNUMBER(L9),L9>='00_审核入口'!$F$2,M9="已核实",N9="完整"),ROUND(I9+J9*S9,2),"") | Y9: =IF(AND(COUNT(C9:J9)=8,C9>0,D9>=0,E9>0,F9>=0,G9>0,G9=INT(G9),H9>=0,I9>=0,J9>0,J9=INT(J9),K9<>"",ISNUMBER(L9),L9>='00_审核入口'!$F$2,M9="已核实",N9="完整"),IF(S9>0,MAX(0,INT((500-I9)/S9)),""),"") | Z9: =IF(AND(COUNT(C9:J9)=8,C9>0,D9>=0,E9>0,F9>=0,G9>0,G9=INT(G9),H9>=0,I9>=0,J9>0,J9=INT(J9),K9<>"",ISNUMBER(L9),L9>='00_审核入口'!$F$2,M9="已核实",N9="完整"),IF(AND(T9>=15,U9>=0.2,W9>=0,X9<=500),"成本条件通过","成本条件不通过"),"待补证") -> 待补证
A10: C06 | B10: 发夹与发圈挂式整理架 | M10: 待核实 | N10: =IF(COUNTIF('04_费用明细'!N95:N112,"完整")=18,"完整","待补证") -> 待补证 | O10: =IF(N10="完整",SUM('04_费用明细'!L95:L112),"") | P10: =IF(N10="完整",SUM('04_费用明细'!M95:M112),"") | Q10: =IF(AND(COUNT(C10:J10)=8,C10>0,D10>=0,E10>0,F10>=0,G10>0,G10=INT(G10),H10>=0,I10>=0,J10>0,J10=INT(J10),K10<>"",ISNUMBER(L10),L10>='00_审核入口'!$F$2,M10="已核实",N10="完整"),ROUND(ROUND((C10+D10)*E10,10),2),"") | R10: =IF(AND(COUNT(C10:J10)=8,C10>0,D10>=0,E10>0,F10>=0,G10>0,G10=INT(G10),H10>=0,I10>=0,J10>0,J10=INT(J10),K10<>"",ISNUMBER(L10),L10>='00_审核入口'!$F$2,M10="已核实",N10="完整"),ROUND(ROUND(F10*G10*(1+H10),10),2),"") | S10: =IF(AND(COUNT(C10:J10)=8,C10>0,D10>=0,E10>0,F10>=0,G10>0,G10=INT(G10),H10>=0,I10>=0,J10>0,J10=INT(J10),K10<>"",ISNUMBER(L10),L10>='00_审核入口'!$F$2,M10="已核实",N10="完整"),R10+O10,"") | T10: =IF(AND(COUNT(C10:J10)=8,C10>0,D10>=0,E10>0,F10>=0,G10>0,G10=INT(G10),H10>=0,I10>=0,J10>0,J10=INT(J10),K10<>"",ISNUMBER(L10),L10>='00_审核入口'!$F$2,M10="已核实",N10="完整"),Q10-S10,"") | U10: =IF(AND(COUNT(C10:J10)=8,C10>0,D10>=0,E10>0,F10>=0,G10>0,G10=INT(G10),H10>=0,I10>=0,J10>0,J10=INT(J10),K10<>"",ISNUMBER(L10),L10>='00_审核入口'!$F$2,M10="已核实",N10="完整"),IF(Q10>0,T10/Q10,""),"") | V10: =IF(AND(COUNT(C10:J10)=8,C10>0,D10>=0,E10>0,F10>=0,G10>0,G10=INT(G10),H10>=0,I10>=0,J10>0,J10=INT(J10),K10<>"",ISNUMBER(L10),L10>='00_审核入口'!$F$2,M10="已核实",N10="完整"),IF(Q10-O10-ROUNDUP(MAX(15,0.2*Q10),2)<0,"无非负可行采购价",ROUNDDOWN((Q10-O10-ROUNDUP(MAX(15,0.2*Q10),2)+0.005-0.0000000001)/(G10*(1+H10)),2)),"") | W10: =IF(AND(COUNT(C10:J10)=8,C10>0,D10>=0,E10>0,F10>=0,G10>0,G10=INT(G10),H10>=0,I10>=0,J10>0,J10=INT(J10),K10<>"",ISNUMBER(L10),L10>='00_审核入口'!$F$2,M10="已核实",N10="完整"),ROUND(ROUND((C10+D10)*E10*0.95,10),2)-ROUND(ROUND(F10*1.1*G10*(1+H10),10),2)-P10,"") | X10: =IF(AND(COUNT(C10:J10)=8,C10>0,D10>=0,E10>0,F10>=0,G10>0,G10=INT(G10),H10>=0,I10>=0,J10>0,J10=INT(J10),K10<>"",ISNUMBER(L10),L10>='00_审核入口'!$F$2,M10="已核实",N10="完整"),ROUND(I10+J10*S10,2),"") | Y10: =IF(AND(COUNT(C10:J10)=8,C10>0,D10>=0,E10>0,F10>=0,G10>0,G10=INT(G10),H10>=0,I10>=0,J10>0,J10=INT(J10),K10<>"",ISNUMBER(L10),L10>='00_审核入口'!$F$2,M10="已核实",N10="完整"),IF(S10>0,MAX(0,INT((500-I10)/S10)),""),"") | Z10: =IF(AND(COUNT(C10:J10)=8,C10>0,D10>=0,E10>0,F10>=0,G10>0,G10=INT(G10),H10>=0,I10>=0,J10>0,J10=INT(J10),K10<>"",ISNUMBER(L10),L10>='00_审核入口'!$F$2,M10="已核实",N10="完整"),IF(AND(T10>=15,U10>=0.2,W10>=0,X10<=500),"成本条件通过","成本条件不通过"),"待补证") -> 待补证
A11: C07 | B11: 自粘桌面理线夹套装 | M11: 待核实 | N11: =IF(COUNTIF('04_费用明细'!N113:N130,"完整")=18,"完整","待补证") -> 待补证 | O11: =IF(N11="完整",SUM('04_费用明细'!L113:L130),"") | P11: =IF(N11="完整",SUM('04_费用明细'!M113:M130),"") | Q11: =IF(AND(COUNT(C11:J11)=8,C11>0,D11>=0,E11>0,F11>=0,G11>0,G11=INT(G11),H11>=0,I11>=0,J11>0,J11=INT(J11),K11<>"",ISNUMBER(L11),L11>='00_审核入口'!$F$2,M11="已核实",N11="完整"),ROUND(ROUND((C11+D11)*E11,10),2),"") | R11: =IF(AND(COUNT(C11:J11)=8,C11>0,D11>=0,E11>0,F11>=0,G11>0,G11=INT(G11),H11>=0,I11>=0,J11>0,J11=INT(J11),K11<>"",ISNUMBER(L11),L11>='00_审核入口'!$F$2,M11="已核实",N11="完整"),ROUND(ROUND(F11*G11*(1+H11),10),2),"") | S11: =IF(AND(COUNT(C11:J11)=8,C11>0,D11>=0,E11>0,F11>=0,G11>0,G11=INT(G11),H11>=0,I11>=0,J11>0,J11=INT(J11),K11<>"",ISNUMBER(L11),L11>='00_审核入口'!$F$2,M11="已核实",N11="完整"),R11+O11,"") | T11: =IF(AND(COUNT(C11:J11)=8,C11>0,D11>=0,E11>0,F11>=0,G11>0,G11=INT(G11),H11>=0,I11>=0,J11>0,J11=INT(J11),K11<>"",ISNUMBER(L11),L11>='00_审核入口'!$F$2,M11="已核实",N11="完整"),Q11-S11,"") | U11: =IF(AND(COUNT(C11:J11)=8,C11>0,D11>=0,E11>0,F11>=0,G11>0,G11=INT(G11),H11>=0,I11>=0,J11>0,J11=INT(J11),K11<>"",ISNUMBER(L11),L11>='00_审核入口'!$F$2,M11="已核实",N11="完整"),IF(Q11>0,T11/Q11,""),"") | V11: =IF(AND(COUNT(C11:J11)=8,C11>0,D11>=0,E11>0,F11>=0,G11>0,G11=INT(G11),H11>=0,I11>=0,J11>0,J11=INT(J11),K11<>"",ISNUMBER(L11),L11>='00_审核入口'!$F$2,M11="已核实",N11="完整"),IF(Q11-O11-ROUNDUP(MAX(15,0.2*Q11),2)<0,"无非负可行采购价",ROUNDDOWN((Q11-O11-ROUNDUP(MAX(15,0.2*Q11),2)+0.005-0.0000000001)/(G11*(1+H11)),2)),"") | W11: =IF(AND(COUNT(C11:J11)=8,C11>0,D11>=0,E11>0,F11>=0,G11>0,G11=INT(G11),H11>=0,I11>=0,J11>0,J11=INT(J11),K11<>"",ISNUMBER(L11),L11>='00_审核入口'!$F$2,M11="已核实",N11="完整"),ROUND(ROUND((C11+D11)*E11*0.95,10),2)-ROUND(ROUND(F11*1.1*G11*(1+H11),10),2)-P11,"") | X11: =IF(AND(COUNT(C11:J11)=8,C11>0,D11>=0,E11>0,F11>=0,G11>0,G11=INT(G11),H11>=0,I11>=0,J11>0,J11=INT(J11),K11<>"",ISNUMBER(L11),L11>='00_审核入口'!$F$2,M11="已核实",N11="完整"),ROUND(I11+J11*S11,2),"") | Y11: =IF(AND(COUNT(C11:J11)=8,C11>0,D11>=0,E11>0,F11>=0,G11>0,G11=INT(G11),H11>=0,I11>=0,J11>0,J11=INT(J11),K11<>"",ISNUMBER(L11),L11>='00_审核入口'!$F$2,M11="已核实",N11="完整"),IF(S11>0,MAX(0,INT((500-I11)/S11)),""),"") | Z11: =IF(AND(COUNT(C11:J11)=8,C11>0,D11>=0,E11>0,F11>=0,G11>0,G11=INT(G11),H11>=0,I11>=0,J11>0,J11=INT(J11),K11<>"",ISNUMBER(L11),L11>='00_审核入口'!$F$2,M11="已核实",N11="完整"),IF(AND(T11>=15,U11>=0.2,W11>=0,X11<=500),"成本条件通过","成本条件不通过"),"待补证") -> 待补证
A12: C08 | B12: 厨房电器电源线绕线器 | M12: 待核实 | N12: =IF(COUNTIF('04_费用明细'!N131:N148,"完整")=18,"完整","待补证") -> 待补证 | O12: =IF(N12="完整",SUM('04_费用明细'!L131:L148),"") | P12: =IF(N12="完整",SUM('04_费用明细'!M131:M148),"") | Q12: =IF(AND(COUNT(C12:J12)=8,C12>0,D12>=0,E12>0,F12>=0,G12>0,G12=INT(G12),H12>=0,I12>=0,J12>0,J12=INT(J12),K12<>"",ISNUMBER(L12),L12>='00_审核入口'!$F$2,M12="已核实",N12="完整"),ROUND(ROUND((C12+D12)*E12,10),2),"") | R12: =IF(AND(COUNT(C12:J12)=8,C12>0,D12>=0,E12>0,F12>=0,G12>0,G12=INT(G12),H12>=0,I12>=0,J12>0,J12=INT(J12),K12<>"",ISNUMBER(L12),L12>='00_审核入口'!$F$2,M12="已核实",N12="完整"),ROUND(ROUND(F12*G12*(1+H12),10),2),"") | S12: =IF(AND(COUNT(C12:J12)=8,C12>0,D12>=0,E12>0,F12>=0,G12>0,G12=INT(G12),H12>=0,I12>=0,J12>0,J12=INT(J12),K12<>"",ISNUMBER(L12),L12>='00_审核入口'!$F$2,M12="已核实",N12="完整"),R12+O12,"") | T12: =IF(AND(COUNT(C12:J12)=8,C12>0,D12>=0,E12>0,F12>=0,G12>0,G12=INT(G12),H12>=0,I12>=0,J12>0,J12=INT(J12),K12<>"",ISNUMBER(L12),L12>='00_审核入口'!$F$2,M12="已核实",N12="完整"),Q12-S12,"") | U12: =IF(AND(COUNT(C12:J12)=8,C12>0,D12>=0,E12>0,F12>=0,G12>0,G12=INT(G12),H12>=0,I12>=0,J12>0,J12=INT(J12),K12<>"",ISNUMBER(L12),L12>='00_审核入口'!$F$2,M12="已核实",N12="完整"),IF(Q12>0,T12/Q12,""),"") | V12: =IF(AND(COUNT(C12:J12)=8,C12>0,D12>=0,E12>0,F12>=0,G12>0,G12=INT(G12),H12>=0,I12>=0,J12>0,J12=INT(J12),K12<>"",ISNUMBER(L12),L12>='00_审核入口'!$F$2,M12="已核实",N12="完整"),IF(Q12-O12-ROUNDUP(MAX(15,0.2*Q12),2)<0,"无非负可行采购价",ROUNDDOWN((Q12-O12-ROUNDUP(MAX(15,0.2*Q12),2)+0.005-0.0000000001)/(G12*(1+H12)),2)),"") | W12: =IF(AND(COUNT(C12:J12)=8,C12>0,D12>=0,E12>0,F12>=0,G12>0,G12=INT(G12),H12>=0,I12>=0,J12>0,J12=INT(J12),K12<>"",ISNUMBER(L12),L12>='00_审核入口'!$F$2,M12="已核实",N12="完整"),ROUND(ROUND((C12+D12)*E12*0.95,10),2)-ROUND(ROUND(F12*1.1*G12*(1+H12),10),2)-P12,"") | X12: =IF(AND(COUNT(C12:J12)=8,C12>0,D12>=0,E12>0,F12>=0,G12>0,G12=INT(G12),H12>=0,I12>=0,J12>0,J12=INT(J12),K12<>"",ISNUMBER(L12),L12>='00_审核入口'!$F$2,M12="已核实",N12="完整"),ROUND(I12+J12*S12,2),"") | Y12: =IF(AND(COUNT(C12:J12)=8,C12>0,D12>=0,E12>0,F12>=0,G12>0,G12=INT(G12),H12>=0,I12>=0,J12>0,J12=INT(J12),K12<>"",ISNUMBER(L12),L12>='00_审核入口'!$F$2,M12="已核实",N12="完整"),IF(S12>0,MAX(0,INT((500-I12)/S12)),""),"") | Z12: =IF(AND(COUNT(C12:J12)=8,C12>0,D12>=0,E12>0,F12>=0,G12>0,G12=INT(G12),H12>=0,I12>=0,J12>0,J12=INT(J12),K12<>"",ISNUMBER(L12),L12>='00_审核入口'!$F$2,M12="已核实",N12="完整"),IF(AND(T12>=15,U12>=0.2,W12>=0,X12<=500),"成本条件通过","成本条件不通过"),"待补证") -> 待补证
A13: C09 | B13: 螺旋式线材整理保护管 | M13: 待核实 | N13: =IF(COUNTIF('04_费用明细'!N149:N166,"完整")=18,"完整","待补证") -> 待补证 | O13: =IF(N13="完整",SUM('04_费用明细'!L149:L166),"") | P13: =IF(N13="完整",SUM('04_费用明细'!M149:M166),"") | Q13: =IF(AND(COUNT(C13:J13)=8,C13>0,D13>=0,E13>0,F13>=0,G13>0,G13=INT(G13),H13>=0,I13>=0,J13>0,J13=INT(J13),K13<>"",ISNUMBER(L13),L13>='00_审核入口'!$F$2,M13="已核实",N13="完整"),ROUND(ROUND((C13+D13)*E13,10),2),"") | R13: =IF(AND(COUNT(C13:J13)=8,C13>0,D13>=0,E13>0,F13>=0,G13>0,G13=INT(G13),H13>=0,I13>=0,J13>0,J13=INT(J13),K13<>"",ISNUMBER(L13),L13>='00_审核入口'!$F$2,M13="已核实",N13="完整"),ROUND(ROUND(F13*G13*(1+H13),10),2),"") | S13: =IF(AND(COUNT(C13:J13)=8,C13>0,D13>=0,E13>0,F13>=0,G13>0,G13=INT(G13),H13>=0,I13>=0,J13>0,J13=INT(J13),K13<>"",ISNUMBER(L13),L13>='00_审核入口'!$F$2,M13="已核实",N13="完整"),R13+O13,"") | T13: =IF(AND(COUNT(C13:J13)=8,C13>0,D13>=0,E13>0,F13>=0,G13>0,G13=INT(G13),H13>=0,I13>=0,J13>0,J13=INT(J13),K13<>"",ISNUMBER(L13),L13>='00_审核入口'!$F$2,M13="已核实",N13="完整"),Q13-S13,"") | U13: =IF(AND(COUNT(C13:J13)=8,C13>0,D13>=0,E13>0,F13>=0,G13>0,G13=INT(G13),H13>=0,I13>=0,J13>0,J13=INT(J13),K13<>"",ISNUMBER(L13),L13>='00_审核入口'!$F$2,M13="已核实",N13="完整"),IF(Q13>0,T13/Q13,""),"") | V13: =IF(AND(COUNT(C13:J13)=8,C13>0,D13>=0,E13>0,F13>=0,G13>0,G13=INT(G13),H13>=0,I13>=0,J13>0,J13=INT(J13),K13<>"",ISNUMBER(L13),L13>='00_审核入口'!$F$2,M13="已核实",N13="完整"),IF(Q13-O13-ROUNDUP(MAX(15,0.2*Q13),2)<0,"无非负可行采购价",ROUNDDOWN((Q13-O13-ROUNDUP(MAX(15,0.2*Q13),2)+0.005-0.0000000001)/(G13*(1+H13)),2)),"") | W13: =IF(AND(COUNT(C13:J13)=8,C13>0,D13>=0,E13>0,F13>=0,G13>0,G13=INT(G13),H13>=0,I13>=0,J13>0,J13=INT(J13),K13<>"",ISNUMBER(L13),L13>='00_审核入口'!$F$2,M13="已核实",N13="完整"),ROUND(ROUND((C13+D13)*E13*0.95,10),2)-ROUND(ROUND(F13*1.1*G13*(1+H13),10),2)-P13,"") | X13: =IF(AND(COUNT(C13:J13)=8,C13>0,D13>=0,E13>0,F13>=0,G13>0,G13=INT(G13),H13>=0,I13>=0,J13>0,J13=INT(J13),K13<>"",ISNUMBER(L13),L13>='00_审核入口'!$F$2,M13="已核实",N13="完整"),ROUND(I13+J13*S13,2),"") | Y13: =IF(AND(COUNT(C13:J13)=8,C13>0,D13>=0,E13>0,F13>=0,G13>0,G13=INT(G13),H13>=0,I13>=0,J13>0,J13=INT(J13),K13<>"",ISNUMBER(L13),L13>='00_审核入口'!$F$2,M13="已核实",N13="完整"),IF(S13>0,MAX(0,INT((500-I13)/S13)),""),"") | Z13: =IF(AND(COUNT(C13:J13)=8,C13>0,D13>=0,E13>0,F13>=0,G13>0,G13=INT(G13),H13>=0,I13>=0,J13>0,J13=INT(J13),K13<>"",ISNUMBER(L13),L13>='00_审核入口'!$F$2,M13="已核实",N13="完整"),IF(AND(T13>=15,U13>=0.2,W13>=0,X13<=500),"成本条件通过","成本条件不通过"),"待补证") -> 待补证
A14: C10 | B14: 衣物粘毛滚筒加替换芯 | M14: 待核实 | N14: =IF(COUNTIF('04_费用明细'!N167:N184,"完整")=18,"完整","待补证") -> 待补证 | O14: =IF(N14="完整",SUM('04_费用明细'!L167:L184),"") | P14: =IF(N14="完整",SUM('04_费用明细'!M167:M184),"") | Q14: =IF(AND(COUNT(C14:J14)=8,C14>0,D14>=0,E14>0,F14>=0,G14>0,G14=INT(G14),H14>=0,I14>=0,J14>0,J14=INT(J14),K14<>"",ISNUMBER(L14),L14>='00_审核入口'!$F$2,M14="已核实",N14="完整"),ROUND(ROUND((C14+D14)*E14,10),2),"") | R14: =IF(AND(COUNT(C14:J14)=8,C14>0,D14>=0,E14>0,F14>=0,G14>0,G14=INT(G14),H14>=0,I14>=0,J14>0,J14=INT(J14),K14<>"",ISNUMBER(L14),L14>='00_审核入口'!$F$2,M14="已核实",N14="完整"),ROUND(ROUND(F14*G14*(1+H14),10),2),"") | S14: =IF(AND(COUNT(C14:J14)=8,C14>0,D14>=0,E14>0,F14>=0,G14>0,G14=INT(G14),H14>=0,I14>=0,J14>0,J14=INT(J14),K14<>"",ISNUMBER(L14),L14>='00_审核入口'!$F$2,M14="已核实",N14="完整"),R14+O14,"") | T14: =IF(AND(COUNT(C14:J14)=8,C14>0,D14>=0,E14>0,F14>=0,G14>0,G14=INT(G14),H14>=0,I14>=0,J14>0,J14=INT(J14),K14<>"",ISNUMBER(L14),L14>='00_审核入口'!$F$2,M14="已核实",N14="完整"),Q14-S14,"") | U14: =IF(AND(COUNT(C14:J14)=8,C14>0,D14>=0,E14>0,F14>=0,G14>0,G14=INT(G14),H14>=0,I14>=0,J14>0,J14=INT(J14),K14<>"",ISNUMBER(L14),L14>='00_审核入口'!$F$2,M14="已核实",N14="完整"),IF(Q14>0,T14/Q14,""),"") | V14: =IF(AND(COUNT(C14:J14)=8,C14>0,D14>=0,E14>0,F14>=0,G14>0,G14=INT(G14),H14>=0,I14>=0,J14>0,J14=INT(J14),K14<>"",ISNUMBER(L14),L14>='00_审核入口'!$F$2,M14="已核实",N14="完整"),IF(Q14-O14-ROUNDUP(MAX(15,0.2*Q14),2)<0,"无非负可行采购价",ROUNDDOWN((Q14-O14-ROUNDUP(MAX(15,0.2*Q14),2)+0.005-0.0000000001)/(G14*(1+H14)),2)),"") | W14: =IF(AND(COUNT(C14:J14)=8,C14>0,D14>=0,E14>0,F14>=0,G14>0,G14=INT(G14),H14>=0,I14>=0,J14>0,J14=INT(J14),K14<>"",ISNUMBER(L14),L14>='00_审核入口'!$F$2,M14="已核实",N14="完整"),ROUND(ROUND((C14+D14)*E14*0.95,10),2)-ROUND(ROUND(F14*1.1*G14*(1+H14),10),2)-P14,"") | X14: =IF(AND(COUNT(C14:J14)=8,C14>0,D14>=0,E14>0,F14>=0,G14>0,G14=INT(G14),H14>=0,I14>=0,J14>0,J14=INT(J14),K14<>"",ISNUMBER(L14),L14>='00_审核入口'!$F$2,M14="已核实",N14="完整"),ROUND(I14+J14*S14,2),"") | Y14: =IF(AND(COUNT(C14:J14)=8,C14>0,D14>=0,E14>0,F14>=0,G14>0,G14=INT(G14),H14>=0,I14>=0,J14>0,J14=INT(J14),K14<>"",ISNUMBER(L14),L14>='00_审核入口'!$F$2,M14="已核实",N14="完整"),IF(S14>0,MAX(0,INT((500-I14)/S14)),""),"") | Z14: =IF(AND(COUNT(C14:J14)=8,C14>0,D14>=0,E14>0,F14>=0,G14>0,G14=INT(G14),H14>=0,I14>=0,J14>0,J14=INT(J14),K14<>"",ISNUMBER(L14),L14>='00_审核入口'!$F$2,M14="已核实",N14="完整"),IF(AND(T14>=15,U14>=0.2,W14>=0,X14<=500),"成本条件通过","成本条件不通过"),"待补证") -> 待补证
A15: C11 | B15: 硅胶排水口毛发过滤片 | M15: 待核实 | N15: =IF(COUNTIF('04_费用明细'!N185:N202,"完整")=18,"完整","待补证") -> 待补证 | O15: =IF(N15="完整",SUM('04_费用明细'!L185:L202),"") | P15: =IF(N15="完整",SUM('04_费用明细'!M185:M202),"") | Q15: =IF(AND(COUNT(C15:J15)=8,C15>0,D15>=0,E15>0,F15>=0,G15>0,G15=INT(G15),H15>=0,I15>=0,J15>0,J15=INT(J15),K15<>"",ISNUMBER(L15),L15>='00_审核入口'!$F$2,M15="已核实",N15="完整"),ROUND(ROUND((C15+D15)*E15,10),2),"") | R15: =IF(AND(COUNT(C15:J15)=8,C15>0,D15>=0,E15>0,F15>=0,G15>0,G15=INT(G15),H15>=0,I15>=0,J15>0,J15=INT(J15),K15<>"",ISNUMBER(L15),L15>='00_审核入口'!$F$2,M15="已核实",N15="完整"),ROUND(ROUND(F15*G15*(1+H15),10),2),"") | S15: =IF(AND(COUNT(C15:J15)=8,C15>0,D15>=0,E15>0,F15>=0,G15>0,G15=INT(G15),H15>=0,I15>=0,J15>0,J15=INT(J15),K15<>"",ISNUMBER(L15),L15>='00_审核入口'!$F$2,M15="已核实",N15="完整"),R15+O15,"") | T15: =IF(AND(COUNT(C15:J15)=8,C15>0,D15>=0,E15>0,F15>=0,G15>0,G15=INT(G15),H15>=0,I15>=0,J15>0,J15=INT(J15),K15<>"",ISNUMBER(L15),L15>='00_审核入口'!$F$2,M15="已核实",N15="完整"),Q15-S15,"") | U15: =IF(AND(COUNT(C15:J15)=8,C15>0,D15>=0,E15>0,F15>=0,G15>0,G15=INT(G15),H15>=0,I15>=0,J15>0,J15=INT(J15),K15<>"",ISNUMBER(L15),L15>='00_审核入口'!$F$2,M15="已核实",N15="完整"),IF(Q15>0,T15/Q15,""),"") | V15: =IF(AND(COUNT(C15:J15)=8,C15>0,D15>=0,E15>0,F15>=0,G15>0,G15=INT(G15),H15>=0,I15>=0,J15>0,J15=INT(J15),K15<>"",ISNUMBER(L15),L15>='00_审核入口'!$F$2,M15="已核实",N15="完整"),IF(Q15-O15-ROUNDUP(MAX(15,0.2*Q15),2)<0,"无非负可行采购价",ROUNDDOWN((Q15-O15-ROUNDUP(MAX(15,0.2*Q15),2)+0.005-0.0000000001)/(G15*(1+H15)),2)),"") | W15: =IF(AND(COUNT(C15:J15)=8,C15>0,D15>=0,E15>0,F15>=0,G15>0,G15=INT(G15),H15>=0,I15>=0,J15>0,J15=INT(J15),K15<>"",ISNUMBER(L15),L15>='00_审核入口'!$F$2,M15="已核实",N15="完整"),ROUND(ROUND((C15+D15)*E15*0.95,10),2)-ROUND(ROUND(F15*1.1*G15*(1+H15),10),2)-P15,"") | X15: =IF(AND(COUNT(C15:J15)=8,C15>0,D15>=0,E15>0,F15>=0,G15>0,G15=INT(G15),H15>=0,I15>=0,J15>0,J15=INT(J15),K15<>"",ISNUMBER(L15),L15>='00_审核入口'!$F$2,M15="已核实",N15="完整"),ROUND(I15+J15*S15,2),"") | Y15: =IF(AND(COUNT(C15:J15)=8,C15>0,D15>=0,E15>0,F15>=0,G15>0,G15=INT(G15),H15>=0,I15>=0,J15>0,J15=INT(J15),K15<>"",ISNUMBER(L15),L15>='00_审核入口'!$F$2,M15="已核实",N15="完整"),IF(S15>0,MAX(0,INT((500-I15)/S15)),""),"") | Z15: =IF(AND(COUNT(C15:J15)=8,C15>0,D15>=0,E15>0,F15>=0,G15>0,G15=INT(G15),H15>=0,I15>=0,J15>0,J15=INT(J15),K15<>"",ISNUMBER(L15),L15>='00_审核入口'!$F$2,M15="已核实",N15="完整"),IF(AND(T15>=15,U15>=0.2,W15>=0,X15<=500),"成本条件通过","成本条件不通过"),"待补证") -> 待补证
A16: C12 | B16: 挂式塑料袋收纳袋 | M16: 待核实 | N16: =IF(COUNTIF('04_费用明细'!N203:N220,"完整")=18,"完整","待补证") -> 待补证 | O16: =IF(N16="完整",SUM('04_费用明细'!L203:L220),"") | P16: =IF(N16="完整",SUM('04_费用明细'!M203:M220),"") | Q16: =IF(AND(COUNT(C16:J16)=8,C16>0,D16>=0,E16>0,F16>=0,G16>0,G16=INT(G16),H16>=0,I16>=0,J16>0,J16=INT(J16),K16<>"",ISNUMBER(L16),L16>='00_审核入口'!$F$2,M16="已核实",N16="完整"),ROUND(ROUND((C16+D16)*E16,10),2),"") | R16: =IF(AND(COUNT(C16:J16)=8,C16>0,D16>=0,E16>0,F16>=0,G16>0,G16=INT(G16),H16>=0,I16>=0,J16>0,J16=INT(J16),K16<>"",ISNUMBER(L16),L16>='00_审核入口'!$F$2,M16="已核实",N16="完整"),ROUND(ROUND(F16*G16*(1+H16),10),2),"") | S16: =IF(AND(COUNT(C16:J16)=8,C16>0,D16>=0,E16>0,F16>=0,G16>0,G16=INT(G16),H16>=0,I16>=0,J16>0,J16=INT(J16),K16<>"",ISNUMBER(L16),L16>='00_审核入口'!$F$2,M16="已核实",N16="完整"),R16+O16,"") | T16: =IF(AND(COUNT(C16:J16)=8,C16>0,D16>=0,E16>0,F16>=0,G16>0,G16=INT(G16),H16>=0,I16>=0,J16>0,J16=INT(J16),K16<>"",ISNUMBER(L16),L16>='00_审核入口'!$F$2,M16="已核实",N16="完整"),Q16-S16,"") | U16: =IF(AND(COUNT(C16:J16)=8,C16>0,D16>=0,E16>0,F16>=0,G16>0,G16=INT(G16),H16>=0,I16>=0,J16>0,J16=INT(J16),K16<>"",ISNUMBER(L16),L16>='00_审核入口'!$F$2,M16="已核实",N16="完整"),IF(Q16>0,T16/Q16,""),"") | V16: =IF(AND(COUNT(C16:J16)=8,C16>0,D16>=0,E16>0,F16>=0,G16>0,G16=INT(G16),H16>=0,I16>=0,J16>0,J16=INT(J16),K16<>"",ISNUMBER(L16),L16>='00_审核入口'!$F$2,M16="已核实",N16="完整"),IF(Q16-O16-ROUNDUP(MAX(15,0.2*Q16),2)<0,"无非负可行采购价",ROUNDDOWN((Q16-O16-ROUNDUP(MAX(15,0.2*Q16),2)+0.005-0.0000000001)/(G16*(1+H16)),2)),"") | W16: =IF(AND(COUNT(C16:J16)=8,C16>0,D16>=0,E16>0,F16>=0,G16>0,G16=INT(G16),H16>=0,I16>=0,J16>0,J16=INT(J16),K16<>"",ISNUMBER(L16),L16>='00_审核入口'!$F$2,M16="已核实",N16="完整"),ROUND(ROUND((C16+D16)*E16*0.95,10),2)-ROUND(ROUND(F16*1.1*G16*(1+H16),10),2)-P16,"") | X16: =IF(AND(COUNT(C16:J16)=8,C16>0,D16>=0,E16>0,F16>=0,G16>0,G16=INT(G16),H16>=0,I16>=0,J16>0,J16=INT(J16),K16<>"",ISNUMBER(L16),L16>='00_审核入口'!$F$2,M16="已核实",N16="完整"),ROUND(I16+J16*S16,2),"") | Y16: =IF(AND(COUNT(C16:J16)=8,C16>0,D16>=0,E16>0,F16>=0,G16>0,G16=INT(G16),H16>=0,I16>=0,J16>0,J16=INT(J16),K16<>"",ISNUMBER(L16),L16>='00_审核入口'!$F$2,M16="已核实",N16="完整"),IF(S16>0,MAX(0,INT((500-I16)/S16)),""),"") | Z16: =IF(AND(COUNT(C16:J16)=8,C16>0,D16>=0,E16>0,F16>=0,G16>0,G16=INT(G16),H16>=0,I16>=0,J16>0,J16=INT(J16),K16<>"",ISNUMBER(L16),L16>='00_审核入口'!$F$2,M16="已核实",N16="完整"),IF(AND(T16>=15,U16>=0.2,W16>=0,X16<=500),"成本条件通过","成本条件不通过"),"待补证") -> 待补证
A17: C13 | B17: 可重复使用粘扣理线带套装 | M17: 待核实 | N17: =IF(COUNTIF('04_费用明细'!N221:N238,"完整")=18,"完整","待补证") -> 待补证 | O17: =IF(N17="完整",SUM('04_费用明细'!L221:L238),"") | P17: =IF(N17="完整",SUM('04_费用明细'!M221:M238),"") | Q17: =IF(AND(COUNT(C17:J17)=8,C17>0,D17>=0,E17>0,F17>=0,G17>0,G17=INT(G17),H17>=0,I17>=0,J17>0,J17=INT(J17),K17<>"",ISNUMBER(L17),L17>='00_审核入口'!$F$2,M17="已核实",N17="完整"),ROUND(ROUND((C17+D17)*E17,10),2),"") | R17: =IF(AND(COUNT(C17:J17)=8,C17>0,D17>=0,E17>0,F17>=0,G17>0,G17=INT(G17),H17>=0,I17>=0,J17>0,J17=INT(J17),K17<>"",ISNUMBER(L17),L17>='00_审核入口'!$F$2,M17="已核实",N17="完整"),ROUND(ROUND(F17*G17*(1+H17),10),2),"") | S17: =IF(AND(COUNT(C17:J17)=8,C17>0,D17>=0,E17>0,F17>=0,G17>0,G17=INT(G17),H17>=0,I17>=0,J17>0,J17=INT(J17),K17<>"",ISNUMBER(L17),L17>='00_审核入口'!$F$2,M17="已核实",N17="完整"),R17+O17,"") | T17: =IF(AND(COUNT(C17:J17)=8,C17>0,D17>=0,E17>0,F17>=0,G17>0,G17=INT(G17),H17>=0,I17>=0,J17>0,J17=INT(J17),K17<>"",ISNUMBER(L17),L17>='00_审核入口'!$F$2,M17="已核实",N17="完整"),Q17-S17,"") | U17: =IF(AND(COUNT(C17:J17)=8,C17>0,D17>=0,E17>0,F17>=0,G17>0,G17=INT(G17),H17>=0,I17>=0,J17>0,J17=INT(J17),K17<>"",ISNUMBER(L17),L17>='00_审核入口'!$F$2,M17="已核实",N17="完整"),IF(Q17>0,T17/Q17,""),"") | V17: =IF(AND(COUNT(C17:J17)=8,C17>0,D17>=0,E17>0,F17>=0,G17>0,G17=INT(G17),H17>=0,I17>=0,J17>0,J17=INT(J17),K17<>"",ISNUMBER(L17),L17>='00_审核入口'!$F$2,M17="已核实",N17="完整"),IF(Q17-O17-ROUNDUP(MAX(15,0.2*Q17),2)<0,"无非负可行采购价",ROUNDDOWN((Q17-O17-ROUNDUP(MAX(15,0.2*Q17),2)+0.005-0.0000000001)/(G17*(1+H17)),2)),"") | W17: =IF(AND(COUNT(C17:J17)=8,C17>0,D17>=0,E17>0,F17>=0,G17>0,G17=INT(G17),H17>=0,I17>=0,J17>0,J17=INT(J17),K17<>"",ISNUMBER(L17),L17>='00_审核入口'!$F$2,M17="已核实",N17="完整"),ROUND(ROUND((C17+D17)*E17*0.95,10),2)-ROUND(ROUND(F17*1.1*G17*(1+H17),10),2)-P17,"") | X17: =IF(AND(COUNT(C17:J17)=8,C17>0,D17>=0,E17>0,F17>=0,G17>0,G17=INT(G17),H17>=0,I17>=0,J17>0,J17=INT(J17),K17<>"",ISNUMBER(L17),L17>='00_审核入口'!$F$2,M17="已核实",N17="完整"),ROUND(I17+J17*S17,2),"") | Y17: =IF(AND(COUNT(C17:J17)=8,C17>0,D17>=0,E17>0,F17>=0,G17>0,G17=INT(G17),H17>=0,I17>=0,J17>0,J17=INT(J17),K17<>"",ISNUMBER(L17),L17>='00_审核入口'!$F$2,M17="已核实",N17="完整"),IF(S17>0,MAX(0,INT((500-I17)/S17)),""),"") | Z17: =IF(AND(COUNT(C17:J17)=8,C17>0,D17>=0,E17>0,F17>=0,G17>0,G17=INT(G17),H17>=0,I17>=0,J17>0,J17=INT(J17),K17<>"",ISNUMBER(L17),L17>='00_审核入口'!$F$2,M17="已核实",N17="完整"),IF(AND(T17>=15,U17>=0.2,W17>=0,X17<=500),"成本条件通过","成本条件不通过"),"待补证") -> 待补证
A18: C14 | B18: 网眼拉链旅行收纳包 | M18: 待核实 | N18: =IF(COUNTIF('04_费用明细'!N239:N256,"完整")=18,"完整","待补证") -> 待补证 | O18: =IF(N18="完整",SUM('04_费用明细'!L239:L256),"") | P18: =IF(N18="完整",SUM('04_费用明细'!M239:M256),"") | Q18: =IF(AND(COUNT(C18:J18)=8,C18>0,D18>=0,E18>0,F18>=0,G18>0,G18=INT(G18),H18>=0,I18>=0,J18>0,J18=INT(J18),K18<>"",ISNUMBER(L18),L18>='00_审核入口'!$F$2,M18="已核实",N18="完整"),ROUND(ROUND((C18+D18)*E18,10),2),"") | R18: =IF(AND(COUNT(C18:J18)=8,C18>0,D18>=0,E18>0,F18>=0,G18>0,G18=INT(G18),H18>=0,I18>=0,J18>0,J18=INT(J18),K18<>"",ISNUMBER(L18),L18>='00_审核入口'!$F$2,M18="已核实",N18="完整"),ROUND(ROUND(F18*G18*(1+H18),10),2),"") | S18: =IF(AND(COUNT(C18:J18)=8,C18>0,D18>=0,E18>0,F18>=0,G18>0,G18=INT(G18),H18>=0,I18>=0,J18>0,J18=INT(J18),K18<>"",ISNUMBER(L18),L18>='00_审核入口'!$F$2,M18="已核实",N18="完整"),R18+O18,"") | T18: =IF(AND(COUNT(C18:J18)=8,C18>0,D18>=0,E18>0,F18>=0,G18>0,G18=INT(G18),H18>=0,I18>=0,J18>0,J18=INT(J18),K18<>"",ISNUMBER(L18),L18>='00_审核入口'!$F$2,M18="已核实",N18="完整"),Q18-S18,"") | U18: =IF(AND(COUNT(C18:J18)=8,C18>0,D18>=0,E18>0,F18>=0,G18>0,G18=INT(G18),H18>=0,I18>=0,J18>0,J18=INT(J18),K18<>"",ISNUMBER(L18),L18>='00_审核入口'!$F$2,M18="已核实",N18="完整"),IF(Q18>0,T18/Q18,""),"") | V18: =IF(AND(COUNT(C18:J18)=8,C18>0,D18>=0,E18>0,F18>=0,G18>0,G18=INT(G18),H18>=0,I18>=0,J18>0,J18=INT(J18),K18<>"",ISNUMBER(L18),L18>='00_审核入口'!$F$2,M18="已核实",N18="完整"),IF(Q18-O18-ROUNDUP(MAX(15,0.2*Q18),2)<0,"无非负可行采购价",ROUNDDOWN((Q18-O18-ROUNDUP(MAX(15,0.2*Q18),2)+0.005-0.0000000001)/(G18*(1+H18)),2)),"") | W18: =IF(AND(COUNT(C18:J18)=8,C18>0,D18>=0,E18>0,F18>=0,G18>0,G18=INT(G18),H18>=0,I18>=0,J18>0,J18=INT(J18),K18<>"",ISNUMBER(L18),L18>='00_审核入口'!$F$2,M18="已核实",N18="完整"),ROUND(ROUND((C18+D18)*E18*0.95,10),2)-ROUND(ROUND(F18*1.1*G18*(1+H18),10),2)-P18,"") | X18: =IF(AND(COUNT(C18:J18)=8,C18>0,D18>=0,E18>0,F18>=0,G18>0,G18=INT(G18),H18>=0,I18>=0,J18>0,J18=INT(J18),K18<>"",ISNUMBER(L18),L18>='00_审核入口'!$F$2,M18="已核实",N18="完整"),ROUND(I18+J18*S18,2),"") | Y18: =IF(AND(COUNT(C18:J18)=8,C18>0,D18>=0,E18>0,F18>=0,G18>0,G18=INT(G18),H18>=0,I18>=0,J18>0,J18=INT(J18),K18<>"",ISNUMBER(L18),L18>='00_审核入口'!$F$2,M18="已核实",N18="完整"),IF(S18>0,MAX(0,INT((500-I18)/S18)),""),"") | Z18: =IF(AND(COUNT(C18:J18)=8,C18>0,D18>=0,E18>0,F18>=0,G18>0,G18=INT(G18),H18>=0,I18>=0,J18>0,J18=INT(J18),K18<>"",ISNUMBER(L18),L18>='00_审核入口'!$F$2,M18="已核实",N18="完整"),IF(AND(T18>=15,U18>=0.2,W18>=0,X18<=500),"成本条件通过","成本条件不通过"),"待补证") -> 待补证
A19: C15 | B19: 五合一可折叠裤架 | M19: 待核实 | N19: =IF(COUNTIF('04_费用明细'!N257:N274,"完整")=18,"完整","待补证") -> 待补证 | O19: =IF(N19="完整",SUM('04_费用明细'!L257:L274),"") | P19: =IF(N19="完整",SUM('04_费用明细'!M257:M274),"") | Q19: =IF(AND(COUNT(C19:J19)=8,C19>0,D19>=0,E19>0,F19>=0,G19>0,G19=INT(G19),H19>=0,I19>=0,J19>0,J19=INT(J19),K19<>"",ISNUMBER(L19),L19>='00_审核入口'!$F$2,M19="已核实",N19="完整"),ROUND(ROUND((C19+D19)*E19,10),2),"") | R19: =IF(AND(COUNT(C19:J19)=8,C19>0,D19>=0,E19>0,F19>=0,G19>0,G19=INT(G19),H19>=0,I19>=0,J19>0,J19=INT(J19),K19<>"",ISNUMBER(L19),L19>='00_审核入口'!$F$2,M19="已核实",N19="完整"),ROUND(ROUND(F19*G19*(1+H19),10),2),"") | S19: =IF(AND(COUNT(C19:J19)=8,C19>0,D19>=0,E19>0,F19>=0,G19>0,G19=INT(G19),H19>=0,I19>=0,J19>0,J19=INT(J19),K19<>"",ISNUMBER(L19),L19>='00_审核入口'!$F$2,M19="已核实",N19="完整"),R19+O19,"") | T19: =IF(AND(COUNT(C19:J19)=8,C19>0,D19>=0,E19>0,F19>=0,G19>0,G19=INT(G19),H19>=0,I19>=0,J19>0,J19=INT(J19),K19<>"",ISNUMBER(L19),L19>='00_审核入口'!$F$2,M19="已核实",N19="完整"),Q19-S19,"") | U19: =IF(AND(COUNT(C19:J19)=8,C19>0,D19>=0,E19>0,F19>=0,G19>0,G19=INT(G19),H19>=0,I19>=0,J19>0,J19=INT(J19),K19<>"",ISNUMBER(L19),L19>='00_审核入口'!$F$2,M19="已核实",N19="完整"),IF(Q19>0,T19/Q19,""),"") | V19: =IF(AND(COUNT(C19:J19)=8,C19>0,D19>=0,E19>0,F19>=0,G19>0,G19=INT(G19),H19>=0,I19>=0,J19>0,J19=INT(J19),K19<>"",ISNUMBER(L19),L19>='00_审核入口'!$F$2,M19="已核实",N19="完整"),IF(Q19-O19-ROUNDUP(MAX(15,0.2*Q19),2)<0,"无非负可行采购价",ROUNDDOWN((Q19-O19-ROUNDUP(MAX(15,0.2*Q19),2)+0.005-0.0000000001)/(G19*(1+H19)),2)),"") | W19: =IF(AND(COUNT(C19:J19)=8,C19>0,D19>=0,E19>0,F19>=0,G19>0,G19=INT(G19),H19>=0,I19>=0,J19>0,J19=INT(J19),K19<>"",ISNUMBER(L19),L19>='00_审核入口'!$F$2,M19="已核实",N19="完整"),ROUND(ROUND((C19+D19)*E19*0.95,10),2)-ROUND(ROUND(F19*1.1*G19*(1+H19),10),2)-P19,"") | X19: =IF(AND(COUNT(C19:J19)=8,C19>0,D19>=0,E19>0,F19>=0,G19>0,G19=INT(G19),H19>=0,I19>=0,J19>0,J19=INT(J19),K19<>"",ISNUMBER(L19),L19>='00_审核入口'!$F$2,M19="已核实",N19="完整"),ROUND(I19+J19*S19,2),"") | Y19: =IF(AND(COUNT(C19:J19)=8,C19>0,D19>=0,E19>0,F19>=0,G19>0,G19=INT(G19),H19>=0,I19>=0,J19>0,J19=INT(J19),K19<>"",ISNUMBER(L19),L19>='00_审核入口'!$F$2,M19="已核实",N19="完整"),IF(S19>0,MAX(0,INT((500-I19)/S19)),""),"") | Z19: =IF(AND(COUNT(C19:J19)=8,C19>0,D19>=0,E19>0,F19>=0,G19>0,G19=INT(G19),H19>=0,I19>=0,J19>0,J19=INT(J19),K19<>"",ISNUMBER(L19),L19>='00_审核入口'!$F$2,M19="已核实",N19="完整"),IF(AND(T19>=15,U19>=0.2,W19>=0,X19<=500),"成本条件通过","成本条件不通过"),"待补证") -> 待补证
A20: C16 | B20: 双层线材旅行收纳包 | M20: 待核实 | N20: =IF(COUNTIF('04_费用明细'!N275:N292,"完整")=18,"完整","待补证") -> 待补证 | O20: =IF(N20="完整",SUM('04_费用明细'!L275:L292),"") | P20: =IF(N20="完整",SUM('04_费用明细'!M275:M292),"") | Q20: =IF(AND(COUNT(C20:J20)=8,C20>0,D20>=0,E20>0,F20>=0,G20>0,G20=INT(G20),H20>=0,I20>=0,J20>0,J20=INT(J20),K20<>"",ISNUMBER(L20),L20>='00_审核入口'!$F$2,M20="已核实",N20="完整"),ROUND(ROUND((C20+D20)*E20,10),2),"") | R20: =IF(AND(COUNT(C20:J20)=8,C20>0,D20>=0,E20>0,F20>=0,G20>0,G20=INT(G20),H20>=0,I20>=0,J20>0,J20=INT(J20),K20<>"",ISNUMBER(L20),L20>='00_审核入口'!$F$2,M20="已核实",N20="完整"),ROUND(ROUND(F20*G20*(1+H20),10),2),"") | S20: =IF(AND(COUNT(C20:J20)=8,C20>0,D20>=0,E20>0,F20>=0,G20>0,G20=INT(G20),H20>=0,I20>=0,J20>0,J20=INT(J20),K20<>"",ISNUMBER(L20),L20>='00_审核入口'!$F$2,M20="已核实",N20="完整"),R20+O20,"") | T20: =IF(AND(COUNT(C20:J20)=8,C20>0,D20>=0,E20>0,F20>=0,G20>0,G20=INT(G20),H20>=0,I20>=0,J20>0,J20=INT(J20),K20<>"",ISNUMBER(L20),L20>='00_审核入口'!$F$2,M20="已核实",N20="完整"),Q20-S20,"") | U20: =IF(AND(COUNT(C20:J20)=8,C20>0,D20>=0,E20>0,F20>=0,G20>0,G20=INT(G20),H20>=0,I20>=0,J20>0,J20=INT(J20),K20<>"",ISNUMBER(L20),L20>='00_审核入口'!$F$2,M20="已核实",N20="完整"),IF(Q20>0,T20/Q20,""),"") | V20: =IF(AND(COUNT(C20:J20)=8,C20>0,D20>=0,E20>0,F20>=0,G20>0,G20=INT(G20),H20>=0,I20>=0,J20>0,J20=INT(J20),K20<>"",ISNUMBER(L20),L20>='00_审核入口'!$F$2,M20="已核实",N20="完整"),IF(Q20-O20-ROUNDUP(MAX(15,0.2*Q20),2)<0,"无非负可行采购价",ROUNDDOWN((Q20-O20-ROUNDUP(MAX(15,0.2*Q20),2)+0.005-0.0000000001)/(G20*(1+H20)),2)),"") | W20: =IF(AND(COUNT(C20:J20)=8,C20>0,D20>=0,E20>0,F20>=0,G20>0,G20=INT(G20),H20>=0,I20>=0,J20>0,J20=INT(J20),K20<>"",ISNUMBER(L20),L20>='00_审核入口'!$F$2,M20="已核实",N20="完整"),ROUND(ROUND((C20+D20)*E20*0.95,10),2)-ROUND(ROUND(F20*1.1*G20*(1+H20),10),2)-P20,"") | X20: =IF(AND(COUNT(C20:J20)=8,C20>0,D20>=0,E20>0,F20>=0,G20>0,G20=INT(G20),H20>=0,I20>=0,J20>0,J20=INT(J20),K20<>"",ISNUMBER(L20),L20>='00_审核入口'!$F$2,M20="已核实",N20="完整"),ROUND(I20+J20*S20,2),"") | Y20: =IF(AND(COUNT(C20:J20)=8,C20>0,D20>=0,E20>0,F20>=0,G20>0,G20=INT(G20),H20>=0,I20>=0,J20>0,J20=INT(J20),K20<>"",ISNUMBER(L20),L20>='00_审核入口'!$F$2,M20="已核实",N20="完整"),IF(S20>0,MAX(0,INT((500-I20)/S20)),""),"") | Z20: =IF(AND(COUNT(C20:J20)=8,C20>0,D20>=0,E20>0,F20>=0,G20>0,G20=INT(G20),H20>=0,I20>=0,J20>0,J20=INT(J20),K20<>"",ISNUMBER(L20),L20>='00_审核入口'!$F$2,M20="已核实",N20="完整"),IF(AND(T20>=15,U20>=0.2,W20>=0,X20<=500),"成本条件通过","成本条件不通过"),"待补证") -> 待补证
A21: C17 | B21: 便携首饰分格收纳盒 | M21: 待核实 | N21: =IF(COUNTIF('04_费用明细'!N293:N310,"完整")=18,"完整","待补证") -> 待补证 | O21: =IF(N21="完整",SUM('04_费用明细'!L293:L310),"") | P21: =IF(N21="完整",SUM('04_费用明细'!M293:M310),"") | Q21: =IF(AND(COUNT(C21:J21)=8,C21>0,D21>=0,E21>0,F21>=0,G21>0,G21=INT(G21),H21>=0,I21>=0,J21>0,J21=INT(J21),K21<>"",ISNUMBER(L21),L21>='00_审核入口'!$F$2,M21="已核实",N21="完整"),ROUND(ROUND((C21+D21)*E21,10),2),"") | R21: =IF(AND(COUNT(C21:J21)=8,C21>0,D21>=0,E21>0,F21>=0,G21>0,G21=INT(G21),H21>=0,I21>=0,J21>0,J21=INT(J21),K21<>"",ISNUMBER(L21),L21>='00_审核入口'!$F$2,M21="已核实",N21="完整"),ROUND(ROUND(F21*G21*(1+H21),10),2),"") | S21: =IF(AND(COUNT(C21:J21)=8,C21>0,D21>=0,E21>0,F21>=0,G21>0,G21=INT(G21),H21>=0,I21>=0,J21>0,J21=INT(J21),K21<>"",ISNUMBER(L21),L21>='00_审核入口'!$F$2,M21="已核实",N21="完整"),R21+O21,"") | T21: =IF(AND(COUNT(C21:J21)=8,C21>0,D21>=0,E21>0,F21>=0,G21>0,G21=INT(G21),H21>=0,I21>=0,J21>0,J21=INT(J21),K21<>"",ISNUMBER(L21),L21>='00_审核入口'!$F$2,M21="已核实",N21="完整"),Q21-S21,"") | U21: =IF(AND(COUNT(C21:J21)=8,C21>0,D21>=0,E21>0,F21>=0,G21>0,G21=INT(G21),H21>=0,I21>=0,J21>0,J21=INT(J21),K21<>"",ISNUMBER(L21),L21>='00_审核入口'!$F$2,M21="已核实",N21="完整"),IF(Q21>0,T21/Q21,""),"") | V21: =IF(AND(COUNT(C21:J21)=8,C21>0,D21>=0,E21>0,F21>=0,G21>0,G21=INT(G21),H21>=0,I21>=0,J21>0,J21=INT(J21),K21<>"",ISNUMBER(L21),L21>='00_审核入口'!$F$2,M21="已核实",N21="完整"),IF(Q21-O21-ROUNDUP(MAX(15,0.2*Q21),2)<0,"无非负可行采购价",ROUNDDOWN((Q21-O21-ROUNDUP(MAX(15,0.2*Q21),2)+0.005-0.0000000001)/(G21*(1+H21)),2)),"") | W21: =IF(AND(COUNT(C21:J21)=8,C21>0,D21>=0,E21>0,F21>=0,G21>0,G21=INT(G21),H21>=0,I21>=0,J21>0,J21=INT(J21),K21<>"",ISNUMBER(L21),L21>='00_审核入口'!$F$2,M21="已核实",N21="完整"),ROUND(ROUND((C21+D21)*E21*0.95,10),2)-ROUND(ROUND(F21*1.1*G21*(1+H21),10),2)-P21,"") | X21: =IF(AND(COUNT(C21:J21)=8,C21>0,D21>=0,E21>0,F21>=0,G21>0,G21=INT(G21),H21>=0,I21>=0,J21>0,J21=INT(J21),K21<>"",ISNUMBER(L21),L21>='00_审核入口'!$F$2,M21="已核实",N21="完整"),ROUND(I21+J21*S21,2),"") | Y21: =IF(AND(COUNT(C21:J21)=8,C21>0,D21>=0,E21>0,F21>=0,G21>0,G21=INT(G21),H21>=0,I21>=0,J21>0,J21=INT(J21),K21<>"",ISNUMBER(L21),L21>='00_审核入口'!$F$2,M21="已核实",N21="完整"),IF(S21>0,MAX(0,INT((500-I21)/S21)),""),"") | Z21: =IF(AND(COUNT(C21:J21)=8,C21>0,D21>=0,E21>0,F21>=0,G21>0,G21=INT(G21),H21>=0,I21>=0,J21>0,J21=INT(J21),K21<>"",ISNUMBER(L21),L21>='00_审核入口'!$F$2,M21="已核实",N21="完整"),IF(AND(T21>=15,U21>=0.2,W21>=0,X21<=500),"成本条件通过","成本条件不通过"),"待补证") -> 待补证
A22: C18 | B22: 门背免打孔挂钩架 | M22: 待核实 | N22: =IF(COUNTIF('04_费用明细'!N311:N328,"完整")=18,"完整","待补证") -> 待补证 | O22: =IF(N22="完整",SUM('04_费用明细'!L311:L328),"") | P22: =IF(N22="完整",SUM('04_费用明细'!M311:M328),"") | Q22: =IF(AND(COUNT(C22:J22)=8,C22>0,D22>=0,E22>0,F22>=0,G22>0,G22=INT(G22),H22>=0,I22>=0,J22>0,J22=INT(J22),K22<>"",ISNUMBER(L22),L22>='00_审核入口'!$F$2,M22="已核实",N22="完整"),ROUND(ROUND((C22+D22)*E22,10),2),"") | R22: =IF(AND(COUNT(C22:J22)=8,C22>0,D22>=0,E22>0,F22>=0,G22>0,G22=INT(G22),H22>=0,I22>=0,J22>0,J22=INT(J22),K22<>"",ISNUMBER(L22),L22>='00_审核入口'!$F$2,M22="已核实",N22="完整"),ROUND(ROUND(F22*G22*(1+H22),10),2),"") | S22: =IF(AND(COUNT(C22:J22)=8,C22>0,D22>=0,E22>0,F22>=0,G22>0,G22=INT(G22),H22>=0,I22>=0,J22>0,J22=INT(J22),K22<>"",ISNUMBER(L22),L22>='00_审核入口'!$F$2,M22="已核实",N22="完整"),R22+O22,"") | T22: =IF(AND(COUNT(C22:J22)=8,C22>0,D22>=0,E22>0,F22>=0,G22>0,G22=INT(G22),H22>=0,I22>=0,J22>0,J22=INT(J22),K22<>"",ISNUMBER(L22),L22>='00_审核入口'!$F$2,M22="已核实",N22="完整"),Q22-S22,"") | U22: =IF(AND(COUNT(C22:J22)=8,C22>0,D22>=0,E22>0,F22>=0,G22>0,G22=INT(G22),H22>=0,I22>=0,J22>0,J22=INT(J22),K22<>"",ISNUMBER(L22),L22>='00_审核入口'!$F$2,M22="已核实",N22="完整"),IF(Q22>0,T22/Q22,""),"") | V22: =IF(AND(COUNT(C22:J22)=8,C22>0,D22>=0,E22>0,F22>=0,G22>0,G22=INT(G22),H22>=0,I22>=0,J22>0,J22=INT(J22),K22<>"",ISNUMBER(L22),L22>='00_审核入口'!$F$2,M22="已核实",N22="完整"),IF(Q22-O22-ROUNDUP(MAX(15,0.2*Q22),2)<0,"无非负可行采购价",ROUNDDOWN((Q22-O22-ROUNDUP(MAX(15,0.2*Q22),2)+0.005-0.0000000001)/(G22*(1+H22)),2)),"") | W22: =IF(AND(COUNT(C22:J22)=8,C22>0,D22>=0,E22>0,F22>=0,G22>0,G22=INT(G22),H22>=0,I22>=0,J22>0,J22=INT(J22),K22<>"",ISNUMBER(L22),L22>='00_审核入口'!$F$2,M22="已核实",N22="完整"),ROUND(ROUND((C22+D22)*E22*0.95,10),2)-ROUND(ROUND(F22*1.1*G22*(1+H22),10),2)-P22,"") | X22: =IF(AND(COUNT(C22:J22)=8,C22>0,D22>=0,E22>0,F22>=0,G22>0,G22=INT(G22),H22>=0,I22>=0,J22>0,J22=INT(J22),K22<>"",ISNUMBER(L22),L22>='00_审核入口'!$F$2,M22="已核实",N22="完整"),ROUND(I22+J22*S22,2),"") | Y22: =IF(AND(COUNT(C22:J22)=8,C22>0,D22>=0,E22>0,F22>=0,G22>0,G22=INT(G22),H22>=0,I22>=0,J22>0,J22=INT(J22),K22<>"",ISNUMBER(L22),L22>='00_审核入口'!$F$2,M22="已核实",N22="完整"),IF(S22>0,MAX(0,INT((500-I22)/S22)),""),"") | Z22: =IF(AND(COUNT(C22:J22)=8,C22>0,D22>=0,E22>0,F22>=0,G22>0,G22=INT(G22),H22>=0,I22>=0,J22>0,J22=INT(J22),K22<>"",ISNUMBER(L22),L22>='00_审核入口'!$F$2,M22="已核实",N22="完整"),IF(AND(T22>=15,U22>=0.2,W22>=0,X22<=500),"成本条件通过","成本条件不通过"),"待补证") -> 待补证
A23: C19 | B23: 十夹式小件晾晒衣架 | M23: 待核实 | N23: =IF(COUNTIF('04_费用明细'!N329:N346,"完整")=18,"完整","待补证") -> 待补证 | O23: =IF(N23="完整",SUM('04_费用明细'!L329:L346),"") | P23: =IF(N23="完整",SUM('04_费用明细'!M329:M346),"") | Q23: =IF(AND(COUNT(C23:J23)=8,C23>0,D23>=0,E23>0,F23>=0,G23>0,G23=INT(G23),H23>=0,I23>=0,J23>0,J23=INT(J23),K23<>"",ISNUMBER(L23),L23>='00_审核入口'!$F$2,M23="已核实",N23="完整"),ROUND(ROUND((C23+D23)*E23,10),2),"") | R23: =IF(AND(COUNT(C23:J23)=8,C23>0,D23>=0,E23>0,F23>=0,G23>0,G23=INT(G23),H23>=0,I23>=0,J23>0,J23=INT(J23),K23<>"",ISNUMBER(L23),L23>='00_审核入口'!$F$2,M23="已核实",N23="完整"),ROUND(ROUND(F23*G23*(1+H23),10),2),"") | S23: =IF(AND(COUNT(C23:J23)=8,C23>0,D23>=0,E23>0,F23>=0,G23>0,G23=INT(G23),H23>=0,I23>=0,J23>0,J23=INT(J23),K23<>"",ISNUMBER(L23),L23>='00_审核入口'!$F$2,M23="已核实",N23="完整"),R23+O23,"") | T23: =IF(AND(COUNT(C23:J23)=8,C23>0,D23>=0,E23>0,F23>=0,G23>0,G23=INT(G23),H23>=0,I23>=0,J23>0,J23=INT(J23),K23<>"",ISNUMBER(L23),L23>='00_审核入口'!$F$2,M23="已核实",N23="完整"),Q23-S23,"") | U23: =IF(AND(COUNT(C23:J23)=8,C23>0,D23>=0,E23>0,F23>=0,G23>0,G23=INT(G23),H23>=0,I23>=0,J23>0,J23=INT(J23),K23<>"",ISNUMBER(L23),L23>='00_审核入口'!$F$2,M23="已核实",N23="完整"),IF(Q23>0,T23/Q23,""),"") | V23: =IF(AND(COUNT(C23:J23)=8,C23>0,D23>=0,E23>0,F23>=0,G23>0,G23=INT(G23),H23>=0,I23>=0,J23>0,J23=INT(J23),K23<>"",ISNUMBER(L23),L23>='00_审核入口'!$F$2,M23="已核实",N23="完整"),IF(Q23-O23-ROUNDUP(MAX(15,0.2*Q23),2)<0,"无非负可行采购价",ROUNDDOWN((Q23-O23-ROUNDUP(MAX(15,0.2*Q23),2)+0.005-0.0000000001)/(G23*(1+H23)),2)),"") | W23: =IF(AND(COUNT(C23:J23)=8,C23>0,D23>=0,E23>0,F23>=0,G23>0,G23=INT(G23),H23>=0,I23>=0,J23>0,J23=INT(J23),K23<>"",ISNUMBER(L23),L23>='00_审核入口'!$F$2,M23="已核实",N23="完整"),ROUND(ROUND((C23+D23)*E23*0.95,10),2)-ROUND(ROUND(F23*1.1*G23*(1+H23),10),2)-P23,"") | X23: =IF(AND(COUNT(C23:J23)=8,C23>0,D23>=0,E23>0,F23>=0,G23>0,G23=INT(G23),H23>=0,I23>=0,J23>0,J23=INT(J23),K23<>"",ISNUMBER(L23),L23>='00_审核入口'!$F$2,M23="已核实",N23="完整"),ROUND(I23+J23*S23,2),"") | Y23: =IF(AND(COUNT(C23:J23)=8,C23>0,D23>=0,E23>0,F23>=0,G23>0,G23=INT(G23),H23>=0,I23>=0,J23>0,J23=INT(J23),K23<>"",ISNUMBER(L23),L23>='00_审核入口'!$F$2,M23="已核实",N23="完整"),IF(S23>0,MAX(0,INT((500-I23)/S23)),""),"") | Z23: =IF(AND(COUNT(C23:J23)=8,C23>0,D23>=0,E23>0,F23>=0,G23>0,G23=INT(G23),H23>=0,I23>=0,J23>0,J23=INT(J23),K23<>"",ISNUMBER(L23),L23>='00_审核入口'!$F$2,M23="已核实",N23="完整"),IF(AND(T23>=15,U23>=0.2,W23>=0,X23<=500),"成本条件通过","成本条件不通过"),"待补证") -> 待补证
A24: C20 | B24: 悬挂文件分袋整理袋 | M24: 待核实 | N24: =IF(COUNTIF('04_费用明细'!N347:N364,"完整")=18,"完整","待补证") -> 待补证 | O24: =IF(N24="完整",SUM('04_费用明细'!L347:L364),"") | P24: =IF(N24="完整",SUM('04_费用明细'!M347:M364),"") | Q24: =IF(AND(COUNT(C24:J24)=8,C24>0,D24>=0,E24>0,F24>=0,G24>0,G24=INT(G24),H24>=0,I24>=0,J24>0,J24=INT(J24),K24<>"",ISNUMBER(L24),L24>='00_审核入口'!$F$2,M24="已核实",N24="完整"),ROUND(ROUND((C24+D24)*E24,10),2),"") | R24: =IF(AND(COUNT(C24:J24)=8,C24>0,D24>=0,E24>0,F24>=0,G24>0,G24=INT(G24),H24>=0,I24>=0,J24>0,J24=INT(J24),K24<>"",ISNUMBER(L24),L24>='00_审核入口'!$F$2,M24="已核实",N24="完整"),ROUND(ROUND(F24*G24*(1+H24),10),2),"") | S24: =IF(AND(COUNT(C24:J24)=8,C24>0,D24>=0,E24>0,F24>=0,G24>0,G24=INT(G24),H24>=0,I24>=0,J24>0,J24=INT(J24),K24<>"",ISNUMBER(L24),L24>='00_审核入口'!$F$2,M24="已核实",N24="完整"),R24+O24,"") | T24: =IF(AND(COUNT(C24:J24)=8,C24>0,D24>=0,E24>0,F24>=0,G24>0,G24=INT(G24),H24>=0,I24>=0,J24>0,J24=INT(J24),K24<>"",ISNUMBER(L24),L24>='00_审核入口'!$F$2,M24="已核实",N24="完整"),Q24-S24,"") | U24: =IF(AND(COUNT(C24:J24)=8,C24>0,D24>=0,E24>0,F24>=0,G24>0,G24=INT(G24),H24>=0,I24>=0,J24>0,J24=INT(J24),K24<>"",ISNUMBER(L24),L24>='00_审核入口'!$F$2,M24="已核实",N24="完整"),IF(Q24>0,T24/Q24,""),"") | V24: =IF(AND(COUNT(C24:J24)=8,C24>0,D24>=0,E24>0,F24>=0,G24>0,G24=INT(G24),H24>=0,I24>=0,J24>0,J24=INT(J24),K24<>"",ISNUMBER(L24),L24>='00_审核入口'!$F$2,M24="已核实",N24="完整"),IF(Q24-O24-ROUNDUP(MAX(15,0.2*Q24),2)<0,"无非负可行采购价",ROUNDDOWN((Q24-O24-ROUNDUP(MAX(15,0.2*Q24),2)+0.005-0.0000000001)/(G24*(1+H24)),2)),"") | W24: =IF(AND(COUNT(C24:J24)=8,C24>0,D24>=0,E24>0,F24>=0,G24>0,G24=INT(G24),H24>=0,I24>=0,J24>0,J24=INT(J24),K24<>"",ISNUMBER(L24),L24>='00_审核入口'!$F$2,M24="已核实",N24="完整"),ROUND(ROUND((C24+D24)*E24*0.95,10),2)-ROUND(ROUND(F24*1.1*G24*(1+H24),10),2)-P24,"") | X24: =IF(AND(COUNT(C24:J24)=8,C24>0,D24>=0,E24>0,F24>=0,G24>0,G24=INT(G24),H24>=0,I24>=0,J24>0,J24=INT(J24),K24<>"",ISNUMBER(L24),L24>='00_审核入口'!$F$2,M24="已核实",N24="完整"),ROUND(I24+J24*S24,2),"") | Y24: =IF(AND(COUNT(C24:J24)=8,C24>0,D24>=0,E24>0,F24>=0,G24>0,G24=INT(G24),H24>=0,I24>=0,J24>0,J24=INT(J24),K24<>"",ISNUMBER(L24),L24>='00_审核入口'!$F$2,M24="已核实",N24="完整"),IF(S24>0,MAX(0,INT((500-I24)/S24)),""),"") | Z24: =IF(AND(COUNT(C24:J24)=8,C24>0,D24>=0,E24>0,F24>=0,G24>0,G24=INT(G24),H24>=0,I24>=0,J24>0,J24=INT(J24),K24<>"",ISNUMBER(L24),L24>='00_审核入口'!$F$2,M24="已核实",N24="完整"),IF(AND(T24>=15,U24>=0.2,W24>=0,X24<=500),"成本条件通过","成本条件不通过"),"待补证") -> 待补证
A25: C21 | B25: 桌面穿线孔盖 | M25: 待核实 | N25: =IF(COUNTIF('04_费用明细'!N365:N382,"完整")=18,"完整","待补证") -> 待补证 | O25: =IF(N25="完整",SUM('04_费用明细'!L365:L382),"") | P25: =IF(N25="完整",SUM('04_费用明细'!M365:M382),"") | Q25: =IF(AND(COUNT(C25:J25)=8,C25>0,D25>=0,E25>0,F25>=0,G25>0,G25=INT(G25),H25>=0,I25>=0,J25>0,J25=INT(J25),K25<>"",ISNUMBER(L25),L25>='00_审核入口'!$F$2,M25="已核实",N25="完整"),ROUND(ROUND((C25+D25)*E25,10),2),"") | R25: =IF(AND(COUNT(C25:J25)=8,C25>0,D25>=0,E25>0,F25>=0,G25>0,G25=INT(G25),H25>=0,I25>=0,J25>0,J25=INT(J25),K25<>"",ISNUMBER(L25),L25>='00_审核入口'!$F$2,M25="已核实",N25="完整"),ROUND(ROUND(F25*G25*(1+H25),10),2),"") | S25: =IF(AND(COUNT(C25:J25)=8,C25>0,D25>=0,E25>0,F25>=0,G25>0,G25=INT(G25),H25>=0,I25>=0,J25>0,J25=INT(J25),K25<>"",ISNUMBER(L25),L25>='00_审核入口'!$F$2,M25="已核实",N25="完整"),R25+O25,"") | T25: =IF(AND(COUNT(C25:J25)=8,C25>0,D25>=0,E25>0,F25>=0,G25>0,G25=INT(G25),H25>=0,I25>=0,J25>0,J25=INT(J25),K25<>"",ISNUMBER(L25),L25>='00_审核入口'!$F$2,M25="已核实",N25="完整"),Q25-S25,"") | U25: =IF(AND(COUNT(C25:J25)=8,C25>0,D25>=0,E25>0,F25>=0,G25>0,G25=INT(G25),H25>=0,I25>=0,J25>0,J25=INT(J25),K25<>"",ISNUMBER(L25),L25>='00_审核入口'!$F$2,M25="已核实",N25="完整"),IF(Q25>0,T25/Q25,""),"") | V25: =IF(AND(COUNT(C25:J25)=8,C25>0,D25>=0,E25>0,F25>=0,G25>0,G25=INT(G25),H25>=0,I25>=0,J25>0,J25=INT(J25),K25<>"",ISNUMBER(L25),L25>='00_审核入口'!$F$2,M25="已核实",N25="完整"),IF(Q25-O25-ROUNDUP(MAX(15,0.2*Q25),2)<0,"无非负可行采购价",ROUNDDOWN((Q25-O25-ROUNDUP(MAX(15,0.2*Q25),2)+0.005-0.0000000001)/(G25*(1+H25)),2)),"") | W25: =IF(AND(COUNT(C25:J25)=8,C25>0,D25>=0,E25>0,F25>=0,G25>0,G25=INT(G25),H25>=0,I25>=0,J25>0,J25=INT(J25),K25<>"",ISNUMBER(L25),L25>='00_审核入口'!$F$2,M25="已核实",N25="完整"),ROUND(ROUND((C25+D25)*E25*0.95,10),2)-ROUND(ROUND(F25*1.1*G25*(1+H25),10),2)-P25,"") | X25: =IF(AND(COUNT(C25:J25)=8,C25>0,D25>=0,E25>0,F25>=0,G25>0,G25=INT(G25),H25>=0,I25>=0,J25>0,J25=INT(J25),K25<>"",ISNUMBER(L25),L25>='00_审核入口'!$F$2,M25="已核实",N25="完整"),ROUND(I25+J25*S25,2),"") | Y25: =IF(AND(COUNT(C25:J25)=8,C25>0,D25>=0,E25>0,F25>=0,G25>0,G25=INT(G25),H25>=0,I25>=0,J25>0,J25=INT(J25),K25<>"",ISNUMBER(L25),L25>='00_审核入口'!$F$2,M25="已核实",N25="完整"),IF(S25>0,MAX(0,INT((500-I25)/S25)),""),"") | Z25: =IF(AND(COUNT(C25:J25)=8,C25>0,D25>=0,E25>0,F25>=0,G25>0,G25=INT(G25),H25>=0,I25>=0,J25>0,J25=INT(J25),K25<>"",ISNUMBER(L25),L25>='00_审核入口'!$F$2,M25="已核实",N25="完整"),IF(AND(T25>=15,U25>=0.2,W25>=0,X25<=500),"成本条件通过","成本条件不通过"),"待补证") -> 待补证
A26: C22 | B26: 编织式线材整理套管 | M26: 待核实 | N26: =IF(COUNTIF('04_费用明细'!N383:N400,"完整")=18,"完整","待补证") -> 待补证 | O26: =IF(N26="完整",SUM('04_费用明细'!L383:L400),"") | P26: =IF(N26="完整",SUM('04_费用明细'!M383:M400),"") | Q26: =IF(AND(COUNT(C26:J26)=8,C26>0,D26>=0,E26>0,F26>=0,G26>0,G26=INT(G26),H26>=0,I26>=0,J26>0,J26=INT(J26),K26<>"",ISNUMBER(L26),L26>='00_审核入口'!$F$2,M26="已核实",N26="完整"),ROUND(ROUND((C26+D26)*E26,10),2),"") | R26: =IF(AND(COUNT(C26:J26)=8,C26>0,D26>=0,E26>0,F26>=0,G26>0,G26=INT(G26),H26>=0,I26>=0,J26>0,J26=INT(J26),K26<>"",ISNUMBER(L26),L26>='00_审核入口'!$F$2,M26="已核实",N26="完整"),ROUND(ROUND(F26*G26*(1+H26),10),2),"") | S26: =IF(AND(COUNT(C26:J26)=8,C26>0,D26>=0,E26>0,F26>=0,G26>0,G26=INT(G26),H26>=0,I26>=0,J26>0,J26=INT(J26),K26<>"",ISNUMBER(L26),L26>='00_审核入口'!$F$2,M26="已核实",N26="完整"),R26+O26,"") | T26: =IF(AND(COUNT(C26:J26)=8,C26>0,D26>=0,E26>0,F26>=0,G26>0,G26=INT(G26),H26>=0,I26>=0,J26>0,J26=INT(J26),K26<>"",ISNUMBER(L26),L26>='00_审核入口'!$F$2,M26="已核实",N26="完整"),Q26-S26,"") | U26: =IF(AND(COUNT(C26:J26)=8,C26>0,D26>=0,E26>0,F26>=0,G26>0,G26=INT(G26),H26>=0,I26>=0,J26>0,J26=INT(J26),K26<>"",ISNUMBER(L26),L26>='00_审核入口'!$F$2,M26="已核实",N26="完整"),IF(Q26>0,T26/Q26,""),"") | V26: =IF(AND(COUNT(C26:J26)=8,C26>0,D26>=0,E26>0,F26>=0,G26>0,G26=INT(G26),H26>=0,I26>=0,J26>0,J26=INT(J26),K26<>"",ISNUMBER(L26),L26>='00_审核入口'!$F$2,M26="已核实",N26="完整"),IF(Q26-O26-ROUNDUP(MAX(15,0.2*Q26),2)<0,"无非负可行采购价",ROUNDDOWN((Q26-O26-ROUNDUP(MAX(15,0.2*Q26),2)+0.005-0.0000000001)/(G26*(1+H26)),2)),"") | W26: =IF(AND(COUNT(C26:J26)=8,C26>0,D26>=0,E26>0,F26>=0,G26>0,G26=INT(G26),H26>=0,I26>=0,J26>0,J26=INT(J26),K26<>"",ISNUMBER(L26),L26>='00_审核入口'!$F$2,M26="已核实",N26="完整"),ROUND(ROUND((C26+D26)*E26*0.95,10),2)-ROUND(ROUND(F26*1.1*G26*(1+H26),10),2)-P26,"") | X26: =IF(AND(COUNT(C26:J26)=8,C26>0,D26>=0,E26>0,F26>=0,G26>0,G26=INT(G26),H26>=0,I26>=0,J26>0,J26=INT(J26),K26<>"",ISNUMBER(L26),L26>='00_审核入口'!$F$2,M26="已核实",N26="完整"),ROUND(I26+J26*S26,2),"") | Y26: =IF(AND(COUNT(C26:J26)=8,C26>0,D26>=0,E26>0,F26>=0,G26>0,G26=INT(G26),H26>=0,I26>=0,J26>0,J26=INT(J26),K26<>"",ISNUMBER(L26),L26>='00_审核入口'!$F$2,M26="已核实",N26="完整"),IF(S26>0,MAX(0,INT((500-I26)/S26)),""),"") | Z26: =IF(AND(COUNT(C26:J26)=8,C26>0,D26>=0,E26>0,F26>=0,G26>0,G26=INT(G26),H26>=0,I26>=0,J26>0,J26=INT(J26),K26<>"",ISNUMBER(L26),L26>='00_审核入口'!$F$2,M26="已核实",N26="完整"),IF(AND(T26>=15,U26>=0.2,W26>=0,X26<=500),"成本条件通过","成本条件不通过"),"待补证") -> 待补证

Sheet 04_费用明细
A1: 04 · 费用明细
A2: 每款18项逐项核实；0要有免费或不适用依据。交易费压力金额必须填；国内运费/仓包/SLS在压力情景再×1.15，PHP费用用汇率×0.95。广告和售后可用有依据的预算，公共费率参考不自动填成本。
A4: ID | B4: 产品 | C4: 费项键 | D4: 费项名称 | E4: 币种 | F4: 基准金额 | G4: 压力金额覆盖 | H4: 状态 | I4: 规则/基数/舍入/封顶/分摊 | J4: 依据 | K4: 有效期截止 | L4: 基准CNY | M4: 压力CNY | N4: 本行完整
A5: C01 | B5: 多尺寸拉链洗衣网袋套装 | C5: commission | D5: 适用跨境佣金 | H5: 待核实 | L5: =IF(AND(N5="完整",ISNUMBER('03_逐品成本'!E5),'03_逐品成本'!E5>0),ROUND(ROUND(F5*IF(E5="PHP",'03_逐品成本'!E5,1),10),2),"") | M5: =IF(AND(N5="完整",ISNUMBER('03_逐品成本'!E5),'03_逐品成本'!E5>0),ROUND(ROUND(IF(ISNUMBER(G5),G5,F5)*1*IF(E5="PHP",'03_逐品成本'!E5*0.95,1),10),2),"") | N5: =IF(AND(ISNUMBER(F5),F5>=0,OR(E5="PHP",E5="CNY"),OR(H5="已核实",H5="不适用"),I5<>"",J5<>"",ISNUMBER(K5),K5>='00_审核入口'!$F$2,OR(H5<>"不适用",F5=0),OR(G5="",AND(ISNUMBER(G5),G5>=0))),"完整","待补证") -> 待补证
A6: C01 | B6: 多尺寸拉链洗衣网袋套装 | C6: transaction | D6: 交易费（含实际支付方式） | H6: 待核实 | L6: =IF(AND(N6="完整",ISNUMBER('03_逐品成本'!E5),'03_逐品成本'!E5>0),ROUND(ROUND(F6*IF(E6="PHP",'03_逐品成本'!E5,1),10),2),"") | M6: =IF(AND(N6="完整",ISNUMBER('03_逐品成本'!E5),'03_逐品成本'!E5>0),ROUND(ROUND(IF(ISNUMBER(G6),G6,F6)*1*IF(E6="PHP",'03_逐品成本'!E5*0.95,1),10),2),"") | N6: =IF(AND(ISNUMBER(F6),F6>=0,OR(E6="PHP",E6="CNY"),OR(H6="已核实",H6="不适用"),I6<>"",J6<>"",ISNUMBER(K6),K6>='00_审核入口'!$F$2,OR(H6<>"不适用",F6=0),OR(G6="",AND(ISNUMBER(G6),G6>=0)),ISNUMBER(G6),G6>=0),"完整","待补证") -> 待补证
A7: C01 | B7: 多尺寸拉链洗衣网袋套装 | C7: installment_extra | D7: 额外分期项目费 | H7: 待核实 | L7: =IF(AND(N7="完整",ISNUMBER('03_逐品成本'!E5),'03_逐品成本'!E5>0),ROUND(ROUND(F7*IF(E7="PHP",'03_逐品成本'!E5,1),10),2),"") | M7: =IF(AND(N7="完整",ISNUMBER('03_逐品成本'!E5),'03_逐品成本'!E5>0),ROUND(ROUND(IF(ISNUMBER(G7),G7,F7)*1*IF(E7="PHP",'03_逐品成本'!E5*0.95,1),10),2),"") | N7: =IF(AND(ISNUMBER(F7),F7>=0,OR(E7="PHP",E7="CNY"),OR(H7="已核实",H7="不适用"),I7<>"",J7<>"",ISNUMBER(K7),K7>='00_审核入口'!$F$2,OR(H7<>"不适用",F7=0),OR(G7="",AND(ISNUMBER(G7),G7>=0))),"完整","待补证") -> 待补证
A8: C01 | B8: 多尺寸拉链洗衣网袋套装 | C8: growth | D8: 卖家增长费 | H8: 待核实 | L8: =IF(AND(N8="完整",ISNUMBER('03_逐品成本'!E5),'03_逐品成本'!E5>0),ROUND(ROUND(F8*IF(E8="PHP",'03_逐品成本'!E5,1),10),2),"") | M8: =IF(AND(N8="完整",ISNUMBER('03_逐品成本'!E5),'03_逐品成本'!E5>0),ROUND(ROUND(IF(ISNUMBER(G8),G8,F8)*1*IF(E8="PHP",'03_逐品成本'!E5*0.95,1),10),2),"") | N8: =IF(AND(ISNUMBER(F8),F8>=0,OR(E8="PHP",E8="CNY"),OR(H8="已核实",H8="不适用"),I8<>"",J8<>"",ISNUMBER(K8),K8>='00_审核入口'!$F$2,OR(H8<>"不适用",F8=0),OR(G8="",AND(ISNUMBER(G8),G8>=0))),"完整","待补证") -> 待补证
A9: C01 | B9: 多尺寸拉链洗衣网袋套装 | C9: platform_shipping | D9: 平台运费计划费 | H9: 待核实 | L9: =IF(AND(N9="完整",ISNUMBER('03_逐品成本'!E5),'03_逐品成本'!E5>0),ROUND(ROUND(F9*IF(E9="PHP",'03_逐品成本'!E5,1),10),2),"") | M9: =IF(AND(N9="完整",ISNUMBER('03_逐品成本'!E5),'03_逐品成本'!E5>0),ROUND(ROUND(IF(ISNUMBER(G9),G9,F9)*1*IF(E9="PHP",'03_逐品成本'!E5*0.95,1),10),2),"") | N9: =IF(AND(ISNUMBER(F9),F9>=0,OR(E9="PHP",E9="CNY"),OR(H9="已核实",H9="不适用"),I9<>"",J9<>"",ISNUMBER(K9),K9>='00_审核入口'!$F$2,OR(H9<>"不适用",F9=0),OR(G9="",AND(ISNUMBER(G9),G9>=0))),"完整","待补证") -> 待补证
A10: C01 | B10: 多尺寸拉链洗衣网袋套装 | C10: order_processing | D10: 订单处理费 | H10: 待核实 | L10: =IF(AND(N10="完整",ISNUMBER('03_逐品成本'!E5),'03_逐品成本'!E5>0),ROUND(ROUND(F10*IF(E10="PHP",'03_逐品成本'!E5,1),10),2),"") | M10: =IF(AND(N10="完整",ISNUMBER('03_逐品成本'!E5),'03_逐品成本'!E5>0),ROUND(ROUND(IF(ISNUMBER(G10),G10,F10)*1*IF(E10="PHP",'03_逐品成本'!E5*0.95,1),10),2),"") | N10: =IF(AND(ISNUMBER(F10),F10>=0,OR(E10="PHP",E10="CNY"),OR(H10="已核实",H10="不适用"),I10<>"",J10<>"",ISNUMBER(K10),K10>='00_审核入口'!$F$2,OR(H10<>"不适用",F10=0),OR(G10="",AND(ISNUMBER(G10),G10>=0))),"完整","待补证") -> 待补证
A11: C01 | B11: 多尺寸拉链洗衣网袋套装 | C11: preorder | D11: 预售及其他平台服务费 | H11: 待核实 | L11: =IF(AND(N11="完整",ISNUMBER('03_逐品成本'!E5),'03_逐品成本'!E5>0),ROUND(ROUND(F11*IF(E11="PHP",'03_逐品成本'!E5,1),10),2),"") | M11: =IF(AND(N11="完整",ISNUMBER('03_逐品成本'!E5),'03_逐品成本'!E5>0),ROUND(ROUND(IF(ISNUMBER(G11),G11,F11)*1*IF(E11="PHP",'03_逐品成本'!E5*0.95,1),10),2),"") | N11: =IF(AND(ISNUMBER(F11),F11>=0,OR(E11="PHP",E11="CNY"),OR(H11="已核实",H11="不适用"),I11<>"",J11<>"",ISNUMBER(K11),K11>='00_审核入口'!$F$2,OR(H11<>"不适用",F11=0),OR(G11="",AND(ISNUMBER(G11),G11>=0))),"完整","待补证") -> 待补证
A12: C01 | B12: 多尺寸拉链洗衣网袋套装 | C12: activities | D12: MDV/返币/直播等活动费 | H12: 待核实 | L12: =IF(AND(N12="完整",ISNUMBER('03_逐品成本'!E5),'03_逐品成本'!E5>0),ROUND(ROUND(F12*IF(E12="PHP",'03_逐品成本'!E5,1),10),2),"") | M12: =IF(AND(N12="完整",ISNUMBER('03_逐品成本'!E5),'03_逐品成本'!E5>0),ROUND(ROUND(IF(ISNUMBER(G12),G12,F12)*1*IF(E12="PHP",'03_逐品成本'!E5*0.95,1),10),2),"") | N12: =IF(AND(ISNUMBER(F12),F12>=0,OR(E12="PHP",E12="CNY"),OR(H12="已核实",H12="不适用"),I12<>"",J12<>"",ISNUMBER(K12),K12>='00_审核入口'!$F$2,OR(H12<>"不适用",F12=0),OR(G12="",AND(ISNUMBER(G12),G12>=0))),"完整","待补证") -> 待补证
A13: C01 | B13: 多尺寸拉链洗衣网袋套装 | C13: domestic | D13: 中国境内运费 | H13: 待核实 | L13: =IF(AND(N13="完整",ISNUMBER('03_逐品成本'!E5),'03_逐品成本'!E5>0),ROUND(ROUND(F13*IF(E13="PHP",'03_逐品成本'!E5,1),10),2),"") | M13: =IF(AND(N13="完整",ISNUMBER('03_逐品成本'!E5),'03_逐品成本'!E5>0),ROUND(ROUND(IF(ISNUMBER(G13),G13,F13)*1.15*IF(E13="PHP",'03_逐品成本'!E5*0.95,1),10),2),"") | N13: =IF(AND(ISNUMBER(F13),F13>=0,OR(E13="PHP",E13="CNY"),OR(H13="已核实",H13="不适用"),I13<>"",J13<>"",ISNUMBER(K13),K13>='00_审核入口'!$F$2,OR(H13<>"不适用",F13=0),OR(G13="",AND(ISNUMBER(G13),G13>=0))),"完整","待补证") -> 待补证
A14: C01 | B14: 多尺寸拉链洗衣网袋套装 | C14: warehouse_pack | D14: 云仓/验货/贴标/仓储/包材 | H14: 待核实 | L14: =IF(AND(N14="完整",ISNUMBER('03_逐品成本'!E5),'03_逐品成本'!E5>0),ROUND(ROUND(F14*IF(E14="PHP",'03_逐品成本'!E5,1),10),2),"") | M14: =IF(AND(N14="完整",ISNUMBER('03_逐品成本'!E5),'03_逐品成本'!E5>0),ROUND(ROUND(IF(ISNUMBER(G14),G14,F14)*1.15*IF(E14="PHP",'03_逐品成本'!E5*0.95,1),10),2),"") | N14: =IF(AND(ISNUMBER(F14),F14>=0,OR(E14="PHP",E14="CNY"),OR(H14="已核实",H14="不适用"),I14<>"",J14<>"",ISNUMBER(K14),K14>='00_审核入口'!$F$2,OR(H14<>"不适用",F14=0),OR(G14="",AND(ISNUMBER(G14),G14>=0))),"完整","待补证") -> 待补证
A15: C01 | B15: 多尺寸拉链洗衣网袋套装 | C15: sls | D15: SLS卖家净国际物流 | H15: 待核实 | L15: =IF(AND(N15="完整",ISNUMBER('03_逐品成本'!E5),'03_逐品成本'!E5>0),ROUND(ROUND(F15*IF(E15="PHP",'03_逐品成本'!E5,1),10),2),"") | M15: =IF(AND(N15="完整",ISNUMBER('03_逐品成本'!E5),'03_逐品成本'!E5>0),ROUND(ROUND(IF(ISNUMBER(G15),G15,F15)*1.15*IF(E15="PHP",'03_逐品成本'!E5*0.95,1),10),2),"") | N15: =IF(AND(ISNUMBER(F15),F15>=0,OR(E15="PHP",E15="CNY"),OR(H15="已核实",H15="不适用"),I15<>"",J15<>"",ISNUMBER(K15),K15>='00_审核入口'!$F$2,OR(H15<>"不适用",F15=0),OR(G15="",AND(ISNUMBER(G15),G15>=0))),"完整","待补证") -> 待补证
A16: C01 | B16: 多尺寸拉链洗衣网袋套装 | C16: ads | D16: 广告预算分摊 | H16: 待核实 | L16: =IF(AND(N16="完整",ISNUMBER('03_逐品成本'!E5),'03_逐品成本'!E5>0),ROUND(ROUND(F16*IF(E16="PHP",'03_逐品成本'!E5,1),10),2),"") | M16: =IF(AND(N16="完整",ISNUMBER('03_逐品成本'!E5),'03_逐品成本'!E5>0),ROUND(ROUND(IF(ISNUMBER(G16),G16,F16)*1*IF(E16="PHP",'03_逐品成本'!E5*0.95,1),10),2),"") | N16: =IF(AND(ISNUMBER(F16),F16>=0,OR(E16="PHP",E16="CNY"),OR(H16="已核实",H16="不适用",H16="预算"),I16<>"",J16<>"",ISNUMBER(K16),K16>='00_审核入口'!$F$2,OR(H16<>"不适用",F16=0),OR(G16="",AND(ISNUMBER(G16),G16>=0))),"完整","待补证") -> 待补证
A17: C01 | B17: 多尺寸拉链洗衣网袋套装 | C17: affiliate | D17: 联盟/达人分摊 | H17: 待核实 | L17: =IF(AND(N17="完整",ISNUMBER('03_逐品成本'!E5),'03_逐品成本'!E5>0),ROUND(ROUND(F17*IF(E17="PHP",'03_逐品成本'!E5,1),10),2),"") | M17: =IF(AND(N17="完整",ISNUMBER('03_逐品成本'!E5),'03_逐品成本'!E5>0),ROUND(ROUND(IF(ISNUMBER(G17),G17,F17)*1*IF(E17="PHP",'03_逐品成本'!E5*0.95,1),10),2),"") | N17: =IF(AND(ISNUMBER(F17),F17>=0,OR(E17="PHP",E17="CNY"),OR(H17="已核实",H17="不适用",H17="预算"),I17<>"",J17<>"",ISNUMBER(K17),K17>='00_审核入口'!$F$2,OR(H17<>"不适用",F17=0),OR(G17="",AND(ISNUMBER(G17),G17>=0))),"完整","待补证") -> 待补证
A18: C01 | B18: 多尺寸拉链洗衣网袋套装 | C18: returns | D18: 售后退款/拒收/破损净损失准备 | H18: 待核实 | L18: =IF(AND(N18="完整",ISNUMBER('03_逐品成本'!E5),'03_逐品成本'!E5>0),ROUND(ROUND(F18*IF(E18="PHP",'03_逐品成本'!E5,1),10),2),"") | M18: =IF(AND(N18="完整",ISNUMBER('03_逐品成本'!E5),'03_逐品成本'!E5>0),ROUND(ROUND(IF(ISNUMBER(G18),G18,F18)*1*IF(E18="PHP",'03_逐品成本'!E5*0.95,1),10),2),"") | N18: =IF(AND(ISNUMBER(F18),F18>=0,OR(E18="PHP",E18="CNY"),OR(H18="已核实",H18="不适用",H18="预算"),I18<>"",J18<>"",ISNUMBER(K18),K18>='00_审核入口'!$F$2,OR(H18<>"不适用",F18=0),OR(G18="",AND(ISNUMBER(G18),G18>=0))),"完整","待补证") -> 待补证
A19: C01 | B19: 多尺寸拉链洗衣网袋套装 | C19: collection | D19: 收款/换汇/提现 | H19: 待核实 | L19: =IF(AND(N19="完整",ISNUMBER('03_逐品成本'!E5),'03_逐品成本'!E5>0),ROUND(ROUND(F19*IF(E19="PHP",'03_逐品成本'!E5,1),10),2),"") | M19: =IF(AND(N19="完整",ISNUMBER('03_逐品成本'!E5),'03_逐品成本'!E5>0),ROUND(ROUND(IF(ISNUMBER(G19),G19,F19)*1*IF(E19="PHP",'03_逐品成本'!E5*0.95,1),10),2),"") | N19: =IF(AND(ISNUMBER(F19),F19>=0,OR(E19="PHP",E19="CNY"),OR(H19="已核实",H19="不适用"),I19<>"",J19<>"",ISNUMBER(K19),K19>='00_审核入口'!$F$2,OR(H19<>"不适用",F19=0),OR(G19="",AND(ISNUMBER(G19),G19>=0))),"完整","待补证") -> 待补证
A20: C01 | B20: 多尺寸拉链洗衣网袋套装 | C20: tax | D20: 其他不可抵扣税费 | H20: 待核实 | L20: =IF(AND(N20="完整",ISNUMBER('03_逐品成本'!E5),'03_逐品成本'!E5>0),ROUND(ROUND(F20*IF(E20="PHP",'03_逐品成本'!E5,1),10),2),"") | M20: =IF(AND(N20="完整",ISNUMBER('03_逐品成本'!E5),'03_逐品成本'!E5>0),ROUND(ROUND(IF(ISNUMBER(G20),G20,F20)*1*IF(E20="PHP",'03_逐品成本'!E5*0.95,1),10),2),"") | N20: =IF(AND(ISNUMBER(F20),F20>=0,OR(E20="PHP",E20="CNY"),OR(H20="已核实",H20="不适用"),I20<>"",J20<>"",ISNUMBER(K20),K20>='00_审核入口'!$F$2,OR(H20<>"不适用",F20=0),OR(G20="",AND(ISNUMBER(G20),G20>=0))),"完整","待补证") -> 待补证
A21: C01 | B21: 多尺寸拉链洗衣网袋套装 | C21: overhead | D21: 固定运营成本分摊 | H21: 待核实 | L21: =IF(AND(N21="完整",ISNUMBER('03_逐品成本'!E5),'03_逐品成本'!E5>0),ROUND(ROUND(F21*IF(E21="PHP",'03_逐品成本'!E5,1),10),2),"") | M21: =IF(AND(N21="完整",ISNUMBER('03_逐品成本'!E5),'03_逐品成本'!E5>0),ROUND(ROUND(IF(ISNUMBER(G21),G21,F21)*1*IF(E21="PHP",'03_逐品成本'!E5*0.95,1),10),2),"") | N21: =IF(AND(ISNUMBER(F21),F21>=0,OR(E21="PHP",E21="CNY"),OR(H21="已核实",H21="不适用",H21="预算"),I21<>"",J21<>"",ISNUMBER(K21),K21>='00_审核入口'!$F$2,OR(H21<>"不适用",F21=0),OR(G21="",AND(ISNUMBER(G21),G21>=0))),"完整","待补证") -> 待补证
A22: C01 | B22: 多尺寸拉链洗衣网袋套装 | C22: other | D22: 其他有说明费用 | H22: 待核实 | L22: =IF(AND(N22="完整",ISNUMBER('03_逐品成本'!E5),'03_逐品成本'!E5>0),ROUND(ROUND(F22*IF(E22="PHP",'03_逐品成本'!E5,1),10),2),"") | M22: =IF(AND(N22="完整",ISNUMBER('03_逐品成本'!E5),'03_逐品成本'!E5>0),ROUND(ROUND(IF(ISNUMBER(G22),G22,F22)*1*IF(E22="PHP",'03_逐品成本'!E5*0.95,1),10),2),"") | N22: =IF(AND(ISNUMBER(F22),F22>=0,OR(E22="PHP",E22="CNY"),OR(H22="已核实",H22="不适用",H22="预算"),I22<>"",J22<>"",ISNUMBER(K22),K22>='00_审核入口'!$F$2,OR(H22<>"不适用",F22=0),OR(G22="",AND(ISNUMBER(G22),G22>=0))),"完整","待补证") -> 待补证
A23: C02 | B23: 行李箱衣物分装收纳套装 | C23: commission | D23: 适用跨境佣金 | H23: 待核实 | L23: =IF(AND(N23="完整",ISNUMBER('03_逐品成本'!E6),'03_逐品成本'!E6>0),ROUND(ROUND(F23*IF(E23="PHP",'03_逐品成本'!E6,1),10),2),"") | M23: =IF(AND(N23="完整",ISNUMBER('03_逐品成本'!E6),'03_逐品成本'!E6>0),ROUND(ROUND(IF(ISNUMBER(G23),G23,F23)*1*IF(E23="PHP",'03_逐品成本'!E6*0.95,1),10),2),"") | N23: =IF(AND(ISNUMBER(F23),F23>=0,OR(E23="PHP",E23="CNY"),OR(H23="已核实",H23="不适用"),I23<>"",J23<>"",ISNUMBER(K23),K23>='00_审核入口'!$F$2,OR(H23<>"不适用",F23=0),OR(G23="",AND(ISNUMBER(G23),G23>=0))),"完整","待补证") -> 待补证
A24: C02 | B24: 行李箱衣物分装收纳套装 | C24: transaction | D24: 交易费（含实际支付方式） | H24: 待核实 | L24: =IF(AND(N24="完整",ISNUMBER('03_逐品成本'!E6),'03_逐品成本'!E6>0),ROUND(ROUND(F24*IF(E24="PHP",'03_逐品成本'!E6,1),10),2),"") | M24: =IF(AND(N24="完整",ISNUMBER('03_逐品成本'!E6),'03_逐品成本'!E6>0),ROUND(ROUND(IF(ISNUMBER(G24),G24,F24)*1*IF(E24="PHP",'03_逐品成本'!E6*0.95,1),10),2),"") | N24: =IF(AND(ISNUMBER(F24),F24>=0,OR(E24="PHP",E24="CNY"),OR(H24="已核实",H24="不适用"),I24<>"",J24<>"",ISNUMBER(K24),K24>='00_审核入口'!$F$2,OR(H24<>"不适用",F24=0),OR(G24="",AND(ISNUMBER(G24),G24>=0)),ISNUMBER(G24),G24>=0),"完整","待补证") -> 待补证
A25: C02 | B25: 行李箱衣物分装收纳套装 | C25: installment_extra | D25: 额外分期项目费 | H25: 待核实 | L25: =IF(AND(N25="完整",ISNUMBER('03_逐品成本'!E6),'03_逐品成本'!E6>0),ROUND(ROUND(F25*IF(E25="PHP",'03_逐品成本'!E6,1),10),2),"") | M25: =IF(AND(N25="完整",ISNUMBER('03_逐品成本'!E6),'03_逐品成本'!E6>0),ROUND(ROUND(IF(ISNUMBER(G25),G25,F25)*1*IF(E25="PHP",'03_逐品成本'!E6*0.95,1),10),2),"") | N25: =IF(AND(ISNUMBER(F25),F25>=0,OR(E25="PHP",E25="CNY"),OR(H25="已核实",H25="不适用"),I25<>"",J25<>"",ISNUMBER(K25),K25>='00_审核入口'!$F$2,OR(H25<>"不适用",F25=0),OR(G25="",AND(ISNUMBER(G25),G25>=0))),"完整","待补证") -> 待补证
A26: C02 | B26: 行李箱衣物分装收纳套装 | C26: growth | D26: 卖家增长费 | H26: 待核实 | L26: =IF(AND(N26="完整",ISNUMBER('03_逐品成本'!E6),'03_逐品成本'!E6>0),ROUND(ROUND(F26*IF(E26="PHP",'03_逐品成本'!E6,1),10),2),"") | M26: =IF(AND(N26="完整",ISNUMBER('03_逐品成本'!E6),'03_逐品成本'!E6>0),ROUND(ROUND(IF(ISNUMBER(G26),G26,F26)*1*IF(E26="PHP",'03_逐品成本'!E6*0.95,1),10),2),"") | N26: =IF(AND(ISNUMBER(F26),F26>=0,OR(E26="PHP",E26="CNY"),OR(H26="已核实",H26="不适用"),I26<>"",J26<>"",ISNUMBER(K26),K26>='00_审核入口'!$F$2,OR(H26<>"不适用",F26=0),OR(G26="",AND(ISNUMBER(G26),G26>=0))),"完整","待补证") -> 待补证
A27: C02 | B27: 行李箱衣物分装收纳套装 | C27: platform_shipping | D27: 平台运费计划费 | H27: 待核实 | L27: =IF(AND(N27="完整",ISNUMBER('03_逐品成本'!E6),'03_逐品成本'!E6>0),ROUND(ROUND(F27*IF(E27="PHP",'03_逐品成本'!E6,1),10),2),"") | M27: =IF(AND(N27="完整",ISNUMBER('03_逐品成本'!E6),'03_逐品成本'!E6>0),ROUND(ROUND(IF(ISNUMBER(G27),G27,F27)*1*IF(E27="PHP",'03_逐品成本'!E6*0.95,1),10),2),"") | N27: =IF(AND(ISNUMBER(F27),F27>=0,OR(E27="PHP",E27="CNY"),OR(H27="已核实",H27="不适用"),I27<>"",J27<>"",ISNUMBER(K27),K27>='00_审核入口'!$F$2,OR(H27<>"不适用",F27=0),OR(G27="",AND(ISNUMBER(G27),G27>=0))),"完整","待补证") -> 待补证
A28: C02 | B28: 行李箱衣物分装收纳套装 | C28: order_processing | D28: 订单处理费 | H28: 待核实 | L28: =IF(AND(N28="完整",ISNUMBER('03_逐品成本'!E6),'03_逐品成本'!E6>0),ROUND(ROUND(F28*IF(E28="PHP",'03_逐品成本'!E6,1),10),2),"") | M28: =IF(AND(N28="完整",ISNUMBER('03_逐品成本'!E6),'03_逐品成本'!E6>0),ROUND(ROUND(IF(ISNUMBER(G28),G28,F28)*1*IF(E28="PHP",'03_逐品成本'!E6*0.95,1),10),2),"") | N28: =IF(AND(ISNUMBER(F28),F28>=0,OR(E28="PHP",E28="CNY"),OR(H28="已核实",H28="不适用"),I28<>"",J28<>"",ISNUMBER(K28),K28>='00_审核入口'!$F$2,OR(H28<>"不适用",F28=0),OR(G28="",AND(ISNUMBER(G28),G28>=0))),"完整","待补证") -> 待补证
A29: C02 | B29: 行李箱衣物分装收纳套装 | C29: preorder | D29: 预售及其他平台服务费 | H29: 待核实 | L29: =IF(AND(N29="完整",ISNUMBER('03_逐品成本'!E6),'03_逐品成本'!E6>0),ROUND(ROUND(F29*IF(E29="PHP",'03_逐品成本'!E6,1),10),2),"") | M29: =IF(AND(N29="完整",ISNUMBER('03_逐品成本'!E6),'03_逐品成本'!E6>0),ROUND(ROUND(IF(ISNUMBER(G29),G29,F29)*1*IF(E29="PHP",'03_逐品成本'!E6*0.95,1),10),2),"") | N29: =IF(AND(ISNUMBER(F29),F29>=0,OR(E29="PHP",E29="CNY"),OR(H29="已核实",H29="不适用"),I29<>"",J29<>"",ISNUMBER(K29),K29>='00_审核入口'!$F$2,OR(H29<>"不适用",F29=0),OR(G29="",AND(ISNUMBER(G29),G29>=0))),"完整","待补证") -> 待补证
A30: C02 | B30: 行李箱衣物分装收纳套装 | C30: activities | D30: MDV/返币/直播等活动费 | H30: 待核实 | L30: =IF(AND(N30="完整",ISNUMBER('03_逐品成本'!E6),'03_逐品成本'!E6>0),ROUND(ROUND(F30*IF(E30="PHP",'03_逐品成本'!E6,1),10),2),"") | M30: =IF(AND(N30="完整",ISNUMBER('03_逐品成本'!E6),'03_逐品成本'!E6>0),ROUND(ROUND(IF(ISNUMBER(G30),G30,F30)*1*IF(E30="PHP",'03_逐品成本'!E6*0.95,1),10),2),"") | N30: =IF(AND(ISNUMBER(F30),F30>=0,OR(E30="PHP",E30="CNY"),OR(H30="已核实",H30="不适用"),I30<>"",J30<>"",ISNUMBER(K30),K30>='00_审核入口'!$F$2,OR(H30<>"不适用",F30=0),OR(G30="",AND(ISNUMBER(G30),G30>=0))),"完整","待补证") -> 待补证
A31: C02 | B31: 行李箱衣物分装收纳套装 | C31: domestic | D31: 中国境内运费 | H31: 待核实 | L31: =IF(AND(N31="完整",ISNUMBER('03_逐品成本'!E6),'03_逐品成本'!E6>0),ROUND(ROUND(F31*IF(E31="PHP",'03_逐品成本'!E6,1),10),2),"") | M31: =IF(AND(N31="完整",ISNUMBER('03_逐品成本'!E6),'03_逐品成本'!E6>0),ROUND(ROUND(IF(ISNUMBER(G31),G31,F31)*1.15*IF(E31="PHP",'03_逐品成本'!E6*0.95,1),10),2),"") | N31: =IF(AND(ISNUMBER(F31),F31>=0,OR(E31="PHP",E31="CNY"),OR(H31="已核实",H31="不适用"),I31<>"",J31<>"",ISNUMBER(K31),K31>='00_审核入口'!$F$2,OR(H31<>"不适用",F31=0),OR(G31="",AND(ISNUMBER(G31),G31>=0))),"完整","待补证") -> 待补证
A32: C02 | B32: 行李箱衣物分装收纳套装 | C32: warehouse_pack | D32: 云仓/验货/贴标/仓储/包材 | H32: 待核实 | L32: =IF(AND(N32="完整",ISNUMBER('03_逐品成本'!E6),'03_逐品成本'!E6>0),ROUND(ROUND(F32*IF(E32="PHP",'03_逐品成本'!E6,1),10),2),"") | M32: =IF(AND(N32="完整",ISNUMBER('03_逐品成本'!E6),'03_逐品成本'!E6>0),ROUND(ROUND(IF(ISNUMBER(G32),G32,F32)*1.15*IF(E32="PHP",'03_逐品成本'!E6*0.95,1),10),2),"") | N32: =IF(AND(ISNUMBER(F32),F32>=0,OR(E32="PHP",E32="CNY"),OR(H32="已核实",H32="不适用"),I32<>"",J32<>"",ISNUMBER(K32),K32>='00_审核入口'!$F$2,OR(H32<>"不适用",F32=0),OR(G32="",AND(ISNUMBER(G32),G32>=0))),"完整","待补证") -> 待补证
A33: C02 | B33: 行李箱衣物分装收纳套装 | C33: sls | D33: SLS卖家净国际物流 | H33: 待核实 | L33: =IF(AND(N33="完整",ISNUMBER('03_逐品成本'!E6),'03_逐品成本'!E6>0),ROUND(ROUND(F33*IF(E33="PHP",'03_逐品成本'!E6,1),10),2),"") | M33: =IF(AND(N33="完整",ISNUMBER('03_逐品成本'!E6),'03_逐品成本'!E6>0),ROUND(ROUND(IF(ISNUMBER(G33),G33,F33)*1.15*IF(E33="PHP",'03_逐品成本'!E6*0.95,1),10),2),"") | N33: =IF(AND(ISNUMBER(F33),F33>=0,OR(E33="PHP",E33="CNY"),OR(H33="已核实",H33="不适用"),I33<>"",J33<>"",ISNUMBER(K33),K33>='00_审核入口'!$F$2,OR(H33<>"不适用",F33=0),OR(G33="",AND(ISNUMBER(G33),G33>=0))),"完整","待补证") -> 待补证
A34: C02 | B34: 行李箱衣物分装收纳套装 | C34: ads | D34: 广告预算分摊 | H34: 待核实 | L34: =IF(AND(N34="完整",ISNUMBER('03_逐品成本'!E6),'03_逐品成本'!E6>0),ROUND(ROUND(F34*IF(E34="PHP",'03_逐品成本'!E6,1),10),2),"") | M34: =IF(AND(N34="完整",ISNUMBER('03_逐品成本'!E6),'03_逐品成本'!E6>0),ROUND(ROUND(IF(ISNUMBER(G34),G34,F34)*1*IF(E34="PHP",'03_逐品成本'!E6*0.95,1),10),2),"") | N34: =IF(AND(ISNUMBER(F34),F34>=0,OR(E34="PHP",E34="CNY"),OR(H34="已核实",H34="不适用",H34="预算"),I34<>"",J34<>"",ISNUMBER(K34),K34>='00_审核入口'!$F$2,OR(H34<>"不适用",F34=0),OR(G34="",AND(ISNUMBER(G34),G34>=0))),"完整","待补证") -> 待补证
A35: C02 | B35: 行李箱衣物分装收纳套装 | C35: affiliate | D35: 联盟/达人分摊 | H35: 待核实 | L35: =IF(AND(N35="完整",ISNUMBER('03_逐品成本'!E6),'03_逐品成本'!E6>0),ROUND(ROUND(F35*IF(E35="PHP",'03_逐品成本'!E6,1),10),2),"") | M35: =IF(AND(N35="完整",ISNUMBER('03_逐品成本'!E6),'03_逐品成本'!E6>0),ROUND(ROUND(IF(ISNUMBER(G35),G35,F35)*1*IF(E35="PHP",'03_逐品成本'!E6*0.95,1),10),2),"") | N35: =IF(AND(ISNUMBER(F35),F35>=0,OR(E35="PHP",E35="CNY"),OR(H35="已核实",H35="不适用",H35="预算"),I35<>"",J35<>"",ISNUMBER(K35),K35>='00_审核入口'!$F$2,OR(H35<>"不适用",F35=0),OR(G35="",AND(ISNUMBER(G35),G35>=0))),"完整","待补证") -> 待补证
A36: C02 | B36: 行李箱衣物分装收纳套装 | C36: returns | D36: 售后退款/拒收/破损净损失准备 | H36: 待核实 | L36: =IF(AND(N36="完整",ISNUMBER('03_逐品成本'!E6),'03_逐品成本'!E6>0),ROUND(ROUND(F36*IF(E36="PHP",'03_逐品成本'!E6,1),10),2),"") | M36: =IF(AND(N36="完整",ISNUMBER('03_逐品成本'!E6),'03_逐品成本'!E6>0),ROUND(ROUND(IF(ISNUMBER(G36),G36,F36)*1*IF(E36="PHP",'03_逐品成本'!E6*0.95,1),10),2),"") | N36: =IF(AND(ISNUMBER(F36),F36>=0,OR(E36="PHP",E36="CNY"),OR(H36="已核实",H36="不适用",H36="预算"),I36<>"",J36<>"",ISNUMBER(K36),K36>='00_审核入口'!$F$2,OR(H36<>"不适用",F36=0),OR(G36="",AND(ISNUMBER(G36),G36>=0))),"完整","待补证") -> 待补证
A37: C02 | B37: 行李箱衣物分装收纳套装 | C37: collection | D37: 收款/换汇/提现 | H37: 待核实 | L37: =IF(AND(N37="完整",ISNUMBER('03_逐品成本'!E6),'03_逐品成本'!E6>0),ROUND(ROUND(F37*IF(E37="PHP",'03_逐品成本'!E6,1),10),2),"") | M37: =IF(AND(N37="完整",ISNUMBER('03_逐品成本'!E6),'03_逐品成本'!E6>0),ROUND(ROUND(IF(ISNUMBER(G37),G37,F37)*1*IF(E37="PHP",'03_逐品成本'!E6*0.95,1),10),2),"") | N37: =IF(AND(ISNUMBER(F37),F37>=0,OR(E37="PHP",E37="CNY"),OR(H37="已核实",H37="不适用"),I37<>"",J37<>"",ISNUMBER(K37),K37>='00_审核入口'!$F$2,OR(H37<>"不适用",F37=0),OR(G37="",AND(ISNUMBER(G37),G37>=0))),"完整","待补证") -> 待补证
A38: C02 | B38: 行李箱衣物分装收纳套装 | C38: tax | D38: 其他不可抵扣税费 | H38: 待核实 | L38: =IF(AND(N38="完整",ISNUMBER('03_逐品成本'!E6),'03_逐品成本'!E6>0),ROUND(ROUND(F38*IF(E38="PHP",'03_逐品成本'!E6,1),10),2),"") | M38: =IF(AND(N38="完整",ISNUMBER('03_逐品成本'!E6),'03_逐品成本'!E6>0),ROUND(ROUND(IF(ISNUMBER(G38),G38,F38)*1*IF(E38="PHP",'03_逐品成本'!E6*0.95,1),10),2),"") | N38: =IF(AND(ISNUMBER(F38),F38>=0,OR(E38="PHP",E38="CNY"),OR(H38="已核实",H38="不适用"),I38<>"",J38<>"",ISNUMBER(K38),K38>='00_审核入口'!$F$2,OR(H38<>"不适用",F38=0),OR(G38="",AND(ISNUMBER(G38),G38>=0))),"完整","待补证") -> 待补证
A39: C02 | B39: 行李箱衣物分装收纳套装 | C39: overhead | D39: 固定运营成本分摊 | H39: 待核实 | L39: =IF(AND(N39="完整",ISNUMBER('03_逐品成本'!E6),'03_逐品成本'!E6>0),ROUND(ROUND(F39*IF(E39="PHP",'03_逐品成本'!E6,1),10),2),"") | M39: =IF(AND(N39="完整",ISNUMBER('03_逐品成本'!E6),'03_逐品成本'!E6>0),ROUND(ROUND(IF(ISNUMBER(G39),G39,F39)*1*IF(E39="PHP",'03_逐品成本'!E6*0.95,1),10),2),"") | N39: =IF(AND(ISNUMBER(F39),F39>=0,OR(E39="PHP",E39="CNY"),OR(H39="已核实",H39="不适用",H39="预算"),I39<>"",J39<>"",ISNUMBER(K39),K39>='00_审核入口'!$F$2,OR(H39<>"不适用",F39=0),OR(G39="",AND(ISNUMBER(G39),G39>=0))),"完整","待补证") -> 待补证
A40: C02 | B40: 行李箱衣物分装收纳套装 | C40: other | D40: 其他有说明费用 | H40: 待核实 | L40: =IF(AND(N40="完整",ISNUMBER('03_逐品成本'!E6),'03_逐品成本'!E6>0),ROUND(ROUND(F40*IF(E40="PHP",'03_逐品成本'!E6,1),10),2),"") | M40: =IF(AND(N40="完整",ISNUMBER('03_逐品成本'!E6),'03_逐品成本'!E6>0),ROUND(ROUND(IF(ISNUMBER(G40),G40,F40)*1*IF(E40="PHP",'03_逐品成本'!E6*0.95,1),10),2),"") | N40: =IF(AND(ISNUMBER(F40),F40>=0,OR(E40="PHP",E40="CNY"),OR(H40="已核实",H40="不适用",H40="预算"),I40<>"",J40<>"",ISNUMBER(K40),K40>='00_审核入口'!$F$2,OR(H40<>"不适用",F40=0),OR(G40="",AND(ISNUMBER(G40),G40>=0))),"完整","待补证") -> 待补证
A41: C03 | B41: 挂钩式旅行洗漱收纳包 | C41: commission | D41: 适用跨境佣金 | H41: 待核实 | L41: =IF(AND(N41="完整",ISNUMBER('03_逐品成本'!E7),'03_逐品成本'!E7>0),ROUND(ROUND(F41*IF(E41="PHP",'03_逐品成本'!E7,1),10),2),"") | M41: =IF(AND(N41="完整",ISNUMBER('03_逐品成本'!E7),'03_逐品成本'!E7>0),ROUND(ROUND(IF(ISNUMBER(G41),G41,F41)*1*IF(E41="PHP",'03_逐品成本'!E7*0.95,1),10),2),"") | N41: =IF(AND(ISNUMBER(F41),F41>=0,OR(E41="PHP",E41="CNY"),OR(H41="已核实",H41="不适用"),I41<>"",J41<>"",ISNUMBER(K41),K41>='00_审核入口'!$F$2,OR(H41<>"不适用",F41=0),OR(G41="",AND(ISNUMBER(G41),G41>=0))),"完整","待补证") -> 待补证
A42: C03 | B42: 挂钩式旅行洗漱收纳包 | C42: transaction | D42: 交易费（含实际支付方式） | H42: 待核实 | L42: =IF(AND(N42="完整",ISNUMBER('03_逐品成本'!E7),'03_逐品成本'!E7>0),ROUND(ROUND(F42*IF(E42="PHP",'03_逐品成本'!E7,1),10),2),"") | M42: =IF(AND(N42="完整",ISNUMBER('03_逐品成本'!E7),'03_逐品成本'!E7>0),ROUND(ROUND(IF(ISNUMBER(G42),G42,F42)*1*IF(E42="PHP",'03_逐品成本'!E7*0.95,1),10),2),"") | N42: =IF(AND(ISNUMBER(F42),F42>=0,OR(E42="PHP",E42="CNY"),OR(H42="已核实",H42="不适用"),I42<>"",J42<>"",ISNUMBER(K42),K42>='00_审核入口'!$F$2,OR(H42<>"不适用",F42=0),OR(G42="",AND(ISNUMBER(G42),G42>=0)),ISNUMBER(G42),G42>=0),"完整","待补证") -> 待补证
A43: C03 | B43: 挂钩式旅行洗漱收纳包 | C43: installment_extra | D43: 额外分期项目费 | H43: 待核实 | L43: =IF(AND(N43="完整",ISNUMBER('03_逐品成本'!E7),'03_逐品成本'!E7>0),ROUND(ROUND(F43*IF(E43="PHP",'03_逐品成本'!E7,1),10),2),"") | M43: =IF(AND(N43="完整",ISNUMBER('03_逐品成本'!E7),'03_逐品成本'!E7>0),ROUND(ROUND(IF(ISNUMBER(G43),G43,F43)*1*IF(E43="PHP",'03_逐品成本'!E7*0.95,1),10),2),"") | N43: =IF(AND(ISNUMBER(F43),F43>=0,OR(E43="PHP",E43="CNY"),OR(H43="已核实",H43="不适用"),I43<>"",J43<>"",ISNUMBER(K43),K43>='00_审核入口'!$F$2,OR(H43<>"不适用",F43=0),OR(G43="",AND(ISNUMBER(G43),G43>=0))),"完整","待补证") -> 待补证
A44: C03 | B44: 挂钩式旅行洗漱收纳包 | C44: growth | D44: 卖家增长费 | H44: 待核实 | L44: =IF(AND(N44="完整",ISNUMBER('03_逐品成本'!E7),'03_逐品成本'!E7>0),ROUND(ROUND(F44*IF(E44="PHP",'03_逐品成本'!E7,1),10),2),"") | M44: =IF(AND(N44="完整",ISNUMBER('03_逐品成本'!E7),'03_逐品成本'!E7>0),ROUND(ROUND(IF(ISNUMBER(G44),G44,F44)*1*IF(E44="PHP",'03_逐品成本'!E7*0.95,1),10),2),"") | N44: =IF(AND(ISNUMBER(F44),F44>=0,OR(E44="PHP",E44="CNY"),OR(H44="已核实",H44="不适用"),I44<>"",J44<>"",ISNUMBER(K44),K44>='00_审核入口'!$F$2,OR(H44<>"不适用",F44=0),OR(G44="",AND(ISNUMBER(G44),G44>=0))),"完整","待补证") -> 待补证
A45: C03 | B45: 挂钩式旅行洗漱收纳包 | C45: platform_shipping | D45: 平台运费计划费 | H45: 待核实 | L45: =IF(AND(N45="完整",ISNUMBER('03_逐品成本'!E7),'03_逐品成本'!E7>0),ROUND(ROUND(F45*IF(E45="PHP",'03_逐品成本'!E7,1),10),2),"") | M45: =IF(AND(N45="完整",ISNUMBER('03_逐品成本'!E7),'03_逐品成本'!E7>0),ROUND(ROUND(IF(ISNUMBER(G45),G45,F45)*1*IF(E45="PHP",'03_逐品成本'!E7*0.95,1),10),2),"") | N45: =IF(AND(ISNUMBER(F45),F45>=0,OR(E45="PHP",E45="CNY"),OR(H45="已核实",H45="不适用"),I45<>"",J45<>"",ISNUMBER(K45),K45>='00_审核入口'!$F$2,OR(H45<>"不适用",F45=0),OR(G45="",AND(ISNUMBER(G45),G45>=0))),"完整","待补证") -> 待补证
A46: C03 | B46: 挂钩式旅行洗漱收纳包 | C46: order_processing | D46: 订单处理费 | H46: 待核实 | L46: =IF(AND(N46="完整",ISNUMBER('03_逐品成本'!E7),'03_逐品成本'!E7>0),ROUND(ROUND(F46*IF(E46="PHP",'03_逐品成本'!E7,1),10),2),"") | M46: =IF(AND(N46="完整",ISNUMBER('03_逐品成本'!E7),'03_逐品成本'!E7>0),ROUND(ROUND(IF(ISNUMBER(G46),G46,F46)*1*IF(E46="PHP",'03_逐品成本'!E7*0.95,1),10),2),"") | N46: =IF(AND(ISNUMBER(F46),F46>=0,OR(E46="PHP",E46="CNY"),OR(H46="已核实",H46="不适用"),I46<>"",J46<>"",ISNUMBER(K46),K46>='00_审核入口'!$F$2,OR(H46<>"不适用",F46=0),OR(G46="",AND(ISNUMBER(G46),G46>=0))),"完整","待补证") -> 待补证
A47: C03 | B47: 挂钩式旅行洗漱收纳包 | C47: preorder | D47: 预售及其他平台服务费 | H47: 待核实 | L47: =IF(AND(N47="完整",ISNUMBER('03_逐品成本'!E7),'03_逐品成本'!E7>0),ROUND(ROUND(F47*IF(E47="PHP",'03_逐品成本'!E7,1),10),2),"") | M47: =IF(AND(N47="完整",ISNUMBER('03_逐品成本'!E7),'03_逐品成本'!E7>0),ROUND(ROUND(IF(ISNUMBER(G47),G47,F47)*1*IF(E47="PHP",'03_逐品成本'!E7*0.95,1),10),2),"") | N47: =IF(AND(ISNUMBER(F47),F47>=0,OR(E47="PHP",E47="CNY"),OR(H47="已核实",H47="不适用"),I47<>"",J47<>"",ISNUMBER(K47),K47>='00_审核入口'!$F$2,OR(H47<>"不适用",F47=0),OR(G47="",AND(ISNUMBER(G47),G47>=0))),"完整","待补证") -> 待补证
A48: C03 | B48: 挂钩式旅行洗漱收纳包 | C48: activities | D48: MDV/返币/直播等活动费 | H48: 待核实 | L48: =IF(AND(N48="完整",ISNUMBER('03_逐品成本'!E7),'03_逐品成本'!E7>0),ROUND(ROUND(F48*IF(E48="PHP",'03_逐品成本'!E7,1),10),2),"") | M48: =IF(AND(N48="完整",ISNUMBER('03_逐品成本'!E7),'03_逐品成本'!E7>0),ROUND(ROUND(IF(ISNUMBER(G48),G48,F48)*1*IF(E48="PHP",'03_逐品成本'!E7*0.95,1),10),2),"") | N48: =IF(AND(ISNUMBER(F48),F48>=0,OR(E48="PHP",E48="CNY"),OR(H48="已核实",H48="不适用"),I48<>"",J48<>"",ISNUMBER(K48),K48>='00_审核入口'!$F$2,OR(H48<>"不适用",F48=0),OR(G48="",AND(ISNUMBER(G48),G48>=0))),"完整","待补证") -> 待补证
A49: C03 | B49: 挂钩式旅行洗漱收纳包 | C49: domestic | D49: 中国境内运费 | H49: 待核实 | L49: =IF(AND(N49="完整",ISNUMBER('03_逐品成本'!E7),'03_逐品成本'!E7>0),ROUND(ROUND(F49*IF(E49="PHP",'03_逐品成本'!E7,1),10),2),"") | M49: =IF(AND(N49="完整",ISNUMBER('03_逐品成本'!E7),'03_逐品成本'!E7>0),ROUND(ROUND(IF(ISNUMBER(G49),G49,F49)*1.15*IF(E49="PHP",'03_逐品成本'!E7*0.95,1),10),2),"") | N49: =IF(AND(ISNUMBER(F49),F49>=0,OR(E49="PHP",E49="CNY"),OR(H49="已核实",H49="不适用"),I49<>"",J49<>"",ISNUMBER(K49),K49>='00_审核入口'!$F$2,OR(H49<>"不适用",F49=0),OR(G49="",AND(ISNUMBER(G49),G49>=0))),"完整","待补证") -> 待补证
A50: C03 | B50: 挂钩式旅行洗漱收纳包 | C50: warehouse_pack | D50: 云仓/验货/贴标/仓储/包材 | H50: 待核实 | L50: =IF(AND(N50="完整",ISNUMBER('03_逐品成本'!E7),'03_逐品成本'!E7>0),ROUND(ROUND(F50*IF(E50="PHP",'03_逐品成本'!E7,1),10),2),"") | M50: =IF(AND(N50="完整",ISNUMBER('03_逐品成本'!E7),'03_逐品成本'!E7>0),ROUND(ROUND(IF(ISNUMBER(G50),G50,F50)*1.15*IF(E50="PHP",'03_逐品成本'!E7*0.95,1),10),2),"") | N50: =IF(AND(ISNUMBER(F50),F50>=0,OR(E50="PHP",E50="CNY"),OR(H50="已核实",H50="不适用"),I50<>"",J50<>"",ISNUMBER(K50),K50>='00_审核入口'!$F$2,OR(H50<>"不适用",F50=0),OR(G50="",AND(ISNUMBER(G50),G50>=0))),"完整","待补证") -> 待补证
A51: C03 | B51: 挂钩式旅行洗漱收纳包 | C51: sls | D51: SLS卖家净国际物流 | H51: 待核实 | L51: =IF(AND(N51="完整",ISNUMBER('03_逐品成本'!E7),'03_逐品成本'!E7>0),ROUND(ROUND(F51*IF(E51="PHP",'03_逐品成本'!E7,1),10),2),"") | M51: =IF(AND(N51="完整",ISNUMBER('03_逐品成本'!E7),'03_逐品成本'!E7>0),ROUND(ROUND(IF(ISNUMBER(G51),G51,F51)*1.15*IF(E51="PHP",'03_逐品成本'!E7*0.95,1),10),2),"") | N51: =IF(AND(ISNUMBER(F51),F51>=0,OR(E51="PHP",E51="CNY"),OR(H51="已核实",H51="不适用"),I51<>"",J51<>"",ISNUMBER(K51),K51>='00_审核入口'!$F$2,OR(H51<>"不适用",F51=0),OR(G51="",AND(ISNUMBER(G51),G51>=0))),"完整","待补证") -> 待补证
A52: C03 | B52: 挂钩式旅行洗漱收纳包 | C52: ads | D52: 广告预算分摊 | H52: 待核实 | L52: =IF(AND(N52="完整",ISNUMBER('03_逐品成本'!E7),'03_逐品成本'!E7>0),ROUND(ROUND(F52*IF(E52="PHP",'03_逐品成本'!E7,1),10),2),"") | M52: =IF(AND(N52="完整",ISNUMBER('03_逐品成本'!E7),'03_逐品成本'!E7>0),ROUND(ROUND(IF(ISNUMBER(G52),G52,F52)*1*IF(E52="PHP",'03_逐品成本'!E7*0.95,1),10),2),"") | N52: =IF(AND(ISNUMBER(F52),F52>=0,OR(E52="PHP",E52="CNY"),OR(H52="已核实",H52="不适用",H52="预算"),I52<>"",J52<>"",ISNUMBER(K52),K52>='00_审核入口'!$F$2,OR(H52<>"不适用",F52=0),OR(G52="",AND(ISNUMBER(G52),G52>=0))),"完整","待补证") -> 待补证
A53: C03 | B53: 挂钩式旅行洗漱收纳包 | C53: affiliate | D53: 联盟/达人分摊 | H53: 待核实 | L53: =IF(AND(N53="完整",ISNUMBER('03_逐品成本'!E7),'03_逐品成本'!E7>0),ROUND(ROUND(F53*IF(E53="PHP",'03_逐品成本'!E7,1),10),2),"") | M53: =IF(AND(N53="完整",ISNUMBER('03_逐品成本'!E7),'03_逐品成本'!E7>0),ROUND(ROUND(IF(ISNUMBER(G53),G53,F53)*1*IF(E53="PHP",'03_逐品成本'!E7*0.95,1),10),2),"") | N53: =IF(AND(ISNUMBER(F53),F53>=0,OR(E53="PHP",E53="CNY"),OR(H53="已核实",H53="不适用",H53="预算"),I53<>"",J53<>"",ISNUMBER(K53),K53>='00_审核入口'!$F$2,OR(H53<>"不适用",F53=0),OR(G53="",AND(ISNUMBER(G53),G53>=0))),"完整","待补证") -> 待补证
A54: C03 | B54: 挂钩式旅行洗漱收纳包 | C54: returns | D54: 售后退款/拒收/破损净损失准备 | H54: 待核实 | L54: =IF(AND(N54="完整",ISNUMBER('03_逐品成本'!E7),'03_逐品成本'!E7>0),ROUND(ROUND(F54*IF(E54="PHP",'03_逐品成本'!E7,1),10),2),"") | M54: =IF(AND(N54="完整",ISNUMBER('03_逐品成本'!E7),'03_逐品成本'!E7>0),ROUND(ROUND(IF(ISNUMBER(G54),G54,F54)*1*IF(E54="PHP",'03_逐品成本'!E7*0.95,1),10),2),"") | N54: =IF(AND(ISNUMBER(F54),F54>=0,OR(E54="PHP",E54="CNY"),OR(H54="已核实",H54="不适用",H54="预算"),I54<>"",J54<>"",ISNUMBER(K54),K54>='00_审核入口'!$F$2,OR(H54<>"不适用",F54=0),OR(G54="",AND(ISNUMBER(G54),G54>=0))),"完整","待补证") -> 待补证
A55: C03 | B55: 挂钩式旅行洗漱收纳包 | C55: collection | D55: 收款/换汇/提现 | H55: 待核实 | L55: =IF(AND(N55="完整",ISNUMBER('03_逐品成本'!E7),'03_逐品成本'!E7>0),ROUND(ROUND(F55*IF(E55="PHP",'03_逐品成本'!E7,1),10),2),"") | M55: =IF(AND(N55="完整",ISNUMBER('03_逐品成本'!E7),'03_逐品成本'!E7>0),ROUND(ROUND(IF(ISNUMBER(G55),G55,F55)*1*IF(E55="PHP",'03_逐品成本'!E7*0.95,1),10),2),"") | N55: =IF(AND(ISNUMBER(F55),F55>=0,OR(E55="PHP",E55="CNY"),OR(H55="已核实",H55="不适用"),I55<>"",J55<>"",ISNUMBER(K55),K55>='00_审核入口'!$F$2,OR(H55<>"不适用",F55=0),OR(G55="",AND(ISNUMBER(G55),G55>=0))),"完整","待补证") -> 待补证
A56: C03 | B56: 挂钩式旅行洗漱收纳包 | C56: tax | D56: 其他不可抵扣税费 | H56: 待核实 | L56: =IF(AND(N56="完整",ISNUMBER('03_逐品成本'!E7),'03_逐品成本'!E7>0),ROUND(ROUND(F56*IF(E56="PHP",'03_逐品成本'!E7,1),10),2),"") | M56: =IF(AND(N56="完整",ISNUMBER('03_逐品成本'!E7),'03_逐品成本'!E7>0),ROUND(ROUND(IF(ISNUMBER(G56),G56,F56)*1*IF(E56="PHP",'03_逐品成本'!E7*0.95,1),10),2),"") | N56: =IF(AND(ISNUMBER(F56),F56>=0,OR(E56="PHP",E56="CNY"),OR(H56="已核实",H56="不适用"),I56<>"",J56<>"",ISNUMBER(K56),K56>='00_审核入口'!$F$2,OR(H56<>"不适用",F56=0),OR(G56="",AND(ISNUMBER(G56),G56>=0))),"完整","待补证") -> 待补证
A57: C03 | B57: 挂钩式旅行洗漱收纳包 | C57: overhead | D57: 固定运营成本分摊 | H57: 待核实 | L57: =IF(AND(N57="完整",ISNUMBER('03_逐品成本'!E7),'03_逐品成本'!E7>0),ROUND(ROUND(F57*IF(E57="PHP",'03_逐品成本'!E7,1),10),2),"") | M57: =IF(AND(N57="完整",ISNUMBER('03_逐品成本'!E7),'03_逐品成本'!E7>0),ROUND(ROUND(IF(ISNUMBER(G57),G57,F57)*1*IF(E57="PHP",'03_逐品成本'!E7*0.95,1),10),2),"") | N57: =IF(AND(ISNUMBER(F57),F57>=0,OR(E57="PHP",E57="CNY"),OR(H57="已核实",H57="不适用",H57="预算"),I57<>"",J57<>"",ISNUMBER(K57),K57>='00_审核入口'!$F$2,OR(H57<>"不适用",F57=0),OR(G57="",AND(ISNUMBER(G57),G57>=0))),"完整","待补证") -> 待补证
A58: C03 | B58: 挂钩式旅行洗漱收纳包 | C58: other | D58: 其他有说明费用 | H58: 待核实 | L58: =IF(AND(N58="完整",ISNUMBER('03_逐品成本'!E7),'03_逐品成本'!E7>0),ROUND(ROUND(F58*IF(E58="PHP",'03_逐品成本'!E7,1),10),2),"") | M58: =IF(AND(N58="完整",ISNUMBER('03_逐品成本'!E7),'03_逐品成本'!E7>0),ROUND(ROUND(IF(ISNUMBER(G58),G58,F58)*1*IF(E58="PHP",'03_逐品成本'!E7*0.95,1),10),2),"") | N58: =IF(AND(ISNUMBER(F58),F58>=0,OR(E58="PHP",E58="CNY"),OR(H58="已核实",H58="不适用",H58="预算"),I58<>"",J58<>"",ISNUMBER(K58),K58>='00_审核入口'!$F$2,OR(H58<>"不适用",F58=0),OR(G58="",AND(ISNUMBER(G58),G58>=0))),"完整","待补证") -> 待补证
A59: C04 | B59: 抽绳鞋子防尘收纳袋 | C59: commission | D59: 适用跨境佣金 | H59: 待核实 | L59: =IF(AND(N59="完整",ISNUMBER('03_逐品成本'!E8),'03_逐品成本'!E8>0),ROUND(ROUND(F59*IF(E59="PHP",'03_逐品成本'!E8,1),10),2),"") | M59: =IF(AND(N59="完整",ISNUMBER('03_逐品成本'!E8),'03_逐品成本'!E8>0),ROUND(ROUND(IF(ISNUMBER(G59),G59,F59)*1*IF(E59="PHP",'03_逐品成本'!E8*0.95,1),10),2),"") | N59: =IF(AND(ISNUMBER(F59),F59>=0,OR(E59="PHP",E59="CNY"),OR(H59="已核实",H59="不适用"),I59<>"",J59<>"",ISNUMBER(K59),K59>='00_审核入口'!$F$2,OR(H59<>"不适用",F59=0),OR(G59="",AND(ISNUMBER(G59),G59>=0))),"完整","待补证") -> 待补证
A60: C04 | B60: 抽绳鞋子防尘收纳袋 | C60: transaction | D60: 交易费（含实际支付方式） | H60: 待核实 | L60: =IF(AND(N60="完整",ISNUMBER('03_逐品成本'!E8),'03_逐品成本'!E8>0),ROUND(ROUND(F60*IF(E60="PHP",'03_逐品成本'!E8,1),10),2),"") | M60: =IF(AND(N60="完整",ISNUMBER('03_逐品成本'!E8),'03_逐品成本'!E8>0),ROUND(ROUND(IF(ISNUMBER(G60),G60,F60)*1*IF(E60="PHP",'03_逐品成本'!E8*0.95,1),10),2),"") | N60: =IF(AND(ISNUMBER(F60),F60>=0,OR(E60="PHP",E60="CNY"),OR(H60="已核实",H60="不适用"),I60<>"",J60<>"",ISNUMBER(K60),K60>='00_审核入口'!$F$2,OR(H60<>"不适用",F60=0),OR(G60="",AND(ISNUMBER(G60),G60>=0)),ISNUMBER(G60),G60>=0),"完整","待补证") -> 待补证
A61: C04 | B61: 抽绳鞋子防尘收纳袋 | C61: installment_extra | D61: 额外分期项目费 | H61: 待核实 | L61: =IF(AND(N61="完整",ISNUMBER('03_逐品成本'!E8),'03_逐品成本'!E8>0),ROUND(ROUND(F61*IF(E61="PHP",'03_逐品成本'!E8,1),10),2),"") | M61: =IF(AND(N61="完整",ISNUMBER('03_逐品成本'!E8),'03_逐品成本'!E8>0),ROUND(ROUND(IF(ISNUMBER(G61),G61,F61)*1*IF(E61="PHP",'03_逐品成本'!E8*0.95,1),10),2),"") | N61: =IF(AND(ISNUMBER(F61),F61>=0,OR(E61="PHP",E61="CNY"),OR(H61="已核实",H61="不适用"),I61<>"",J61<>"",ISNUMBER(K61),K61>='00_审核入口'!$F$2,OR(H61<>"不适用",F61=0),OR(G61="",AND(ISNUMBER(G61),G61>=0))),"完整","待补证") -> 待补证
A62: C04 | B62: 抽绳鞋子防尘收纳袋 | C62: growth | D62: 卖家增长费 | H62: 待核实 | L62: =IF(AND(N62="完整",ISNUMBER('03_逐品成本'!E8),'03_逐品成本'!E8>0),ROUND(ROUND(F62*IF(E62="PHP",'03_逐品成本'!E8,1),10),2),"") | M62: =IF(AND(N62="完整",ISNUMBER('03_逐品成本'!E8),'03_逐品成本'!E8>0),ROUND(ROUND(IF(ISNUMBER(G62),G62,F62)*1*IF(E62="PHP",'03_逐品成本'!E8*0.95,1),10),2),"") | N62: =IF(AND(ISNUMBER(F62),F62>=0,OR(E62="PHP",E62="CNY"),OR(H62="已核实",H62="不适用"),I62<>"",J62<>"",ISNUMBER(K62),K62>='00_审核入口'!$F$2,OR(H62<>"不适用",F62=0),OR(G62="",AND(ISNUMBER(G62),G62>=0))),"完整","待补证") -> 待补证
A63: C04 | B63: 抽绳鞋子防尘收纳袋 | C63: platform_shipping | D63: 平台运费计划费 | H63: 待核实 | L63: =IF(AND(N63="完整",ISNUMBER('03_逐品成本'!E8),'03_逐品成本'!E8>0),ROUND(ROUND(F63*IF(E63="PHP",'03_逐品成本'!E8,1),10),2),"") | M63: =IF(AND(N63="完整",ISNUMBER('03_逐品成本'!E8),'03_逐品成本'!E8>0),ROUND(ROUND(IF(ISNUMBER(G63),G63,F63)*1*IF(E63="PHP",'03_逐品成本'!E8*0.95,1),10),2),"") | N63: =IF(AND(ISNUMBER(F63),F63>=0,OR(E63="PHP",E63="CNY"),OR(H63="已核实",H63="不适用"),I63<>"",J63<>"",ISNUMBER(K63),K63>='00_审核入口'!$F$2,OR(H63<>"不适用",F63=0),OR(G63="",AND(ISNUMBER(G63),G63>=0))),"完整","待补证") -> 待补证
A64: C04 | B64: 抽绳鞋子防尘收纳袋 | C64: order_processing | D64: 订单处理费 | H64: 待核实 | L64: =IF(AND(N64="完整",ISNUMBER('03_逐品成本'!E8),'03_逐品成本'!E8>0),ROUND(ROUND(F64*IF(E64="PHP",'03_逐品成本'!E8,1),10),2),"") | M64: =IF(AND(N64="完整",ISNUMBER('03_逐品成本'!E8),'03_逐品成本'!E8>0),ROUND(ROUND(IF(ISNUMBER(G64),G64,F64)*1*IF(E64="PHP",'03_逐品成本'!E8*0.95,1),10),2),"") | N64: =IF(AND(ISNUMBER(F64),F64>=0,OR(E64="PHP",E64="CNY"),OR(H64="已核实",H64="不适用"),I64<>"",J64<>"",ISNUMBER(K64),K64>='00_审核入口'!$F$2,OR(H64<>"不适用",F64=0),OR(G64="",AND(ISNUMBER(G64),G64>=0))),"完整","待补证") -> 待补证
A65: C04 | B65: 抽绳鞋子防尘收纳袋 | C65: preorder | D65: 预售及其他平台服务费 | H65: 待核实 | L65: =IF(AND(N65="完整",ISNUMBER('03_逐品成本'!E8),'03_逐品成本'!E8>0),ROUND(ROUND(F65*IF(E65="PHP",'03_逐品成本'!E8,1),10),2),"") | M65: =IF(AND(N65="完整",ISNUMBER('03_逐品成本'!E8),'03_逐品成本'!E8>0),ROUND(ROUND(IF(ISNUMBER(G65),G65,F65)*1*IF(E65="PHP",'03_逐品成本'!E8*0.95,1),10),2),"") | N65: =IF(AND(ISNUMBER(F65),F65>=0,OR(E65="PHP",E65="CNY"),OR(H65="已核实",H65="不适用"),I65<>"",J65<>"",ISNUMBER(K65),K65>='00_审核入口'!$F$2,OR(H65<>"不适用",F65=0),OR(G65="",AND(ISNUMBER(G65),G65>=0))),"完整","待补证") -> 待补证
A66: C04 | B66: 抽绳鞋子防尘收纳袋 | C66: activities | D66: MDV/返币/直播等活动费 | H66: 待核实 | L66: =IF(AND(N66="完整",ISNUMBER('03_逐品成本'!E8),'03_逐品成本'!E8>0),ROUND(ROUND(F66*IF(E66="PHP",'03_逐品成本'!E8,1),10),2),"") | M66: =IF(AND(N66="完整",ISNUMBER('03_逐品成本'!E8),'03_逐品成本'!E8>0),ROUND(ROUND(IF(ISNUMBER(G66),G66,F66)*1*IF(E66="PHP",'03_逐品成本'!E8*0.95,1),10),2),"") | N66: =IF(AND(ISNUMBER(F66),F66>=0,OR(E66="PHP",E66="CNY"),OR(H66="已核实",H66="不适用"),I66<>"",J66<>"",ISNUMBER(K66),K66>='00_审核入口'!$F$2,OR(H66<>"不适用",F66=0),OR(G66="",AND(ISNUMBER(G66),G66>=0))),"完整","待补证") -> 待补证
A67: C04 | B67: 抽绳鞋子防尘收纳袋 | C67: domestic | D67: 中国境内运费 | H67: 待核实 | L67: =IF(AND(N67="完整",ISNUMBER('03_逐品成本'!E8),'03_逐品成本'!E8>0),ROUND(ROUND(F67*IF(E67="PHP",'03_逐品成本'!E8,1),10),2),"") | M67: =IF(AND(N67="完整",ISNUMBER('03_逐品成本'!E8),'03_逐品成本'!E8>0),ROUND(ROUND(IF(ISNUMBER(G67),G67,F67)*1.15*IF(E67="PHP",'03_逐品成本'!E8*0.95,1),10),2),"") | N67: =IF(AND(ISNUMBER(F67),F67>=0,OR(E67="PHP",E67="CNY"),OR(H67="已核实",H67="不适用"),I67<>"",J67<>"",ISNUMBER(K67),K67>='00_审核入口'!$F$2,OR(H67<>"不适用",F67=0),OR(G67="",AND(ISNUMBER(G67),G67>=0))),"完整","待补证") -> 待补证
A68: C04 | B68: 抽绳鞋子防尘收纳袋 | C68: warehouse_pack | D68: 云仓/验货/贴标/仓储/包材 | H68: 待核实 | L68: =IF(AND(N68="完整",ISNUMBER('03_逐品成本'!E8),'03_逐品成本'!E8>0),ROUND(ROUND(F68*IF(E68="PHP",'03_逐品成本'!E8,1),10),2),"") | M68: =IF(AND(N68="完整",ISNUMBER('03_逐品成本'!E8),'03_逐品成本'!E8>0),ROUND(ROUND(IF(ISNUMBER(G68),G68,F68)*1.15*IF(E68="PHP",'03_逐品成本'!E8*0.95,1),10),2),"") | N68: =IF(AND(ISNUMBER(F68),F68>=0,OR(E68="PHP",E68="CNY"),OR(H68="已核实",H68="不适用"),I68<>"",J68<>"",ISNUMBER(K68),K68>='00_审核入口'!$F$2,OR(H68<>"不适用",F68=0),OR(G68="",AND(ISNUMBER(G68),G68>=0))),"完整","待补证") -> 待补证
A69: C04 | B69: 抽绳鞋子防尘收纳袋 | C69: sls | D69: SLS卖家净国际物流 | H69: 待核实 | L69: =IF(AND(N69="完整",ISNUMBER('03_逐品成本'!E8),'03_逐品成本'!E8>0),ROUND(ROUND(F69*IF(E69="PHP",'03_逐品成本'!E8,1),10),2),"") | M69: =IF(AND(N69="完整",ISNUMBER('03_逐品成本'!E8),'03_逐品成本'!E8>0),ROUND(ROUND(IF(ISNUMBER(G69),G69,F69)*1.15*IF(E69="PHP",'03_逐品成本'!E8*0.95,1),10),2),"") | N69: =IF(AND(ISNUMBER(F69),F69>=0,OR(E69="PHP",E69="CNY"),OR(H69="已核实",H69="不适用"),I69<>"",J69<>"",ISNUMBER(K69),K69>='00_审核入口'!$F$2,OR(H69<>"不适用",F69=0),OR(G69="",AND(ISNUMBER(G69),G69>=0))),"完整","待补证") -> 待补证
A70: C04 | B70: 抽绳鞋子防尘收纳袋 | C70: ads | D70: 广告预算分摊 | H70: 待核实 | L70: =IF(AND(N70="完整",ISNUMBER('03_逐品成本'!E8),'03_逐品成本'!E8>0),ROUND(ROUND(F70*IF(E70="PHP",'03_逐品成本'!E8,1),10),2),"") | M70: =IF(AND(N70="完整",ISNUMBER('03_逐品成本'!E8),'03_逐品成本'!E8>0),ROUND(ROUND(IF(ISNUMBER(G70),G70,F70)*1*IF(E70="PHP",'03_逐品成本'!E8*0.95,1),10),2),"") | N70: =IF(AND(ISNUMBER(F70),F70>=0,OR(E70="PHP",E70="CNY"),OR(H70="已核实",H70="不适用",H70="预算"),I70<>"",J70<>"",ISNUMBER(K70),K70>='00_审核入口'!$F$2,OR(H70<>"不适用",F70=0),OR(G70="",AND(ISNUMBER(G70),G70>=0))),"完整","待补证") -> 待补证
A71: C04 | B71: 抽绳鞋子防尘收纳袋 | C71: affiliate | D71: 联盟/达人分摊 | H71: 待核实 | L71: =IF(AND(N71="完整",ISNUMBER('03_逐品成本'!E8),'03_逐品成本'!E8>0),ROUND(ROUND(F71*IF(E71="PHP",'03_逐品成本'!E8,1),10),2),"") | M71: =IF(AND(N71="完整",ISNUMBER('03_逐品成本'!E8),'03_逐品成本'!E8>0),ROUND(ROUND(IF(ISNUMBER(G71),G71,F71)*1*IF(E71="PHP",'03_逐品成本'!E8*0.95,1),10),2),"") | N71: =IF(AND(ISNUMBER(F71),F71>=0,OR(E71="PHP",E71="CNY"),OR(H71="已核实",H71="不适用",H71="预算"),I71<>"",J71<>"",ISNUMBER(K71),K71>='00_审核入口'!$F$2,OR(H71<>"不适用",F71=0),OR(G71="",AND(ISNUMBER(G71),G71>=0))),"完整","待补证") -> 待补证
A72: C04 | B72: 抽绳鞋子防尘收纳袋 | C72: returns | D72: 售后退款/拒收/破损净损失准备 | H72: 待核实 | L72: =IF(AND(N72="完整",ISNUMBER('03_逐品成本'!E8),'03_逐品成本'!E8>0),ROUND(ROUND(F72*IF(E72="PHP",'03_逐品成本'!E8,1),10),2),"") | M72: =IF(AND(N72="完整",ISNUMBER('03_逐品成本'!E8),'03_逐品成本'!E8>0),ROUND(ROUND(IF(ISNUMBER(G72),G72,F72)*1*IF(E72="PHP",'03_逐品成本'!E8*0.95,1),10),2),"") | N72: =IF(AND(ISNUMBER(F72),F72>=0,OR(E72="PHP",E72="CNY"),OR(H72="已核实",H72="不适用",H72="预算"),I72<>"",J72<>"",ISNUMBER(K72),K72>='00_审核入口'!$F$2,OR(H72<>"不适用",F72=0),OR(G72="",AND(ISNUMBER(G72),G72>=0))),"完整","待补证") -> 待补证
A73: C04 | B73: 抽绳鞋子防尘收纳袋 | C73: collection | D73: 收款/换汇/提现 | H73: 待核实 | L73: =IF(AND(N73="完整",ISNUMBER('03_逐品成本'!E8),'03_逐品成本'!E8>0),ROUND(ROUND(F73*IF(E73="PHP",'03_逐品成本'!E8,1),10),2),"") | M73: =IF(AND(N73="完整",ISNUMBER('03_逐品成本'!E8),'03_逐品成本'!E8>0),ROUND(ROUND(IF(ISNUMBER(G73),G73,F73)*1*IF(E73="PHP",'03_逐品成本'!E8*0.95,1),10),2),"") | N73: =IF(AND(ISNUMBER(F73),F73>=0,OR(E73="PHP",E73="CNY"),OR(H73="已核实",H73="不适用"),I73<>"",J73<>"",ISNUMBER(K73),K73>='00_审核入口'!$F$2,OR(H73<>"不适用",F73=0),OR(G73="",AND(ISNUMBER(G73),G73>=0))),"完整","待补证") -> 待补证
A74: C04 | B74: 抽绳鞋子防尘收纳袋 | C74: tax | D74: 其他不可抵扣税费 | H74: 待核实 | L74: =IF(AND(N74="完整",ISNUMBER('03_逐品成本'!E8),'03_逐品成本'!E8>0),ROUND(ROUND(F74*IF(E74="PHP",'03_逐品成本'!E8,1),10),2),"") | M74: =IF(AND(N74="完整",ISNUMBER('03_逐品成本'!E8),'03_逐品成本'!E8>0),ROUND(ROUND(IF(ISNUMBER(G74),G74,F74)*1*IF(E74="PHP",'03_逐品成本'!E8*0.95,1),10),2),"") | N74: =IF(AND(ISNUMBER(F74),F74>=0,OR(E74="PHP",E74="CNY"),OR(H74="已核实",H74="不适用"),I74<>"",J74<>"",ISNUMBER(K74),K74>='00_审核入口'!$F$2,OR(H74<>"不适用",F74=0),OR(G74="",AND(ISNUMBER(G74),G74>=0))),"完整","待补证") -> 待补证
A75: C04 | B75: 抽绳鞋子防尘收纳袋 | C75: overhead | D75: 固定运营成本分摊 | H75: 待核实 | L75: =IF(AND(N75="完整",ISNUMBER('03_逐品成本'!E8),'03_逐品成本'!E8>0),ROUND(ROUND(F75*IF(E75="PHP",'03_逐品成本'!E8,1),10),2),"") | M75: =IF(AND(N75="完整",ISNUMBER('03_逐品成本'!E8),'03_逐品成本'!E8>0),ROUND(ROUND(IF(ISNUMBER(G75),G75,F75)*1*IF(E75="PHP",'03_逐品成本'!E8*0.95,1),10),2),"") | N75: =IF(AND(ISNUMBER(F75),F75>=0,OR(E75="PHP",E75="CNY"),OR(H75="已核实",H75="不适用",H75="预算"),I75<>"",J75<>"",ISNUMBER(K75),K75>='00_审核入口'!$F$2,OR(H75<>"不适用",F75=0),OR(G75="",AND(ISNUMBER(G75),G75>=0))),"完整","待补证") -> 待补证
A76: C04 | B76: 抽绳鞋子防尘收纳袋 | C76: other | D76: 其他有说明费用 | H76: 待核实 | L76: =IF(AND(N76="完整",ISNUMBER('03_逐品成本'!E8),'03_逐品成本'!E8>0),ROUND(ROUND(F76*IF(E76="PHP",'03_逐品成本'!E8,1),10),2),"") | M76: =IF(AND(N76="完整",ISNUMBER('03_逐品成本'!E8),'03_逐品成本'!E8>0),ROUND(ROUND(IF(ISNUMBER(G76),G76,F76)*1*IF(E76="PHP",'03_逐品成本'!E8*0.95,1),10),2),"") | N76: =IF(AND(ISNUMBER(F76),F76>=0,OR(E76="PHP",E76="CNY"),OR(H76="已核实",H76="不适用",H76="预算"),I76<>"",J76<>"",ISNUMBER(K76),K76>='00_审核入口'!$F$2,OR(H76<>"不适用",F76=0),OR(G76="",AND(ISNUMBER(G76),G76>=0))),"完整","待补证") -> 待补证
A77: C05 | B77: 衣柜悬挂手袋收纳袋 | C77: commission | D77: 适用跨境佣金 | H77: 待核实 | L77: =IF(AND(N77="完整",ISNUMBER('03_逐品成本'!E9),'03_逐品成本'!E9>0),ROUND(ROUND(F77*IF(E77="PHP",'03_逐品成本'!E9,1),10),2),"") | M77: =IF(AND(N77="完整",ISNUMBER('03_逐品成本'!E9),'03_逐品成本'!E9>0),ROUND(ROUND(IF(ISNUMBER(G77),G77,F77)*1*IF(E77="PHP",'03_逐品成本'!E9*0.95,1),10),2),"") | N77: =IF(AND(ISNUMBER(F77),F77>=0,OR(E77="PHP",E77="CNY"),OR(H77="已核实",H77="不适用"),I77<>"",J77<>"",ISNUMBER(K77),K77>='00_审核入口'!$F$2,OR(H77<>"不适用",F77=0),OR(G77="",AND(ISNUMBER(G77),G77>=0))),"完整","待补证") -> 待补证
A78: C05 | B78: 衣柜悬挂手袋收纳袋 | C78: transaction | D78: 交易费（含实际支付方式） | H78: 待核实 | L78: =IF(AND(N78="完整",ISNUMBER('03_逐品成本'!E9),'03_逐品成本'!E9>0),ROUND(ROUND(F78*IF(E78="PHP",'03_逐品成本'!E9,1),10),2),"") | M78: =IF(AND(N78="完整",ISNUMBER('03_逐品成本'!E9),'03_逐品成本'!E9>0),ROUND(ROUND(IF(ISNUMBER(G78),G78,F78)*1*IF(E78="PHP",'03_逐品成本'!E9*0.95,1),10),2),"") | N78: =IF(AND(ISNUMBER(F78),F78>=0,OR(E78="PHP",E78="CNY"),OR(H78="已核实",H78="不适用"),I78<>"",J78<>"",ISNUMBER(K78),K78>='00_审核入口'!$F$2,OR(H78<>"不适用",F78=0),OR(G78="",AND(ISNUMBER(G78),G78>=0)),ISNUMBER(G78),G78>=0),"完整","待补证") -> 待补证
A79: C05 | B79: 衣柜悬挂手袋收纳袋 | C79: installment_extra | D79: 额外分期项目费 | H79: 待核实 | L79: =IF(AND(N79="完整",ISNUMBER('03_逐品成本'!E9),'03_逐品成本'!E9>0),ROUND(ROUND(F79*IF(E79="PHP",'03_逐品成本'!E9,1),10),2),"") | M79: =IF(AND(N79="完整",ISNUMBER('03_逐品成本'!E9),'03_逐品成本'!E9>0),ROUND(ROUND(IF(ISNUMBER(G79),G79,F79)*1*IF(E79="PHP",'03_逐品成本'!E9*0.95,1),10),2),"") | N79: =IF(AND(ISNUMBER(F79),F79>=0,OR(E79="PHP",E79="CNY"),OR(H79="已核实",H79="不适用"),I79<>"",J79<>"",ISNUMBER(K79),K79>='00_审核入口'!$F$2,OR(H79<>"不适用",F79=0),OR(G79="",AND(ISNUMBER(G79),G79>=0))),"完整","待补证") -> 待补证
A80: C05 | B80: 衣柜悬挂手袋收纳袋 | C80: growth | D80: 卖家增长费 | H80: 待核实 | L80: =IF(AND(N80="完整",ISNUMBER('03_逐品成本'!E9),'03_逐品成本'!E9>0),ROUND(ROUND(F80*IF(E80="PHP",'03_逐品成本'!E9,1),10),2),"") | M80: =IF(AND(N80="完整",ISNUMBER('03_逐品成本'!E9),'03_逐品成本'!E9>0),ROUND(ROUND(IF(ISNUMBER(G80),G80,F80)*1*IF(E80="PHP",'03_逐品成本'!E9*0.95,1),10),2),"") | N80: =IF(AND(ISNUMBER(F80),F80>=0,OR(E80="PHP",E80="CNY"),OR(H80="已核实",H80="不适用"),I80<>"",J80<>"",ISNUMBER(K80),K80>='00_审核入口'!$F$2,OR(H80<>"不适用",F80=0),OR(G80="",AND(ISNUMBER(G80),G80>=0))),"完整","待补证") -> 待补证
A81: C05 | B81: 衣柜悬挂手袋收纳袋 | C81: platform_shipping | D81: 平台运费计划费 | H81: 待核实 | L81: =IF(AND(N81="完整",ISNUMBER('03_逐品成本'!E9),'03_逐品成本'!E9>0),ROUND(ROUND(F81*IF(E81="PHP",'03_逐品成本'!E9,1),10),2),"") | M81: =IF(AND(N81="完整",ISNUMBER('03_逐品成本'!E9),'03_逐品成本'!E9>0),ROUND(ROUND(IF(ISNUMBER(G81),G81,F81)*1*IF(E81="PHP",'03_逐品成本'!E9*0.95,1),10),2),"") | N81: =IF(AND(ISNUMBER(F81),F81>=0,OR(E81="PHP",E81="CNY"),OR(H81="已核实",H81="不适用"),I81<>"",J81<>"",ISNUMBER(K81),K81>='00_审核入口'!$F$2,OR(H81<>"不适用",F81=0),OR(G81="",AND(ISNUMBER(G81),G81>=0))),"完整","待补证") -> 待补证
A82: C05 | B82: 衣柜悬挂手袋收纳袋 | C82: order_processing | D82: 订单处理费 | H82: 待核实 | L82: =IF(AND(N82="完整",ISNUMBER('03_逐品成本'!E9),'03_逐品成本'!E9>0),ROUND(ROUND(F82*IF(E82="PHP",'03_逐品成本'!E9,1),10),2),"") | M82: =IF(AND(N82="完整",ISNUMBER('03_逐品成本'!E9),'03_逐品成本'!E9>0),ROUND(ROUND(IF(ISNUMBER(G82),G82,F82)*1*IF(E82="PHP",'03_逐品成本'!E9*0.95,1),10),2),"") | N82: =IF(AND(ISNUMBER(F82),F82>=0,OR(E82="PHP",E82="CNY"),OR(H82="已核实",H82="不适用"),I82<>"",J82<>"",ISNUMBER(K82),K82>='00_审核入口'!$F$2,OR(H82<>"不适用",F82=0),OR(G82="",AND(ISNUMBER(G82),G82>=0))),"完整","待补证") -> 待补证
A83: C05 | B83: 衣柜悬挂手袋收纳袋 | C83: preorder | D83: 预售及其他平台服务费 | H83: 待核实 | L83: =IF(AND(N83="完整",ISNUMBER('03_逐品成本'!E9),'03_逐品成本'!E9>0),ROUND(ROUND(F83*IF(E83="PHP",'03_逐品成本'!E9,1),10),2),"") | M83: =IF(AND(N83="完整",ISNUMBER('03_逐品成本'!E9),'03_逐品成本'!E9>0),ROUND(ROUND(IF(ISNUMBER(G83),G83,F83)*1*IF(E83="PHP",'03_逐品成本'!E9*0.95,1),10),2),"") | N83: =IF(AND(ISNUMBER(F83),F83>=0,OR(E83="PHP",E83="CNY"),OR(H83="已核实",H83="不适用"),I83<>"",J83<>"",ISNUMBER(K83),K83>='00_审核入口'!$F$2,OR(H83<>"不适用",F83=0),OR(G83="",AND(ISNUMBER(G83),G83>=0))),"完整","待补证") -> 待补证
A84: C05 | B84: 衣柜悬挂手袋收纳袋 | C84: activities | D84: MDV/返币/直播等活动费 | H84: 待核实 | L84: =IF(AND(N84="完整",ISNUMBER('03_逐品成本'!E9),'03_逐品成本'!E9>0),ROUND(ROUND(F84*IF(E84="PHP",'03_逐品成本'!E9,1),10),2),"") | M84: =IF(AND(N84="完整",ISNUMBER('03_逐品成本'!E9),'03_逐品成本'!E9>0),ROUND(ROUND(IF(ISNUMBER(G84),G84,F84)*1*IF(E84="PHP",'03_逐品成本'!E9*0.95,1),10),2),"") | N84: =IF(AND(ISNUMBER(F84),F84>=0,OR(E84="PHP",E84="CNY"),OR(H84="已核实",H84="不适用"),I84<>"",J84<>"",ISNUMBER(K84),K84>='00_审核入口'!$F$2,OR(H84<>"不适用",F84=0),OR(G84="",AND(ISNUMBER(G84),G84>=0))),"完整","待补证") -> 待补证
A85: C05 | B85: 衣柜悬挂手袋收纳袋 | C85: domestic | D85: 中国境内运费 | H85: 待核实 | L85: =IF(AND(N85="完整",ISNUMBER('03_逐品成本'!E9),'03_逐品成本'!E9>0),ROUND(ROUND(F85*IF(E85="PHP",'03_逐品成本'!E9,1),10),2),"") | M85: =IF(AND(N85="完整",ISNUMBER('03_逐品成本'!E9),'03_逐品成本'!E9>0),ROUND(ROUND(IF(ISNUMBER(G85),G85,F85)*1.15*IF(E85="PHP",'03_逐品成本'!E9*0.95,1),10),2),"") | N85: =IF(AND(ISNUMBER(F85),F85>=0,OR(E85="PHP",E85="CNY"),OR(H85="已核实",H85="不适用"),I85<>"",J85<>"",ISNUMBER(K85),K85>='00_审核入口'!$F$2,OR(H85<>"不适用",F85=0),OR(G85="",AND(ISNUMBER(G85),G85>=0))),"完整","待补证") -> 待补证
A86: C05 | B86: 衣柜悬挂手袋收纳袋 | C86: warehouse_pack | D86: 云仓/验货/贴标/仓储/包材 | H86: 待核实 | L86: =IF(AND(N86="完整",ISNUMBER('03_逐品成本'!E9),'03_逐品成本'!E9>0),ROUND(ROUND(F86*IF(E86="PHP",'03_逐品成本'!E9,1),10),2),"") | M86: =IF(AND(N86="完整",ISNUMBER('03_逐品成本'!E9),'03_逐品成本'!E9>0),ROUND(ROUND(IF(ISNUMBER(G86),G86,F86)*1.15*IF(E86="PHP",'03_逐品成本'!E9*0.95,1),10),2),"") | N86: =IF(AND(ISNUMBER(F86),F86>=0,OR(E86="PHP",E86="CNY"),OR(H86="已核实",H86="不适用"),I86<>"",J86<>"",ISNUMBER(K86),K86>='00_审核入口'!$F$2,OR(H86<>"不适用",F86=0),OR(G86="",AND(ISNUMBER(G86),G86>=0))),"完整","待补证") -> 待补证
A87: C05 | B87: 衣柜悬挂手袋收纳袋 | C87: sls | D87: SLS卖家净国际物流 | H87: 待核实 | L87: =IF(AND(N87="完整",ISNUMBER('03_逐品成本'!E9),'03_逐品成本'!E9>0),ROUND(ROUND(F87*IF(E87="PHP",'03_逐品成本'!E9,1),10),2),"") | M87: =IF(AND(N87="完整",ISNUMBER('03_逐品成本'!E9),'03_逐品成本'!E9>0),ROUND(ROUND(IF(ISNUMBER(G87),G87,F87)*1.15*IF(E87="PHP",'03_逐品成本'!E9*0.95,1),10),2),"") | N87: =IF(AND(ISNUMBER(F87),F87>=0,OR(E87="PHP",E87="CNY"),OR(H87="已核实",H87="不适用"),I87<>"",J87<>"",ISNUMBER(K87),K87>='00_审核入口'!$F$2,OR(H87<>"不适用",F87=0),OR(G87="",AND(ISNUMBER(G87),G87>=0))),"完整","待补证") -> 待补证
A88: C05 | B88: 衣柜悬挂手袋收纳袋 | C88: ads | D88: 广告预算分摊 | H88: 待核实 | L88: =IF(AND(N88="完整",ISNUMBER('03_逐品成本'!E9),'03_逐品成本'!E9>0),ROUND(ROUND(F88*IF(E88="PHP",'03_逐品成本'!E9,1),10),2),"") | M88: =IF(AND(N88="完整",ISNUMBER('03_逐品成本'!E9),'03_逐品成本'!E9>0),ROUND(ROUND(IF(ISNUMBER(G88),G88,F88)*1*IF(E88="PHP",'03_逐品成本'!E9*0.95,1),10),2),"") | N88: =IF(AND(ISNUMBER(F88),F88>=0,OR(E88="PHP",E88="CNY"),OR(H88="已核实",H88="不适用",H88="预算"),I88<>"",J88<>"",ISNUMBER(K88),K88>='00_审核入口'!$F$2,OR(H88<>"不适用",F88=0),OR(G88="",AND(ISNUMBER(G88),G88>=0))),"完整","待补证") -> 待补证
A89: C05 | B89: 衣柜悬挂手袋收纳袋 | C89: affiliate | D89: 联盟/达人分摊 | H89: 待核实 | L89: =IF(AND(N89="完整",ISNUMBER('03_逐品成本'!E9),'03_逐品成本'!E9>0),ROUND(ROUND(F89*IF(E89="PHP",'03_逐品成本'!E9,1),10),2),"") | M89: =IF(AND(N89="完整",ISNUMBER('03_逐品成本'!E9),'03_逐品成本'!E9>0),ROUND(ROUND(IF(ISNUMBER(G89),G89,F89)*1*IF(E89="PHP",'03_逐品成本'!E9*0.95,1),10),2),"") | N89: =IF(AND(ISNUMBER(F89),F89>=0,OR(E89="PHP",E89="CNY"),OR(H89="已核实",H89="不适用",H89="预算"),I89<>"",J89<>"",ISNUMBER(K89),K89>='00_审核入口'!$F$2,OR(H89<>"不适用",F89=0),OR(G89="",AND(ISNUMBER(G89),G89>=0))),"完整","待补证") -> 待补证
A90: C05 | B90: 衣柜悬挂手袋收纳袋 | C90: returns | D90: 售后退款/拒收/破损净损失准备 | H90: 待核实 | L90: =IF(AND(N90="完整",ISNUMBER('03_逐品成本'!E9),'03_逐品成本'!E9>0),ROUND(ROUND(F90*IF(E90="PHP",'03_逐品成本'!E9,1),10),2),"") | M90: =IF(AND(N90="完整",ISNUMBER('03_逐品成本'!E9),'03_逐品成本'!E9>0),ROUND(ROUND(IF(ISNUMBER(G90),G90,F90)*1*IF(E90="PHP",'03_逐品成本'!E9*0.95,1),10),2),"") | N90: =IF(AND(ISNUMBER(F90),F90>=0,OR(E90="PHP",E90="CNY"),OR(H90="已核实",H90="不适用",H90="预算"),I90<>"",J90<>"",ISNUMBER(K90),K90>='00_审核入口'!$F$2,OR(H90<>"不适用",F90=0),OR(G90="",AND(ISNUMBER(G90),G90>=0))),"完整","待补证") -> 待补证
A91: C05 | B91: 衣柜悬挂手袋收纳袋 | C91: collection | D91: 收款/换汇/提现 | H91: 待核实 | L91: =IF(AND(N91="完整",ISNUMBER('03_逐品成本'!E9),'03_逐品成本'!E9>0),ROUND(ROUND(F91*IF(E91="PHP",'03_逐品成本'!E9,1),10),2),"") | M91: =IF(AND(N91="完整",ISNUMBER('03_逐品成本'!E9),'03_逐品成本'!E9>0),ROUND(ROUND(IF(ISNUMBER(G91),G91,F91)*1*IF(E91="PHP",'03_逐品成本'!E9*0.95,1),10),2),"") | N91: =IF(AND(ISNUMBER(F91),F91>=0,OR(E91="PHP",E91="CNY"),OR(H91="已核实",H91="不适用"),I91<>"",J91<>"",ISNUMBER(K91),K91>='00_审核入口'!$F$2,OR(H91<>"不适用",F91=0),OR(G91="",AND(ISNUMBER(G91),G91>=0))),"完整","待补证") -> 待补证
A92: C05 | B92: 衣柜悬挂手袋收纳袋 | C92: tax | D92: 其他不可抵扣税费 | H92: 待核实 | L92: =IF(AND(N92="完整",ISNUMBER('03_逐品成本'!E9),'03_逐品成本'!E9>0),ROUND(ROUND(F92*IF(E92="PHP",'03_逐品成本'!E9,1),10),2),"") | M92: =IF(AND(N92="完整",ISNUMBER('03_逐品成本'!E9),'03_逐品成本'!E9>0),ROUND(ROUND(IF(ISNUMBER(G92),G92,F92)*1*IF(E92="PHP",'03_逐品成本'!E9*0.95,1),10),2),"") | N92: =IF(AND(ISNUMBER(F92),F92>=0,OR(E92="PHP",E92="CNY"),OR(H92="已核实",H92="不适用"),I92<>"",J92<>"",ISNUMBER(K92),K92>='00_审核入口'!$F$2,OR(H92<>"不适用",F92=0),OR(G92="",AND(ISNUMBER(G92),G92>=0))),"完整","待补证") -> 待补证
A93: C05 | B93: 衣柜悬挂手袋收纳袋 | C93: overhead | D93: 固定运营成本分摊 | H93: 待核实 | L93: =IF(AND(N93="完整",ISNUMBER('03_逐品成本'!E9),'03_逐品成本'!E9>0),ROUND(ROUND(F93*IF(E93="PHP",'03_逐品成本'!E9,1),10),2),"") | M93: =IF(AND(N93="完整",ISNUMBER('03_逐品成本'!E9),'03_逐品成本'!E9>0),ROUND(ROUND(IF(ISNUMBER(G93),G93,F93)*1*IF(E93="PHP",'03_逐品成本'!E9*0.95,1),10),2),"") | N93: =IF(AND(ISNUMBER(F93),F93>=0,OR(E93="PHP",E93="CNY"),OR(H93="已核实",H93="不适用",H93="预算"),I93<>"",J93<>"",ISNUMBER(K93),K93>='00_审核入口'!$F$2,OR(H93<>"不适用",F93=0),OR(G93="",AND(ISNUMBER(G93),G93>=0))),"完整","待补证") -> 待补证
A94: C05 | B94: 衣柜悬挂手袋收纳袋 | C94: other | D94: 其他有说明费用 | H94: 待核实 | L94: =IF(AND(N94="完整",ISNUMBER('03_逐品成本'!E9),'03_逐品成本'!E9>0),ROUND(ROUND(F94*IF(E94="PHP",'03_逐品成本'!E9,1),10),2),"") | M94: =IF(AND(N94="完整",ISNUMBER('03_逐品成本'!E9),'03_逐品成本'!E9>0),ROUND(ROUND(IF(ISNUMBER(G94),G94,F94)*1*IF(E94="PHP",'03_逐品成本'!E9*0.95,1),10),2),"") | N94: =IF(AND(ISNUMBER(F94),F94>=0,OR(E94="PHP",E94="CNY"),OR(H94="已核实",H94="不适用",H94="预算"),I94<>"",J94<>"",ISNUMBER(K94),K94>='00_审核入口'!$F$2,OR(H94<>"不适用",F94=0),OR(G94="",AND(ISNUMBER(G94),G94>=0))),"完整","待补证") -> 待补证
A95: C06 | B95: 发夹与发圈挂式整理架 | C95: commission | D95: 适用跨境佣金 | H95: 待核实 | L95: =IF(AND(N95="完整",ISNUMBER('03_逐品成本'!E10),'03_逐品成本'!E10>0),ROUND(ROUND(F95*IF(E95="PHP",'03_逐品成本'!E10,1),10),2),"") | M95: =IF(AND(N95="完整",ISNUMBER('03_逐品成本'!E10),'03_逐品成本'!E10>0),ROUND(ROUND(IF(ISNUMBER(G95),G95,F95)*1*IF(E95="PHP",'03_逐品成本'!E10*0.95,1),10),2),"") | N95: =IF(AND(ISNUMBER(F95),F95>=0,OR(E95="PHP",E95="CNY"),OR(H95="已核实",H95="不适用"),I95<>"",J95<>"",ISNUMBER(K95),K95>='00_审核入口'!$F$2,OR(H95<>"不适用",F95=0),OR(G95="",AND(ISNUMBER(G95),G95>=0))),"完整","待补证") -> 待补证
A96: C06 | B96: 发夹与发圈挂式整理架 | C96: transaction | D96: 交易费（含实际支付方式） | H96: 待核实 | L96: =IF(AND(N96="完整",ISNUMBER('03_逐品成本'!E10),'03_逐品成本'!E10>0),ROUND(ROUND(F96*IF(E96="PHP",'03_逐品成本'!E10,1),10),2),"") | M96: =IF(AND(N96="完整",ISNUMBER('03_逐品成本'!E10),'03_逐品成本'!E10>0),ROUND(ROUND(IF(ISNUMBER(G96),G96,F96)*1*IF(E96="PHP",'03_逐品成本'!E10*0.95,1),10),2),"") | N96: =IF(AND(ISNUMBER(F96),F96>=0,OR(E96="PHP",E96="CNY"),OR(H96="已核实",H96="不适用"),I96<>"",J96<>"",ISNUMBER(K96),K96>='00_审核入口'!$F$2,OR(H96<>"不适用",F96=0),OR(G96="",AND(ISNUMBER(G96),G96>=0)),ISNUMBER(G96),G96>=0),"完整","待补证") -> 待补证
A97: C06 | B97: 发夹与发圈挂式整理架 | C97: installment_extra | D97: 额外分期项目费 | H97: 待核实 | L97: =IF(AND(N97="完整",ISNUMBER('03_逐品成本'!E10),'03_逐品成本'!E10>0),ROUND(ROUND(F97*IF(E97="PHP",'03_逐品成本'!E10,1),10),2),"") | M97: =IF(AND(N97="完整",ISNUMBER('03_逐品成本'!E10),'03_逐品成本'!E10>0),ROUND(ROUND(IF(ISNUMBER(G97),G97,F97)*1*IF(E97="PHP",'03_逐品成本'!E10*0.95,1),10),2),"") | N97: =IF(AND(ISNUMBER(F97),F97>=0,OR(E97="PHP",E97="CNY"),OR(H97="已核实",H97="不适用"),I97<>"",J97<>"",ISNUMBER(K97),K97>='00_审核入口'!$F$2,OR(H97<>"不适用",F97=0),OR(G97="",AND(ISNUMBER(G97),G97>=0))),"完整","待补证") -> 待补证
A98: C06 | B98: 发夹与发圈挂式整理架 | C98: growth | D98: 卖家增长费 | H98: 待核实 | L98: =IF(AND(N98="完整",ISNUMBER('03_逐品成本'!E10),'03_逐品成本'!E10>0),ROUND(ROUND(F98*IF(E98="PHP",'03_逐品成本'!E10,1),10),2),"") | M98: =IF(AND(N98="完整",ISNUMBER('03_逐品成本'!E10),'03_逐品成本'!E10>0),ROUND(ROUND(IF(ISNUMBER(G98),G98,F98)*1*IF(E98="PHP",'03_逐品成本'!E10*0.95,1),10),2),"") | N98: =IF(AND(ISNUMBER(F98),F98>=0,OR(E98="PHP",E98="CNY"),OR(H98="已核实",H98="不适用"),I98<>"",J98<>"",ISNUMBER(K98),K98>='00_审核入口'!$F$2,OR(H98<>"不适用",F98=0),OR(G98="",AND(ISNUMBER(G98),G98>=0))),"完整","待补证") -> 待补证
A99: C06 | B99: 发夹与发圈挂式整理架 | C99: platform_shipping | D99: 平台运费计划费 | H99: 待核实 | L99: =IF(AND(N99="完整",ISNUMBER('03_逐品成本'!E10),'03_逐品成本'!E10>0),ROUND(ROUND(F99*IF(E99="PHP",'03_逐品成本'!E10,1),10),2),"") | M99: =IF(AND(N99="完整",ISNUMBER('03_逐品成本'!E10),'03_逐品成本'!E10>0),ROUND(ROUND(IF(ISNUMBER(G99),G99,F99)*1*IF(E99="PHP",'03_逐品成本'!E10*0.95,1),10),2),"") | N99: =IF(AND(ISNUMBER(F99),F99>=0,OR(E99="PHP",E99="CNY"),OR(H99="已核实",H99="不适用"),I99<>"",J99<>"",ISNUMBER(K99),K99>='00_审核入口'!$F$2,OR(H99<>"不适用",F99=0),OR(G99="",AND(ISNUMBER(G99),G99>=0))),"完整","待补证") -> 待补证
A100: C06 | B100: 发夹与发圈挂式整理架 | C100: order_processing | D100: 订单处理费 | H100: 待核实 | L100: =IF(AND(N100="完整",ISNUMBER('03_逐品成本'!E10),'03_逐品成本'!E10>0),ROUND(ROUND(F100*IF(E100="PHP",'03_逐品成本'!E10,1),10),2),"") | M100: =IF(AND(N100="完整",ISNUMBER('03_逐品成本'!E10),'03_逐品成本'!E10>0),ROUND(ROUND(IF(ISNUMBER(G100),G100,F100)*1*IF(E100="PHP",'03_逐品成本'!E10*0.95,1),10),2),"") | N100: =IF(AND(ISNUMBER(F100),F100>=0,OR(E100="PHP",E100="CNY"),OR(H100="已核实",H100="不适用"),I100<>"",J100<>"",ISNUMBER(K100),K100>='00_审核入口'!$F$2,OR(H100<>"不适用",F100=0),OR(G100="",AND(ISNUMBER(G100),G100>=0))),"完整","待补证") -> 待补证
A101: C06 | B101: 发夹与发圈挂式整理架 | C101: preorder | D101: 预售及其他平台服务费 | H101: 待核实 | L101: =IF(AND(N101="完整",ISNUMBER('03_逐品成本'!E10),'03_逐品成本'!E10>0),ROUND(ROUND(F101*IF(E101="PHP",'03_逐品成本'!E10,1),10),2),"") | M101: =IF(AND(N101="完整",ISNUMBER('03_逐品成本'!E10),'03_逐品成本'!E10>0),ROUND(ROUND(IF(ISNUMBER(G101),G101,F101)*1*IF(E101="PHP",'03_逐品成本'!E10*0.95,1),10),2),"") | N101: =IF(AND(ISNUMBER(F101),F101>=0,OR(E101="PHP",E101="CNY"),OR(H101="已核实",H101="不适用"),I101<>"",J101<>"",ISNUMBER(K101),K101>='00_审核入口'!$F$2,OR(H101<>"不适用",F101=0),OR(G101="",AND(ISNUMBER(G101),G101>=0))),"完整","待补证") -> 待补证
...

Sheet 05_500元与现金
A1: 05 · 500元与现金
A2: 同一预算不可逐品重复使用；历史启动资金不是当前余额。测试成本、最坏损失和峰值垫资分别计算。
A4: 检查项 | B4: 计算/控制规则 | C4: 本轮值或状态 | D4: 依据 | E4: 审核重点
A5: 单品预算 | B5: 样品/拍摄等固定费+计划测试订单×每订单完全成本≤500 | C5: 真实值未知 | D5: 用户2026-09-15要求 | E5: 广告、税、售后不遗漏；固定费与单件分摊不重复
A6: 运行期预算 | B6: 已发生+不可撤销承诺+拟新增+未决损失准备≤500 | C6: 真实值未知 | D6: 用户上限；经营控制建议 | E6: 销售回款不抵消总测试成本；逐订单登记
A7: 单品测试容量 | B7: floor((500−固定测试费)/单件完全成本) | C7: 待成本完整后计算 | D7: 03_逐品成本Y列 | E7: 不能用理想销售单量当固定费分摊分母
A8: 一批10/20款上限 | B8: 10×500=5000；20×500=10000 | C8: 条件算例，非今日投入 | D8: 用户测试上限×目标数量 | E8: 审核候选数量不是每天同时付费测品数量
A9: 新增现金额度 | B9: 0.8×max(0,今日现金−应急金−既有未付承诺) | C9: 今日现金未知 | D9: 历史保护金5000，80%经营规则 | E9: 若20,000仍可用、无承诺，则0.8×(20,000−5,000)=12,000
A10: 现金峰值 | B10: 14/21/28天累计支付减已可用回款的最大缺口 | C10: 回款分布未知 | D10: 按订单与人民币可用到账日计算 | E10: 短测试可先按28天无回款、所有拟付现金保守检验
A11: 月亏损与风险容量 | B11: 4000−已实现月损失−未决预计损失−本批最坏损失≥0 | C11: 真实余额未知 | D11: 历史月亏损硬上限4000 | E11: 若现有损失0，每款最坏损失500，则最多8款全损风险；非默认授权
A12: 收益目标量级 | B12: 若完全成本后每单净利15，超过5000元需至少334单/月 | C12: 条件推算，不是销量预测 | D12: floor(5000/15)+1=334 | E12: 税和固定费用未完整时不能称真实净利
A13: 不囤货仍有垫资 | B13: 付款采购到回款前，货款与物流需要先支付 | C13: 模式事实/资金影响推断 | D13: 本店经营记录 | E13: 跨期未回款、取消/拒收须进入预测，不假定当日循环
A14: 500元与统计证据 | B14: 预算最多支持的订单少于20时，成熟验证样本不足 | C14: 不得自动加预算 | D14: 经营复盘建议 | E14: 可停止得出未证实；需要新预算时另行由店主决定

Sheet 06_1688历史货源
A1: 06 · 1688历史货源
A2: 原始历史来源记录；未经本轮SKU/税/阶梯/库存复核。不表示已匹配同款或可按起价买整套。0价标为无效，原值保留。
A4: 采集时间 | B4: 查询词 | C4: 1688商品ID | D4: 商品标题 | E4: 供应商 | F4: 原始起价CNY | G4: MOQ原值 | H4: 代发原值 | I4: 库存原值 | J4: 零价/有效性 | K4: 详情链接 | L4: 证据定位
A5: 2026-09-10T13:40:27.931Z | B5: 洗衣袋套装 | C5: 740476883384 | D5: 塑料袋洗衣袋定 制 干洗店专用手提袋洗衣店包装袋酒店洗衣袋 | E5: 桐城市东捷塑业有限公司 | F5: 0.08 | G5: 1 | H5: False | I5: 94269943 | J5: 历史起价待复核 | K5: https://detail.1688.com/offer/740476883384.html | L5: evidence/2026-09-10-raw-observations.json#/suppliers/0/result/content/0/text→JSON/data/0
A6: 2026-09-10T13:40:27.931Z | B6: 洗衣袋套装 | C6: 959024425225 | D6: 加厚大容量可水洗收纳袋防水搬家学生行李衣物整理袋便携可折叠 | E6: 义乌市樊丞电子商务商行 | F6: 3.4 | G6: 2 | H6: True | I6: 85486 | J6: 历史起价待复核 | K6: https://detail.1688.com/offer/959024425225.html | L6: evidence/2026-09-10-raw-observations.json#/suppliers/0/result/content/0/text→JSON/data/1
A7: 2026-09-10T13:40:27.931Z | B7: 洗衣袋套装 | C7: 757301647238 | D7: 小包洗衣液袋装500g薰衣草1斤装家用开业礼品会销活动整箱批发 | E7: 临沂贝雅日化有限公司 | F7: 0.9 | G7: 200 | H7: False | I7: 962040 | J7: 历史起价待复核 | K7: https://detail.1688.com/offer/757301647238.html | L7: evidence/2026-09-10-raw-observations.json#/suppliers/0/result/content/0/text→JSON/data/2
A8: 2026-09-10T13:40:27.931Z | B8: 洗衣袋套装 | C8: 719860595971 | D8: FaSoLa洗衣袋洗衣机机洗专用防变形护洗内衣服文胸过滤网袋兜家用 | E8: 义乌市远阳日用百货有限公司 | F8: 4.73 | G8: 5 | H8: True | I8: 3292 | J8: 历史起价待复核 | K8: https://detail.1688.com/offer/719860595971.html | L8: evidence/2026-09-10-raw-observations.json#/suppliers/0/result/content/0/text→JSON/data/3
A9: 2026-09-10T13:40:27.931Z | B9: 洗衣袋套装 | C9: 813925971481 | D9: 洗衣液薰衣草香袋装去污瓶袋装婴儿内衣洗衣液厂家家用整箱桶量批 | E9: 东阳市浯晔电子商务商行 | F9: 0.01 | G9: 1 | H9: False | I9: 18483009 | J9: 历史起价待复核 | K9: https://detail.1688.com/offer/813925971481.html | L9: evidence/2026-09-10-raw-observations.json#/suppliers/0/result/content/0/text→JSON/data/4
A10: 2026-09-10T13:40:27.931Z | B10: 洗衣袋套装 | C10: 625255182969 | D10: 洗衣袋套装加厚护洗袋粗细网袋洗护袋内衣袋文胸袋机洗厂家批发 | E10: 义乌市艾依日用品有限公司 | F10: 0.6 | G10: 1 | H10: True | I10: 783544 | J10: 历史起价待复核 | K10: https://detail.1688.com/offer/625255182969.html | L10: evidence/2026-09-10-raw-observations.json#/suppliers/0/result/content/0/text→JSON/data/5
A11: 2026-09-10T13:40:27.931Z | B11: 洗衣袋套装 | C11: 705110577312 | D11: 厂家批发洗衣袋洗护袋网袋机洗衣物清洁袋粗网细网家用洗衣服袋子 | E11: 义乌市丘彼特日用品有限公司 | F11: 1.58 | G11: 1 | H11: True | I11: 253769 | J11: 历史起价待复核 | K11: https://detail.1688.com/offer/705110577312.html | L11: evidence/2026-09-10-raw-observations.json#/suppliers/0/result/content/0/text→JSON/data/6
A12: 2026-09-10T13:40:27.931Z | B12: 洗衣袋套装 | C12: 795873942999 | D12: 洗衣袋洗衣服袋子洗衣防变形家用洗衣袋加厚耐用不变形洗衣机袋子 | E12: 义乌市佳峰日用品有限公司 | F12: 1.1 | G12: 1 | H12: True | I12: 127117930 | J12: 历史起价待复核 | K12: https://detail.1688.com/offer/795873942999.html | L12: evidence/2026-09-10-raw-observations.json#/suppliers/0/result/content/0/text→JSON/data/7
A13: 2026-09-10T13:40:27.931Z | B13: 洗衣袋套装 | C13: 596364807955 | D13: 内衣袜子圆筒洗衣袋多功能粗细网涤纶文胸护洗袋洗衣机网袋现货 | E13: 义乌市酷适日用品有限公司 | F13: 0 | G13: 1 | H13: False | I13: 0 | J13: 0价/缺失无效 | K13: https://detail.1688.com/offer/596364807955.html | L13: evidence/2026-09-10-raw-observations.json#/suppliers/0/result/content/0/text→JSON/data/8
A14: 2026-09-10T13:40:27.931Z | B14: 洗衣袋套装 | C14: 763443524740 | D14: 70克细网粗网洗衣袋家用护洗袋套装机洗防变形内衣文胸洗护袋批发 | E14: 江西省舒米日用品有限公司 | F14: 0 | G14: 0 | H14: False | I14: 0 | J14: 0价/缺失无效 | K14: https://detail.1688.com/offer/763443524740.html | L14: evidence/2026-09-10-raw-observations.json#/suppliers/0/result/content/0/text→JSON/data/9
A15: 2026-09-10T13:40:27.931Z | B15: 洗衣袋套装 | C15: 617113480161 | D15: 日式无印洗衣网袋良品洗衣隔离袋子专柜同步简约白色洗衣袋 | E15: 南通素艺家居用品有限公司 | F15: 0 | G15: 1 | H15: False | I15: 0 | J15: 0价/缺失无效 | K15: https://detail.1688.com/offer/617113480161.html | L15: evidence/2026-09-10-raw-observations.json#/suppliers/0/result/content/0/text→JSON/data/10
A16: 2026-09-10T13:40:27.931Z | B16: 洗衣袋套装 | C16: 713462628237 | D16: 洗衣袋批发洗衣机专用洗衣网袋套装粗网细网内衣文胸专用护洗衣袋 | E16: 义乌市太格日用品有限公司 | F16: 1.5 | G16: 1 | H16: False | I16: 6477433 | J16: 历史起价待复核 | K16: https://detail.1688.com/offer/713462628237.html | L16: evidence/2026-09-10-raw-observations.json#/suppliers/0/result/content/0/text→JSON/data/11
... A21: 2026-09-10T13:40:27.931Z | B21: 洗衣袋套装 | C21: 914125600672 | D21: 洗衣袋家用洗衣机专用洗衣凝珠留香珠加厚网袋肥皂袋香皂护洗袋 | E21: 邵武市希梦纺家居用品厂 | F21: 0.6 | G21: 2 | H21: True | I21: 545255 | J21: 历史起价待复核 | K21: https://detail.1688.com/offer/914125600672.html | L21: evidence/2026-09-10-raw-observations.json#/suppliers/0/result/content/0/text→JSON/data/16
A22: 2026-09-10T13:40:27.931Z | B22: 洗衣袋套装 | C22: 945740708989 | D22: 洗衣袋洗衣机专用涤纶洗衣网兜袋刺绣加厚内衣文胸护洗袋 | F22: 0 | G22: 0 | H22: False | I22: 0 | J22: 0价/缺失无效 | K22: https://detail.1688.com/offer/945740708989.html | L22: evidence/2026-09-10-raw-observations.json#/suppliers/0/result/content/0/text→JSON/data/17
A23: 2026-09-10T13:40:27.931Z | B23: 洗衣袋套装 | C23: 678102897733 | D23: 厂家直销粗网洗衣袋四件套装护洗袋内衣文胸洗衣网袋批发 | E23: 天长市纤程日用品有限公司 | F23: 0.6 | G23: 5 | H23: True | I23: 4043533 | J23: 历史起价待复核 | K23: https://detail.1688.com/offer/678102897733.html | L23: evidence/2026-09-10-raw-observations.json#/suppliers/0/result/content/0/text→JSON/data/18
A24: 2026-09-10T13:40:27.931Z | B24: 洗衣袋套装 | C24: 883527333937 | D24: 多功能立体护衣洗衣袋网孔细腻透水性强内衣分类球形洗衣网袋 | E24: 邵武市舒纺家居用品厂 | F24: 0 | G24: 1 | H24: False | I24: 0 | J24: 0价/缺失无效 | K24: https://detail.1688.com/offer/883527333937.html | L24: evidence/2026-09-10-raw-observations.json#/suppliers/0/result/content/0/text→JSON/data/19
A25: 2026-09-10T13:40:27.931Z | B25: 洗衣袋套装 | C25: 894717160880 | D25: 厂家现货灰粗细网洗衣袋机洗专用防变形洗护袋衣物网袋洗护袋批发 | E25: 义乌市叮当日用品有限公司 | F25: 0 | G25: 1 | H25: False | I25: 0 | J25: 0价/缺失无效 | K25: https://detail.1688.com/offer/894717160880.html | L25: evidence/2026-09-10-raw-observations.json#/suppliers/0/result/content/0/text→JSON/data/20
A26: 2026-09-10T13:40:27.931Z | B26: 洗衣袋套装 | C26: 721245381400 | D26: 立体洗衣袋家用毛衣内衣护洗袋衣物旅行收纳袋防缠绕文胸洗护袋 | E26: 浦江丰瑞日用品有限公司 | F26: 0 | G26: 1 | H26: False | I26: 0 | J26: 0价/缺失无效 | K26: https://detail.1688.com/offer/721245381400.html | L26: evidence/2026-09-10-raw-observations.json#/suppliers/0/result/content/0/text→JSON/data/21
A27: 2026-09-10T13:40:27.931Z | B27: 洗衣袋套装 | C27: 718385804237 | D27: 厂家洗衣袋洗衣机专用防变形60克加厚细网文胸内衣家用洗衣袋批发 | E27: 义乌市东晟日用品有限公司 | F27: 0 | G27: 1 | H27: False | I27: 0 | J27: 0价/缺失无效 | K27: https://detail.1688.com/offer/718385804237.html | L27: evidence/2026-09-10-raw-observations.json#/suppliers/0/result/content/0/text→JSON/data/22
A28: 2026-09-10T13:40:27.931Z | B28: 洗衣袋套装 | C28: 755489755204 | D28: 工厂直销袋装洗衣袋家用内衣洗袋细网加厚洗衣机专用防变形网袋 | E28: 义乌市珂岚日用品有限公司 | F28: 0 | G28: 2 | H28: False | I28: 0 | J28: 0价/缺失无效 | K28: https://detail.1688.com/offer/755489755204.html | L28: evidence/2026-09-10-raw-observations.json#/suppliers/0/result/content/0/text→JSON/data/23
A29: 2026-09-10T13:40:27.931Z | B29: 洗衣袋套装 | C29: 598663018077 | D29: 工厂细网洗衣袋洗衣机过滤网内衣洗护袋护洗袋家用衣物洗衣袋批发 | E29: 义乌市旺顺日用品有限公司 | F29: 0.6 | G29: 1 | H29: True | I29: 10228962 | J29: 历史起价待复核 | K29: https://detail.1688.com/offer/598663018077.html | L29: evidence/2026-09-10-raw-observations.json#/suppliers/0/result/content/0/text→JSON/data/24
A30: 2026-09-10T13:40:27.931Z | B30: 洗衣袋套装 | C30: 858339494134 | D30: 防变形洗衣袋洗衣机专用毛衣羊毛衫细网洗衣服过滤网袋内衣护洗袋 | E30: 义乌市柏佳娜箱包有限公司 | F30: 0 | G30: 1 | H30: False | I30: 0 | J30: 0价/缺失无效 | K30: https://detail.1688.com/offer/858339494134.html | L30: evidence/2026-09-10-raw-observations.json#/suppliers/0/result/content/0/text→JSON/data/25
A31: 2026-09-10T13:40:27.931Z | B31: 洗衣袋套装 | C31: 808715329025 | D31: 洗衣袋洗衣机专用加厚毛衣内衣网兜衣服防变形护洗袋大号网袋批发 | E31: 芜湖贝石塑业有限公司 | F31: 0 | G31: 1 | H31: False | I31: 0 | J31: 0价/缺失无效 | K31: https://detail.1688.com/offer/808715329025.html | L31: evidence/2026-09-10-raw-observations.json#/suppliers/0/result/content/0/text→JSON/data/26
A32: 2026-09-10T13:40:27.931Z | B32: 洗衣袋套装 | C32: 665976181640 | D32: 洗衣机洗衣袋细网洗护袋6件套洗衣服羽绒服大号网兜内衣袋文胸袋 | E32: 义乌市甄常日用品有限公司 | F32: 0 | G32: 1 | H32: False | I32: 0 | J32: 0价/缺失无效 | K32: https://detail.1688.com/offer/665976181640.html | L32: evidence/2026-09-10-raw-observations.json#/suppliers/0/result/content/0/text→JSON/data/27
A33: 2026-09-10T13:40:27.931Z | B33: 洗衣袋套装 | C33: 618364145714 | D33: 细网粗网洗衣袋家用衣物洗护袋外出旅行便携收纳折叠方袋大网孔 | E33: 义乌市沐家日用品有限公司 | F33: 1.05 | G33: 2 | H33: False | I33: 0 | J33: 历史起价待复核 | K33: https://detail.1688.com/offer/618364145714.html | L33: evidence/2026-09-10-raw-observations.json#/suppliers/0/result/content/0/text→JSON/data/28
A34: 2026-09-10T13:40:27.931Z | B34: 洗衣袋套装 | C34: 707087838335 | D34: 棉麻脏衣篮脏衣服收纳筐防水脏衣篓可折叠洗衣篮大号脏衣筐收纳袋 | E34: 义乌市猴七日用品有限公司 | F34: 0 | G34: 0 | H34: False | I34: 0 | J34: 0价/缺失无效 | K34: https://detail.1688.com/offer/707087838335.html | L34: evidence/2026-09-10-raw-observations.json#/suppliers/0/result/content/0/text→JSON/data/29
... A42: 2026-09-10T13:40:27.931Z | B42: 洗衣袋套装 | C42: 808175297177 | D42: 卡通家用衣物细网护洗袋加厚防变形洗衣袋专用网袋手拎化妆洗漱包 | E42: 广陵区燕佑毛绒玩具经营部 | F42: 0 | G42: 1 | H42: False | I42: 0 | J42: 0价/缺失无效 | K42: https://detail.1688.com/offer/808175297177.html | L42: evidence/2026-09-10-raw-observations.json#/suppliers/0/result/content/0/text→JSON/data/37
A43: 2026-09-10T13:40:27.931Z | B43: 洗衣袋套装 | C43: 871970135264 | D43: 洗衣机过滤网袋衣服专用万能过滤器清洁球除毛器洗衣网袋洗衣袋子 | F43: 0 | G43: 0 | H43: False | I43: 0 | J43: 0价/缺失无效 | K43: https://detail.1688.com/offer/871970135264.html | L43: evidence/2026-09-10-raw-observations.json#/suppliers/0/result/content/0/text→JSON/data/38
A44: 2026-09-10T13:40:27.931Z | B44: 洗衣袋套装 | C44: 771122054369 | D44: 洗衣袋洗衣机专用防变形网袋细网粗网大孔加厚双层洗衣袋套装批发 | E44: 义乌市甄喜日用品有限公司 | F44: 0.7 | G44: 1 | H44: False | I44: 0 | J44: 历史起价待复核 | K44: https://detail.1688.com/offer/771122054369.html | L44: evidence/2026-09-10-raw-observations.json#/suppliers/0/result/content/0/text→JSON/data/39
A45: 2026-09-10T13:40:27.931Z | B45: 洗衣袋套装 | C45: 684757410094 | D45: 三明治刺绣洗衣店洗衣袋加厚双层内衣防打结洗衣机专用护洗袋收纳 | E45: 蠡县未阿姨洗衣袋厂 | F45: 0 | G45: 1 | H45: False | I45: 0 | J45: 0价/缺失无效 | K45: https://detail.1688.com/offer/684757410094.html | L45: evidence/2026-09-10-raw-observations.json#/suppliers/0/result/content/0/text→JSON/data/40
A46: 2026-09-10T13:40:27.931Z | B46: 洗衣袋套装 | C46: 677014985803 | D46: 洗衣袋洗衣机专用家用毛衣内衣文胸清洗网袋衣服过滤网衣物洗护袋 | E46: 温州贝石收纳用品有限公司 | F46: 1.39 | G46: 1 | H46: True | I46: 5489000 | J46: 历史起价待复核 | K46: https://detail.1688.com/offer/677014985803.html | L46: evidence/2026-09-10-raw-observations.json#/suppliers/0/result/content/0/text→JSON/data/41
A47: 2026-09-10T13:40:27.931Z | B47: 洗衣袋套装 | C47: 673840320423 | D47: 家用加厚家用洗衣袋洗衣机专用防变形网袋毛衣勾丝内衣洗护衣服 | E47: 靖江市贝石智造家居用品有限公司 | F47: 0 | G47: 1 | H47: False | I47: 0 | J47: 0价/缺失无效 | K47: https://detail.1688.com/offer/673840320423.html | L47: evidence/2026-09-10-raw-observations.json#/suppliers/0/result/content/0/text→JSON/data/42
A48: 2026-09-10T13:40:27.931Z | B48: 洗衣袋套装 | C48: 837604730616 | D48: 洗衣袋护洗袋套装文胸毛衣家用洗衣机机洗专用细网防变形网袋网兜 | E48: 义乌市豫思雅贸易有限公司 | F48: 0 | G48: 1 | H48: False | I48: 0 | J48: 0价/缺失无效 | K48: https://detail.1688.com/offer/837604730616.html | L48: evidence/2026-09-10-raw-observations.json#/suppliers/0/result/content/0/text→JSON/data/43
A49: 2026-09-10T13:40:27.931Z | B49: 洗衣袋套装 | C49: 664473602789 | D49: 印花洗衣袋套装洗衣机机洗专用细网袋毛衣衣服内衣文胸家用护洗袋 | E49: 义乌市薏茹日用品有限公司 | F49: 2.2 | G49: 1 | H49: False | I49: 0 | J49: 历史起价待复核 | K49: https://detail.1688.com/offer/664473602789.html | L49: evidence/2026-09-10-raw-observations.json#/suppliers/0/result/content/0/text→JSON/data/44
A50: 2026-09-10T13:40:27.931Z | B50: 洗衣袋套装 | C50: 694765458344 | D50: 洗衣机专用网袋洗护袋刺绣洗衣袋大号加厚双层宣传赠衣物品内衣护 | E50: 蠡县未阿姨洗衣袋厂 | F50: 0 | G50: 1 | H50: False | I50: 0 | J50: 0价/缺失无效 | K50: https://detail.1688.com/offer/694765458344.html | L50: evidence/2026-09-10-raw-observations.json#/suppliers/0/result/content/0/text→JSON/data/45
A51: 2026-09-10T13:40:27.931Z | B51: 洗衣袋套装 | C51: 853111186335 | D51: 洗衣袋家用防变形多功能网布内衣护洗袋大容量加厚可手提洗衣神器 | E51: 丽水春涧家居有限公司 | F51: 0 | G51: 1 | H51: False | I51: 0 | J51: 0价/缺失无效 | K51: https://detail.1688.com/offer/853111186335.html | L51: evidence/2026-09-10-raw-observations.json#/suppliers/0/result/content/0/text→JSON/data/46
A52: 2026-09-10T13:40:27.931Z | B52: 洗衣袋套装 | C52: 975084879091 | D52: 防变形加厚洗衣袋洗衣机专用衣物内衣洗护袋简约涤纶粗细洗衣网袋 | E52: 袁州区好居日用品厂 | F52: 0 | G52: 1 | H52: False | I52: 0 | J52: 0价/缺失无效 | K52: https://detail.1688.com/offer/975084879091.html | L52: evidence/2026-09-10-raw-observations.json#/suppliers/0/result/content/0/text→JSON/data/47
A53: 2026-09-10T13:40:27.931Z | B53: 洗衣袋套装 | C53: 951599413930 | D53: 护洗衣袋洗衣机机洗通用网袋宿舍洗内衣衣服网兜家用防变形收纳袋 | E53: 义乌市首飒贸易有限公司 | F53: 0 | G53: 1 | H53: False | I53: 0 | J53: 0价/缺失无效 | K53: https://detail.1688.com/offer/951599413930.html | L53: evidence/2026-09-10-raw-observations.json#/suppliers/0/result/content/0/text→JSON/data/48
A54: 2026-09-10T13:40:27.931Z | B54: 洗衣袋套装 | C54: 852567268657 | D54: 家用波轮洗衣机过滤网袋衣服清洁漂浮除毛器毛毛杂物洗衣袋洗衣球 | E54: 义乌市物风日用品有限公司 | F54: 0 | G54: 1 | H54: False | I54: 0 | J54: 0价/缺失无效 | K54: https://detail.1688.com/offer/852567268657.html | L54: evidence/2026-09-10-raw-observations.json#/suppliers/0/result/content/0/text→JSON/data/49
A55: 2026-09-10T13:40:27.931Z | B55: 洗衣袋套装 | C55: 981131284061 | D55: 加厚洗衣袋洗衣机专用防变形家用衣物内衣洗衣袋便携式洗衣网袋 | E55: 袁州区好居日用品厂 | F55: 0 | G55: 1 | H55: False | I55: 0 | J55: 0价/缺失无效 | K55: https://detail.1688.com/offer/981131284061.html | L55: evidence/2026-09-10-raw-observations.json#/suppliers/0/result/content/0/text→JSON/data/50
... A59: 2026-09-10T13:40:27.931Z | B59: 洗衣袋套装 | C59: 847685310950 | D59: 立体洗衣袋家用毛衣内衣护洗袋衣物旅行收纳袋防缠绕文胸洗护袋 | E59: 金华市源奇日用品有限公司 | F59: 0 | G59: 1 | H59: False | I59: 0 | J59: 0价/缺失无效 | K59: https://detail.1688.com/offer/847685310950.html | L59: evidence/2026-09-10-raw-observations.json#/suppliers/0/result/content/0/text→JSON/data/54
A60: 2026-09-10T13:40:27.931Z | B60: 洗衣袋套装 | C60: 989309189673 | D60: 外贸大容量洗衣袋背包网袋大学宿舍旅行公寓脏衣服洗衣收纳袋 | F60: 0 | G60: 0 | H60: False | I60: 0 | J60: 0价/缺失无效 | K60: https://detail.1688.com/offer/989309189673.html | L60: evidence/2026-09-10-raw-observations.json#/suppliers/0/result/content/0/text→JSON/data/55
A61: 2026-09-10T13:40:27.931Z | B61: 洗衣袋套装 | C61: 773016402361 | D61: 跨境亚马逊特大号60×90拉绳洗衣袋抽绳衣物护洗袋窗帘衣服收纳袋 | F61: 0 | G61: 0 | H61: False | I61: 0 | J61: 0价/缺失无效 | K61: https://detail.1688.com/offer/773016402361.html | L61: evidence/2026-09-10-raw-observations.json#/suppliers/0/result/content/0/text→JSON/data/56
A62: 2026-09-10T13:40:27.931Z | B62: 洗衣袋套装 | C62: 901335779184 | D62: 亚马逊热销款超大号拉绳洗衣袋细网衣物护洗袋脏衣篮窗帘毛毯专用 | F62: 0 | G62: 0 | H62: False | I62: 0 | J62: 0价/缺失无效 | K62: https://detail.1688.com/offer/901335779184.html | L62: evidence/2026-09-10-raw-observations.json#/suppliers/0/result/content/0/text→JSON/data/57
A63: 2026-09-10T13:40:27.931Z | B63: 洗衣袋套装 | C63: 574091390849 | D63: 工厂直供洗衣袋网袋细网洗衣袋加厚家用洗衣机用防变形内衣洗护袋 | E63: 义乌市鸿启日用品有限公司 | F63: 1.5 | G63: 1 | H63: False | I63: 0 | J63: 历史起价待复核 | K63: https://detail.1688.com/offer/574091390849.html | L63: evidence/2026-09-10-raw-observations.json#/suppliers/0/result/content/0/text→JSON/data/58
A64: 2026-09-10T13:40:27.931Z | B64: 洗衣袋套装 | C64: 923644754855 | D64: 跨境脏衣篮卧室配内袋带盖可折叠收纳脏衣服收纳筐浴室大容量收纳 | F64: 0 | G64: 0 | H64: False | I64: 0 | J64: 0价/缺失无效 | K64: https://detail.1688.com/offer/923644754855.html | L64: evidence/2026-09-10-raw-observations.json#/suppliers/0/result/content/0/text→JSON/data/59
A65: 2026-09-10T13:40:27.931Z | B65: 洗衣袋套装 | C65: 985649189695 | D65: 护洗衣袋洗衣机机洗网袋洗文胸内衣衣服网兜家用防变形网 | E65: 义乌市昂宝家居用品有限公司 | F65: 0.61 | G65: 1 | H65: False | I65: 34453638 | J65: 历史起价待复核 | K65: https://detail.1688.com/offer/985649189695.html | L65: evidence/2026-09-10-raw-observations.json#/suppliers/0/result/content/0/text→JSON/data/60
A66: 2026-09-10T13:40:27.931Z | B66: 洗衣袋套装 | C66: 967988481772 | D66: 洗衣袋洗衣机防变形毛衣文胸护洗羊毛衫洗衣服内衣羽绒服网袋 | F66: 0 | G66: 0 | H66: False | I66: 0 | J66: 0价/缺失无效 | K66: https://detail.1688.com/offer/967988481772.html | L66: evidence/2026-09-10-raw-observations.json#/suppliers/0/result/content/0/text→JSON/data/61
A67: 2026-09-10T13:40:27.931Z | B67: 洗衣袋套装 | C67: 987870538123 | D67: 现货批发洗衣袋家用洗衣袋洗衣机专用防变形网袋加厚细粗过滤网袋 | F67: 0 | G67: 0 | H67: False | I67: 0 | J67: 0价/缺失无效 | K67: https://detail.1688.com/offer/987870538123.html | L67: evidence/2026-09-10-raw-observations.json#/suppliers/0/result/content/0/text→JSON/data/62
A68: 2026-09-10T13:40:27.931Z | B68: 洗衣袋套装 | C68: 725621467189 | D68: 厂家现货加厚洗衣机专用洗衣袋套装批发文胸内衣防变形粗网护洗袋 | F68: 0 | G68: 0 | H68: False | I68: 0 | J68: 0价/缺失无效 | K68: https://detail.1688.com/offer/725621467189.html | L68: evidence/2026-09-10-raw-observations.json#/suppliers/0/result/content/0/text→JSON/data/63
A69: 2026-09-10T13:40:27.931Z | B69: 洗衣袋套装 | C69: 982447728829 | D69: 超大抽绳洗衣袋加厚网袋套装洗衣机专用洗护袋网袋防变形染色网兜 | F69: 0 | G69: 0 | H69: False | I69: 0 | J69: 0价/缺失无效 | K69: https://detail.1688.com/offer/982447728829.html | L69: evidence/2026-09-10-raw-observations.json#/suppliers/0/result/content/0/text→JSON/data/64
A70: 2026-09-10T13:40:27.931Z | B70: 洗衣袋套装 | C70: 989785866751 | D70: 酒店洗衣袋拉绳收纳袋民宿客房防尘袋酒店一次性塑料洗衣袋定制 | F70: 0 | G70: 0 | H70: False | I70: 0 | J70: 0价/缺失无效 | K70: https://detail.1688.com/offer/989785866751.html | L70: evidence/2026-09-10-raw-observations.json#/suppliers/0/result/content/0/text→JSON/data/65
A71: 2026-09-10T13:40:27.931Z | B71: 洗衣袋套装 | C71: 799271250425 | D71: 加厚蜂窝网洗衣袋护洗袋衣物甩干袋洗衣网袋机洗护洗袋批发家用 | F71: 0 | G71: 0 | H71: False | I71: 0 | J71: 0价/缺失无效 | K71: https://detail.1688.com/offer/799271250425.html | L71: evidence/2026-09-10-raw-observations.json#/suppliers/0/result/content/0/text→JSON/data/66
A72: 2026-09-10T13:40:27.931Z | B72: 洗衣袋套装 | C72: 1269868641 | D72: 加厚粗细网洗衣袋套装洗衣机专用文胸洗护袋防变形网眼袋现货批发 | F72: 0 | G72: 0 | H72: False | I72: 0 | J72: 0价/缺失无效 | K72: https://detail.1688.com/offer/1269868641.html | L72: evidence/2026-09-10-raw-observations.json#/suppliers/0/result/content/0/text→JSON/data/67
A73: 2026-09-10T13:40:27.931Z | B73: 洗衣袋套装 | C73: 645353215222 | D73: 彩色洗衣袋套装亚马逊纯色洗衣袋网袋便携旅行衣物清洗袋洗衣机用 | F73: 0 | G73: 0 | H73: False | I73: 0 | J73: 0价/缺失无效 | K73: https://detail.1688.com/offer/645353215222.html | L73: evidence/2026-09-10-raw-observations.json#/suppliers/0/result/content/0/text→JSON/data/68
A74: 2026-09-10T13:40:27.931Z | B74: 洗衣袋套装 | C74: 743189515138 | D74: 洗衣袋洗衣机专用防变形网袋内衣洗衣袋加厚家用洗衣防变形套装 | F74: 0 | G74: 0 | H74: False | I74: 0 | J74: 0价/缺失无效 | K74: https://detail.1688.com/offer/743189515138.html | L74: evidence/2026-09-10-raw-observations.json#/suppliers/0/result/content/0/text→JSON/data/69
A75: 2026-09-10T13:40:27.931Z | B75: 洗衣袋套装 | C75: 775079732722 | D75: 洗衣袋洗衣机专用防变形家用文胸护洗网袋加厚容量加大衣物清洗袋 | F75: 0 | G75: 0 | H75: False | I75: 0 | J75: 0价/缺失无效 | K75: https://detail.1688.com/offer/775079732722.html | L75: evidence/2026-09-10-raw-observations.json#/suppliers/0/result/content/0/text→JSON/data/70
A76: 2026-09-10T13:40:27.931Z | B76: 洗衣袋套装 | C76: 709876185671 | D76: 洗衣机专用护洗袋网袋过滤洗毛衣衣服羽绒服网兜防变形破损洗衣袋 | E76: 义乌市爱丫日用品厂 | F76: 3.3 | G76: 1 | H76: False | I76: 0 | J76: 历史起价待复核 | K76: https://detail.1688.com/offer/709876185671.html | L76: evidence/2026-09-10-raw-observations.json#/suppliers/0/result/content/0/text→JSON/data/71
A77: 2026-09-10T13:40:27.931Z | B77: 洗衣袋套装 | C77: 755015139921 | D77: 外贸酒店洗衣袋一次性束口抽绳洗衣袋干洗店脏衣袋laundry bag | E77: 桐城市优立洁塑业有限公司 | F77: 0.4 | G77: 1 | H77: False | I77: 15298 | J77: 历史起价待复核 | K77: https://detail.1688.com/offer/755015139921.html | L77: evidence/2026-09-10-raw-observations.json#/suppliers/0/result/content/0/text→JSON/data/72
A78: 2026-09-10T13:40:27.931Z | B78: 洗衣袋套装 | C78: 915529304159 | D78: 50g细网加厚洗衣袋护洗袋洗衣机专用防变形网袋内衣袋洗护袋批发 | E78: 邵武市华源纺织厂 | F78: 0.25 | G78: 1 | H78: False | I78: 0 | J78: 历史起价待复核 | K78: https://detail.1688.com/offer/915529304159.html | L78: evidence/2026-09-10-raw-observations.json#/suppliers/0/result/content/0/text→JSON/data/73
A79: 2026-09-10T13:40:27.931Z | B79: 洗衣袋套装 | C79: 677742569302 | D79: 洗衣袋护洗袋家用细网洗衣套装加厚防变形洗衣机内衣文胸洗护网袋 | F79: 0 | G79: 0 | H79: False | I79: 0 | J79: 0价/缺失无效 | K79: https://detail.1688.com/offer/677742569302.html | L79: evidence/2026-09-10-raw-observations.json#/suppliers/0/result/content/0/text→JSON/data/74
A80: 2026-09-10T13:40:27.931Z | B80: 洗衣袋套装 | C80: 921070812710 | D80: 工厂大号旅行洗衣袋防水带手柄可水洗脏衣服袋旅行干湿袋沐浴套装 | F80: 0 | G80: 0 | H80: False | I80: 0 | J80: 0价/缺失无效 | K80: https://detail.1688.com/offer/921070812710.html | L80: evidence/2026-09-10-raw-observations.json#/suppliers/0/result/content/0/text→JSON/data/75
A81: 2026-09-10T13:40:27.931Z | B81: 洗衣袋套装 | C81: 966663582489 | D81: 护洗衣袋洗衣机机洗网袋洗毛衣内衣衣服网兜家用防变形收纳 | F81: 0 | G81: 0 | H81: False | I81: 0 | J81: 0价/缺失无效 | K81: https://detail.1688.com/offer/966663582489.html | L81: evidence/2026-09-10-raw-observations.json#/suppliers/0/result/content/0/text→JSON/data/76
A82: 2026-09-10T13:40:27.931Z | B82: 洗衣袋套装 | C82: 998559694269 | D82: 无包装洗衣袋洗衣机专用加厚防缠绕防变形洗护袋家用衣物毛衣网袋 | E82: 袁州区好居日用品厂 | F82: 0.73 | G82: 1 | H82: False | I82: 0 | J82: 历史起价待复核 | K82: https://detail.1688.com/offer/998559694269.html | L82: evidence/2026-09-10-raw-observations.json#/suppliers/0/result/content/0/text→JSON/data/77
A83: 2026-09-10T13:40:27.931Z | B83: 洗衣袋套装 | C83: 611772118624 | D83: 机洗衣袋套装批发文胸袋护洗袋三明治网袋laundrybag衣物可机洗 | F83: 0 | G83: 0 | H83: False | I83: 0 | J83: 0价/缺失无效 | K83: https://detail.1688.com/offer/611772118624.html | L83: evidence/2026-09-10-raw-observations.json#/suppliers/0/result/content/0/text→JSON/data/78
A84: 2026-09-10T13:40:27.931Z | B84: 洗衣袋套装 | C84: 633878185735 | D84: 厂家批发细网洗衣袋家用机洗文胸内衣护洗袋旅行收纳洗护袋套装 | E84: 义乌市悠忆日用品有限公司 | F84: 1.3 | G84: 1 | H84: False | I84: 0 | J84: 历史起价待复核 | K84: https://detail.1688.com/offer/633878185735.html | L84: evidence/2026-09-10-raw-observations.json#/suppliers/0/result/content/0/text→JSON/data/79
A85: 2026-09-10T13:40:27.931Z | B85: 洗衣袋套装 | C85: 858357592612 | D85: 洗衣袋女护洗袋细网套装加厚文胸衣服护洗内衣袋洗衣机用于防变形 | F85: 0 | G85: 0 | H85: False | I85: 0 | J85: 0价/缺失无效 | K85: https://detail.1688.com/offer/858357592612.html | L85: evidence/2026-09-10-raw-observations.json#/suppliers/0/result/content/0/text→JSON/data/80
A86: 2026-09-10T13:40:27.931Z | B86: 洗衣袋套装 | C86: 987191317000 | D86: ✅洗衣袋洗衣机过滤网袋套装刺绣收纳袋文胸内衣护洗袋厂家直销 | F86: 0 | G86: 0 | H86: False | I86: 0 | J86: 0价/缺失无效 | K86: https://detail.1688.com/offer/987191317000.html | L86: evidence/2026-09-10-raw-observations.json#/suppliers/0/result/content/0/text→JSON/data/81
A87: 2026-09-10T13:40:27.931Z | B87: 洗衣袋套装 | C87: 649948708566 | D87: 加厚洗衣袋细网文胸衣物洗护网袋机洗家用防变形超大网兜套装批发 | E87: 义乌市硕甲日用品有限公司 | F87: 1.75 | G87: 1 | H87: True | I87: 13655416 | J87: 历史起价待复核 | K87: https://detail.1688.com/offer/649948708566.html | L87: evidence/2026-09-10-raw-observations.json#/suppliers/0/result/content/0/text→JSON/data/82
A88: 2026-09-10T13:40:27.931Z | B88: 洗衣袋套装 | C88: 898083970582 | D88: 新款大容量折叠洗衣袋多功能简约抽绳束口袋透气防潮便携收纳袋 | F88: 0 | G88: 0 | H88: False | I88: 0 | J88: 0价/缺失无效 | K88: https://detail.1688.com/offer/898083970582.html | L88: evidence/2026-09-10-raw-observations.json#/suppliers/0/result/content/0/text→JSON/data/83
A89: 2026-09-10T13:40:27.931Z | B89: 洗衣袋套装 | C89: 773074807232 | D89: 跨境亚马逊现货洗衣袋束口袋抽绳居家旅行收纳袋脏衣袋 | F89: 0 | G89: 0 | H89: False | I89: 0 | J89: 0价/缺失无效 | K89: https://detail.1688.com/offer/773074807232.html | L89: evidence/2026-09-10-raw-observations.json#/suppliers/0/result/content/0/text→JSON/data/84
A90: 2026-09-10T13:40:27.931Z | B90: 洗衣袋套装 | C90: 639777060808 | D90: 家用洗衣袋圆柱形印花护洗袋防变形胸罩护洗袋洗衣机印花网袋网兜 | E90: 义乌市合达电子商务商行 | F90: 1.19 | G90: 1 | H90: True | I90: 100926879 | J90: 历史起价待复核 | K90: https://detail.1688.com/offer/639777060808.html | L90: evidence/2026-09-10-raw-observations.json#/suppliers/0/result/content/0/text→JSON/data/85
A91: 2026-09-10T13:40:27.931Z | B91: 洗衣袋套装 | C91: 642959237785 | D91: 厂家直销洗衣机衣物清洗网袋三明治涤纶洗鞋袋网兜护洗袋批发 | E91: 上海仙桂实业有限公司 | F91: 4 | G91: 1 | H91: False | I91: 82962 | J91: 历史起价待复核 | K91: https://detail.1688.com/offer/642959237785.html | L91: evidence/2026-09-10-raw-observations.json#/suppliers/0/result/content/0/text→JSON/data/86
A92: 2026-09-10T13:40:27.931Z | B92: 洗衣袋套装 | C92: 823893327026 | D92: 双层洗衣袋家用洗毛衣网兜加厚大号细网衣物护洗袋机洗衣服洗衣机 | F92: 0 | G92: 0 | H92: False | I92: 0 | J92: 0价/缺失无效 | K92: https://detail.1688.com/offer/823893327026.html | L92: evidence/2026-09-10-raw-observations.json#/suppliers/0/result/content/0/text→JSON/data/87
A93: 2026-09-10T13:40:27.931Z | B93: 洗衣袋套装 | C93: 1016445945717 | D93: 加厚内衣洗衣袋细网套装文胸洗护袋网状防变形特大号网袋厂家批发 | F93: 0 | G93: 0 | H93: False | I93: 0 | J93: 0价/缺失无效 | K93: https://detail.1688.com/offer/1016445945717.html | L93: evidence/2026-09-10-raw-observations.json#/suppliers/0/result/content/0/text→JSON/data/88
A94: 2026-09-10T13:40:27.931Z | B94: 洗衣袋套装 | C94: 1002197616374 | D94: 洗衣袋家用洗毛衣网兜大号洗衣机网袋护洗袋内衣洗衣机专用防变形 | F94: 0 | G94: 0 | H94: False | I94: 0 | J94: 0价/缺失无效 | K94: https://detail.1688.com/offer/1002197616374.html | L94: evidence/2026-09-10-raw-observations.json#/suppliers/0/result/content/0/text→JSON/data/89
A95: 2026-09-10T13:40:27.931Z | B95: 洗衣袋套装 | C95: 900357593445 | D95: 幼儿园宝宝入园衣服儿童入学必备用品衣物收纳袋密封分装脏衣袋子 | F95: 0 | G95: 0 | H95: False | I95: 0 | J95: 0价/缺失无效 | K95: https://detail.1688.com/offer/900357593445.html | L95: evidence/2026-09-10-raw-observations.json#/suppliers/0/result/content/0/text→JSON/data/90
A96: 2026-09-10T13:40:27.931Z | B96: 洗衣袋套装 | C96: 814563719256 | D96: 洗衣袋洗衣机专用加厚细网防变形袋家用洗护袋涤纶护洗袋 | F96: 0 | G96: 0 | H96: False | I96: 0 | J96: 0价/缺失无效 | K96: https://detail.1688.com/offer/814563719256.html | L96: evidence/2026-09-10-raw-observations.json#/suppliers/0/result/content/0/text→JSON/data/91
A97: 2026-09-10T13:40:27.931Z | B97: 洗衣袋套装 | C97: 666589127054 | D97: 洗衣袋洗衣机专用网袋家用洗毛衣衣服内衣袜子粗细网兜大号防变形 | F97: 0 | G97: 0 | H97: False | I97: 0 | J97: 0价/缺失无效 | K97: https://detail.1688.com/offer/666589127054.html | L97: evidence/2026-09-10-raw-observations.json#/suppliers/0/result/content/0/text→JSON/data/92
A98: 2026-09-10T13:40:27.931Z | B98: 洗衣袋套装 | C98: 967202351772 | D98: 护洗袋洗衣机机洗粗网袋内衣毛衣洗衣服网袋 | F98: 0 | G98: 0 | H98: False | I98: 0 | J98: 0价/缺失无效 | K98: https://detail.1688.com/offer/967202351772.html | L98: evidence/2026-09-10-raw-observations.json#/suppliers/0/result/content/0/text→JSON/data/93
A99: 2026-09-10T13:40:27.931Z | B99: 洗衣袋套装 | C99: 974986223620 | D99: 跨境亚马逊现货洗衣袋束口袋抽绳居家旅行收纳袋脏衣袋 | F99: 0 | G99: 0 | H99: False | I99: 0 | J99: 0价/缺失无效 | K99: https://detail.1688.com/offer/974986223620.html | L99: evidence/2026-09-10-raw-observations.json#/suppliers/0/result/content/0/text→JSON/data/94
A100: 2026-09-10T13:40:27.931Z | B100: 洗衣袋套装 | C100: 995141970762 | D100: 批发洗衣袋洗衣机专用防变形网袋细网粗网大孔加厚双层洗衣袋套装 | F100: 0 | G100: 0 | H100: False | I100: 0 | J100: 0价/缺失无效 | K100: https://detail.1688.com/offer/995141970762.html | L100: evidence/2026-09-10-raw-observations.json#/suppliers/0/result/content/0/text→JSON/data/95
A101: 2026-09-10T13:40:27.931Z | B101: 洗衣袋套装 | C101: 710233346685 | D101: 印花洗衣袋洗衣机超大专用细网袋洗毛衣衣服内衣加大号家用护洗袋 | F101: 0 | G101: 0 | H101: False | I101: 0 | J101: 0价/缺失无效 | K101: https://detail.1688.com/offer/710233346685.html | L101: evidence/2026-09-10-raw-observations.json#/suppliers/0/result/content/0/text→JSON/data/96
A102: 2026-09-10T13:40:27.931Z | B102: 洗衣袋套装 | C102: 958622601559 | D102: 家用便携晾衣袋围裙 跨境亚马逊temu晒衣围兜批发 | F102: 0 | G102: 0 | H102: False | I102: 0 | J102: 0价/缺失无效 | K102: https://detail.1688.com/offer/958622601559.html | L102: evidence/2026-09-10-raw-observations.json#/suppliers/0/result/content/0/text→JSON/data/97
A103: 2026-09-10T13:40:27.931Z | B103: 洗衣袋套装 | C103: 902369462756 | D103: 160克三明治洗帽袋帽子洗护袋加厚防变形洗衣机专用洗衣袋批发 | F103: 0 | G103: 0 | H103: False | I103: 0 | J103: 0价/缺失无效 | K103: https://detail.1688.com/offer/902369462756.html | L103: evidence/2026-09-10-raw-observations.json#/suppliers/0/result/content/0/text→JSON/data/98
A104: 2026-09-10T13:40:27.931Z | B104: 洗衣袋套装 | C104: 1029105426208 | D104: 洗衣袋护洗袋套装家用洗衣机机洗凝珠留香珠专用加厚洗衣凝珠网袋 | F104: 0 | G104: 0 | H104: False | I104: 0 | J104: 0价/缺失无效 | K104: https://detail.1688.com/offer/1029105426208.html | L104: evidence/2026-09-10-raw-observations.json#/suppliers/0/result/content/0/text→JSON/data/99
A105: 2026-09-10T13:40:27.931Z | B105: 旅行收纳袋套装 | C105: 847068328975 | D105: 旅行收纳袋六件套布艺包旅游防水内衣内裤行李箱衣服收纳分装袋 | E105: 义乌市辉弘箱包有限公司 | F105: 7.8 | G105: 1 | H105: False | I105: 467097 | J105: 历史起价待复核 | K105: https://detail.1688.com/offer/847068328975.html | L105: evidence/2026-09-10-raw-observations.json#/suppliers/1/result/content/0/text→JSON/data/0
A106: 2026-09-10T13:40:27.931Z | B106: 旅行收纳袋套装 | C106: 612759901613 | D106: 批发旅行收纳套装旅行收纳袋8件套八件套装旅游衣物分类收纳包 | E106: 义乌市瑟辰箱包有限公司 | F106: 9.8 | G106: 2 | H106: True | I106: 1189800 | J106: 历史起价待复核 | K106: https://detail.1688.com/offer/612759901613.html | L106: evidence/2026-09-10-raw-observations.json#/suppliers/1/result/content/0/text→JSON/data/1
A107: 2026-09-10T13:40:27.931Z | B107: 旅行收纳袋套装 | C107: 669090162462 | D107: 旅行收纳袋套装出差衣物束口11件套收纳包化妆洗漱折叠网格收纳袋 | E107: 义乌市正穗箱包有限公司 | F107: 14.4 | G107: 1 | H107: True | I107: 115831135 | J107: 历史起价待复核 | K107: https://detail.1688.com/offer/669090162462.html | L107: evidence/2026-09-10-raw-observations.json#/suppliers/1/result/content/0/text→JSON/data/2
A108: 2026-09-10T13:40:27.931Z | B108: 旅行收纳袋套装 | C108: 902357966626 | D108: 斜纹7件套8件套旅行收纳袋套装大容量多用途分类衣物洗漱收纳包 | E108: 义乌市欣纳箱包有限公司 | F108: 12.9 | G108: 1 | H108: True | I108: 1536353 | J108: 历史起价待复核 | K108: https://detail.1688.com/offer/902357966626.html | L108: evidence/2026-09-10-raw-observations.json#/suppliers/1/result/content/0/text→JSON/data/3
A109: 2026-09-10T13:40:27.931Z | B109: 旅行收纳袋套装 | C109: 856807873812 | D109: 印花压缩旅行收纳袋折叠套装束口衣物包行李分装网格收纳袋搬家 | E109: 义乌市南睿箱包有限公司 | F109: 26.5 | G109: 1 | H109: True | I109: 472668 | J109: 历史起价待复核 | K109: https://detail.1688.com/offer/856807873812.html | L109: evidence/2026-09-10-raw-observations.json#/suppliers/1/result/content/0/text→JSON/data/4
A110: 2026-09-10T13:40:27.931Z | B110: 旅行收纳袋套装 | C110: 733720708391 | D110: 旅行收纳袋套装斜纹七件套出差旅游行李箱衣物鞋子整理分装袋 | E110: 江西联诚家居用品有限公司 | F110: 13 | G110: 1 | H110: True | I110: 169486 | J110: 历史起价待复核 | K110: https://detail.1688.com/offer/733720708391.html | L110: evidence/2026-09-10-raw-observations.json#/suppliers/1/result/content/0/text→JSON/data/5
A111: 2026-09-10T13:40:27.931Z | B111: 旅行收纳袋套装 | C111: 711213182201 | D111: 旅行收纳袋七件套行李箱衣物整理袋出差旅游衣服鞋内衣分装收纳袋 | E111: 义乌市华磊箱包有限公司 | F111: 8 | G111: 1 | H111: True | I111: 2710415 | J111: 历史起价待复核 | K111: https://detail.1688.com/offer/711213182201.html | L111: evidence/2026-09-10-raw-observations.json#/suppliers/1/result/content/0/text→JSON/data/6
A112: 2026-09-10T13:40:27.931Z | B112: 旅行收纳袋套装 | C112: 835044853744 | D112: 跨境旅行收纳袋套装数码洗漱化妆品分装收纳包衣服鞋子行李旅行袋 | E112: 横峰县鼎胜箱包厂 | F112: 0 | G112: 1 | H112: False | I112: 0 | J112: 0价/缺失无效 | K112: https://detail.1688.com/offer/835044853744.html | L112: evidence/2026-09-10-raw-observations.json#/suppliers/1/result/content/0/text→JSON/data/7
A113: 2026-09-10T13:40:27.931Z | B113: 旅行收纳袋套装 | C113: 775894572345 | D113: 一件代发干湿分离旅行收纳包洗漱化妆包透明沥水大容量手提收纳包 | E113: 常州宝锦纺织有限公司 | F113: 0 | G113: 0 | H113: False | I113: 0 | J113: 0价/缺失无效 | K113: https://detail.1688.com/offer/775894572345.html | L113: evidence/2026-09-10-raw-observations.json#/suppliers/1/result/content/0/text→JSON/data/8
A114: 2026-09-10T13:40:27.931Z | B114: 旅行收纳袋套装 | C114: 605378793755 | D114: 旅行收纳袋家居收纳包套装压缩三件套尼龙材料亚马逊多场景收纳 | E114: 义乌市卓逸箱包有限公司 | F114: 26 | G114: 1 | H114: True | I114: 31287 | J114: 历史起价待复核 | K114: https://detail.1688.com/offer/605378793755.html | L114: evidence/2026-09-10-raw-observations.json#/suppliers/1/result/content/0/text→JSON/data/9
A115: 2026-09-10T13:40:27.931Z | B115: 旅行收纳袋套装 | C115: 915193655734 | D115: 亚马逊跨境旅行收纳七八九十件套装旅游内衣衣物分类整理收纳包袋 | E115: 义乌市辉弘箱包有限公司 | F115: 0 | G115: 1 | H115: False | I115: 0 | J115: 0价/缺失无效 | K115: https://detail.1688.com/offer/915193655734.html | L115: evidence/2026-09-10-raw-observations.json#/suppliers/1/result/content/0/text→JSON/data/10
...

Sheet 07_历史市场原值
A1: 07 · 历史市场原值
A2: 原始价格和销量故意不进入正式利润/市场规模。sales_calc_time=1970及PH/THB冲突无法证明真实近期需求。
A4: 记录ID | B4: 采集时间 | C4: 关键词 | D4: 商品ID | E4: 店铺ID | F4: 原始标题 | G4: 原始价格 | H4: 币种状态 | I4: 原始销量字段 | J4: 销量计算日 | K4: 评分原值 | L4: 评论数原值 | M4: 本轮可用于放行 | N4: 证据定位
A5: M-0001 | B5: 2026-09-10T13:40:27.931Z | C5: storage organizer | D5: 25675666003 | E5: 74897176 | F5: Desktop Organizer #163 Multilayer Storage Drawer Crafts Makeup Accessories Medicine (ramdom color) | G5: 120 | H5: 未确认：PH查询，接口字典价格标THB | I5: 2236 | J5: 1970-01-01 | K5: 4.42 | L5: 1474 | M5: 否，待币种/窗口/SKU核实 | N5: evidence/2026-09-10-raw-observations.json#/market/0/result/content/0/text→JSON/data/0
A6: M-0002 | B6: 2026-09-10T13:40:27.931Z | C6: storage organizer | D6: 45914455255 | E6: 727712488 | F6: COD Foldable Shoe Box Shoe Rack Cabinet Transparent Storage Organizer Installation-Free | G6: 395 | H6: 未确认：PH查询，接口字典价格标THB | I6: 1416 | J6: 1970-01-01 | K6: 4.85 | L6: 68 | M6: 否，待币种/窗口/SKU核实 | N6: evidence/2026-09-10-raw-observations.json#/market/0/result/content/0/text→JSON/data/1
A7: M-0003 | B7: 2026-09-10T13:40:27.931Z | C7: storage organizer | D7: 42964121227 | E7: 1343835021 | F7: 3pcs 5 Grids Desktop Organizer Storage Box Large Capacity Office Storage Box Cosmetics Desk Desktop Storage | G7: 66 | H7: 未确认：PH查询，接口字典价格标THB | I7: 361 | J7: 1970-01-01 | K7: 4.74 | L7: 2819 | M7: 否，待币种/窗口/SKU核实 | N7: evidence/2026-09-10-raw-observations.json#/market/0/result/content/0/text→JSON/data/2
A8: M-0004 | B8: 2026-09-10T13:40:27.931Z | C8: storage organizer | D8: 29682979631 | E8: 1491372234 | F8: 6 Grids Desktop Stationery Organizer Makeup Organizer Drawer Jewelry Accessories Storage Box(White) | G8: 93 | H8: 未确认：PH查询，接口字典价格标THB | I8: 238 | J8: 1970-01-01 | K8: 4.79 | L8: 704 | M8: 否，待币种/窗口/SKU核实 | N8: evidence/2026-09-10-raw-observations.json#/market/0/result/content/0/text→JSON/data/3
A9: M-0005 | B9: 2026-09-10T13:40:27.931Z | C9: storage organizer | D9: 47101644762 | E9: 813327496 | F9: Storage Organizer Acrylic Transparents Shoe Box Foldable Shoe Rack Shelf Installation Free | G9: 445 | H9: 未确认：PH查询，接口字典价格标THB | I9: 170 | J9: 1970-01-01 | K9: 4.68 | L9: 256 | M9: 否，待币种/窗口/SKU核实 | N9: evidence/2026-09-10-raw-observations.json#/market/0/result/content/0/text→JSON/data/4
A10: M-0006 | B10: 2026-09-10T13:40:27.931Z | C10: storage organizer | D10: 45605408192 | E10: 1175541521 | F10: 8 Grids Money Organizer Box Financial Desktop Cashier Cash Box Drawer Register Coin storage box | G10: 149 | H10: 未确认：PH查询，接口字典价格标THB | I10: 134 | J10: 1970-01-01 | K10: 4.86 | L10: 72 | M10: 否，待币种/窗口/SKU核实 | N10: evidence/2026-09-10-raw-observations.json#/market/0/result/content/0/text→JSON/data/5
A11: M-0007 | B11: 2026-09-10T13:40:27.931Z | C11: storage organizer | D11: 51412239867 | E11: 1776503098 | F11: Long A4 File Organizer Sturdy Plastic Folder for School Homework Sorting Office Data Collection | G11: 80 | H11: 未确认：PH查询，接口字典价格标THB | I11: 132 | J11: 1970-01-01 | K11: 4.88 | L11: 42 | M11: 否，待币种/窗口/SKU核实 | N11: evidence/2026-09-10-raw-observations.json#/market/0/result/content/0/text→JSON/data/6
A12: M-0008 | B12: 2026-09-10T13:40:27.931Z | C12: storage organizer | D12: 24447895116 | E12: 1093841757 | F12: Pen Holder Large Capacity Desktop Organizer Plastic Storage Box Student Stationery Stand Office Desk | G12: 41 | H12: 未确认：PH查询，接口字典价格标THB | I12: 125 | J12: 1970-01-01 | K12: 4.88 | L12: 298 | M12: 否，待币种/窗口/SKU核实 | N12: evidence/2026-09-10-raw-observations.json#/market/0/result/content/0/text→JSON/data/7
A13: M-0009 | B13: 2026-09-10T13:40:27.931Z | C13: storage organizer | D13: 42274507221 | E13: 1630671336 | F13: Long File Organizer 13-Layer Handle Folder Test Paper Document Storage Portable File Folder | G13: 91 | H13: 未确认：PH查询，接口字典价格标THB | I13: 108 | J13: 1970-01-01 | K13: 4.85 | L13: 1003 | M13: 否，待币种/窗口/SKU核实 | N13: evidence/2026-09-10-raw-observations.json#/market/0/result/content/0/text→JSON/data/8
A14: M-0010 | B14: 2026-09-10T13:40:27.931Z | C14: storage organizer | D14: 25181554000 | E14: 21704787 | F14: Desktop Storage Rack Organizer for Kitchen Bathroom Office Dorm Cosmetic Stationery Holder | G14: 19 | H14: 未确认：PH查询，接口字典价格标THB | I14: 103 | J14: 1970-01-01 | K14: 4.88 | L14: 172 | M14: 否，待币种/窗口/SKU核实 | N14: evidence/2026-09-10-raw-observations.json#/market/0/result/content/0/text→JSON/data/9
A15: M-0011 | B15: 2026-09-10T13:40:27.931Z | C15: storage organizer | D15: 25544554587 | E15: 699515539 | F15: Reusable Non-woven Drawstring Shoes Handbag Clothes Storage Organizer Dustproof Pouch Bag Dust Cover | G15: 15 | H15: 未确认：PH查询，接口字典价格标THB | I15: 102 | J15: 1970-01-01 | K15: 4.67 | L15: 18 | M15: 否，待币种/窗口/SKU核实 | N15: evidence/2026-09-10-raw-observations.json#/market/0/result/content/0/text→JSON/data/10
A16: M-0012 | B16: 2026-09-10T13:40:27.931Z | C16: storage organizer | D16: 25022119838 | E16: 21704787 | F16: Clear Acrylic File Organizer Sturdy Desk File Organizer Shelf Book Holder Purse Handbag Clutch Divid | G16: 109 | H16: 未确认：PH查询，接口字典价格标THB | I16: 89 | J16: 1970-01-01 | K16: 4.84 | L16: 76 | M16: 否，待币种/窗口/SKU核实 | N16: evidence/2026-09-10-raw-observations.json#/market/0/result/content/0/text→JSON/data/11
... A224: M-0220 | B224: 2026-09-11T13:49:14.285Z | C224: travel accessories organizer | D224: 22605566723 | E224: 258609910 | F224: TRAVEL POUCH CLEAR ORGANIZERS(16x21) | G224: 32 | H224: 未确认：PH查询，接口字典价格标THB | I224: 313 | J224: 1970-01-01 | K224: 4.75 | L224: 1476 | M224: 否，待币种/窗口/SKU核实 | N224: evidence/2026-09-11-raw-observations.json#/queries/3/result/content/0/text→JSON/data/19

Sheet 08_数据问题
A1: 08 · 数据问题
A2: 历史问题逐条保留；重复记录是跨查询重复观测，不能误说重复订单。来源不一致要解决，不静默改币种或日期。
A4: 问题ID | B4: 类型 | C4: 字段 | D4: 原始值 | E4: 影响 | F4: 来源 | G4: 修复动作 | H4: 状态
A5: EX-0001 | B5: 事实 | C5: sales_calc_time | D5: 1970-01-01 | E5: 无法确认30天窗口，阻断需求/趋势/集中度 | F5: outputs/shopee-plan-2026-09-10/raw-observations.json#/market/0/result/content/0/text→JSON/data/0/sales_calc_time | G5: 重取同一明确窗口销量；原值保留 | H5: 未解决
A6: EX-0002 | B6: 事实 | C6: sales_calc_time | D6: 1970-01-01 | E6: 无法确认30天窗口，阻断需求/趋势/集中度 | F6: outputs/shopee-plan-2026-09-10/raw-observations.json#/market/0/result/content/0/text→JSON/data/1/sales_calc_time | G6: 重取同一明确窗口销量；原值保留 | H6: 未解决
A7: EX-0003 | B7: 事实 | C7: sales_calc_time | D7: 1970-01-01 | E7: 无法确认30天窗口，阻断需求/趋势/集中度 | F7: outputs/shopee-plan-2026-09-10/raw-observations.json#/market/0/result/content/0/text→JSON/data/2/sales_calc_time | G7: 重取同一明确窗口销量；原值保留 | H7: 未解决
A8: EX-0004 | B8: 事实 | C8: sales_calc_time | D8: 1970-01-01 | E8: 无法确认30天窗口，阻断需求/趋势/集中度 | F8: outputs/shopee-plan-2026-09-10/raw-observations.json#/market/0/result/content/0/text→JSON/data/3/sales_calc_time | G8: 重取同一明确窗口销量；原值保留 | H8: 未解决
A9: EX-0005 | B9: 事实 | C9: sales_calc_time | D9: 1970-01-01 | E9: 无法确认30天窗口，阻断需求/趋势/集中度 | F9: outputs/shopee-plan-2026-09-10/raw-observations.json#/market/0/result/content/0/text→JSON/data/4/sales_calc_time | G9: 重取同一明确窗口销量；原值保留 | H9: 未解决
A10: EX-0006 | B10: 事实 | C10: sales_calc_time | D10: 1970-01-01 | E10: 无法确认30天窗口，阻断需求/趋势/集中度 | F10: outputs/shopee-plan-2026-09-10/raw-observations.json#/market/0/result/content/0/text→JSON/data/5/sales_calc_time | G10: 重取同一明确窗口销量；原值保留 | H10: 未解决
A11: EX-0007 | B11: 事实 | C11: sales_calc_time | D11: 1970-01-01 | E11: 无法确认30天窗口，阻断需求/趋势/集中度 | F11: outputs/shopee-plan-2026-09-10/raw-observations.json#/market/0/result/content/0/text→JSON/data/6/sales_calc_time | G11: 重取同一明确窗口销量；原值保留 | H11: 未解决
A12: EX-0008 | B12: 事实 | C12: sales_calc_time | D12: 1970-01-01 | E12: 无法确认30天窗口，阻断需求/趋势/集中度 | F12: outputs/shopee-plan-2026-09-10/raw-observations.json#/market/0/result/content/0/text→JSON/data/7/sales_calc_time | G12: 重取同一明确窗口销量；原值保留 | H12: 未解决
A13: EX-0009 | B13: 事实 | C13: sales_calc_time | D13: 1970-01-01 | E13: 无法确认30天窗口，阻断需求/趋势/集中度 | F13: outputs/shopee-plan-2026-09-10/raw-observations.json#/market/0/result/content/0/text→JSON/data/8/sales_calc_time | G13: 重取同一明确窗口销量；原值保留 | H13: 未解决
A14: EX-0010 | B14: 事实 | C14: sales_calc_time | D14: 1970-01-01 | E14: 无法确认30天窗口，阻断需求/趋势/集中度 | F14: outputs/shopee-plan-2026-09-10/raw-observations.json#/market/0/result/content/0/text→JSON/data/9/sales_calc_time | G14: 重取同一明确窗口销量；原值保留 | H14: 未解决
A15: EX-0011 | B15: 事实 | C15: sales_calc_time | D15: 1970-01-01 | E15: 无法确认30天窗口，阻断需求/趋势/集中度 | F15: outputs/shopee-plan-2026-09-10/raw-observations.json#/market/0/result/content/0/text→JSON/data/10/sales_calc_time | G15: 重取同一明确窗口销量；原值保留 | H15: 未解决
... A287: NEW-002 | B287: 本轮访问限制 | C287: 1688详情读取 | D287: 网页读取失败；浏览器站点安全策略阻止 | E287: 无法取得当前SKU、阶梯价和现货证据 | F287: source-log.json | G287: 提供用户合法取得的SKU报价与包装物流证据；不绕过限制 | H287: 未解决

Sheet 09_市场与官方证据
A1: 09 · 市场与官方证据
A2: 官方宏观数据说明市场背景，不证明任何单品可以盈利。所有比例口径保留；第三方搜索结果不作为正式当前报价。
A4: 来源ID | B4: 主题 | C4: 本轮读取结果 | D4: 结论性质 | E4: 适用限制 | F4: 来源链接/文件 | G4: 读取日期
A5: O01 | B5: 菲律宾数字经济背景 | C5: PSA 2026-04-30发布：2025年数字经济GVA为2.74万亿PHP，占GDP9.8%，按现价较2024年增长5.4%。 | D5: 官方事实 | E5: 这是全国数字经济增加值，不是Shopee GMV。不能据此推出单品需求或利润。 | F5: https://psa.gov.ph/system/files/sad/Press%20Release_2025%20PDESA_0.pdf | G5: 2026-09-15
A6: O02 | B6: 全国电商增加值 | C6: PSA图表列2025年电商GVA为8804.6亿PHP，占数字经济32.2%。 | D6: 官方事实 | E6: 这是电商增加值口径，不是交易总额，不代表Shopee独有份额。 | F6: https://psa.gov.ph/sites/default/files/infographics/Infographic_2025%20PDESA.pdf | G6: 2026-09-15
A7: O03 | B7: Shopee禁限售 | C7: 当前公开政策把合法合规责任放在卖家；禁止/限制清单非穷尽且会更新。 | D7: 官方规则 | E7: 逐SKU对照；药物、受限设备等排除；无列表命中不代表已批准。 | F7: https://help.shopee.ph/portal/4/article/77276 | G7: 2026-09-15
A8: O04 | B8: BPS强制认证 | C8: BPS要求受管制产品按PS/ICC方案具备相应标识。 | D8: 官方规则 | E8: 概述页写87，明细页编号到111；统计口径/更新可能不同，不写固定数量作为准入条件，以实际类别/规格清单为准。 | F8: https://bps.dti.gov.ph/product-certification/list-of-products-under-mandatory-certification | G8: 2026-09-15
A9: O05 | B9: 菲律宾跨境收费 | C9: 条款§23普通交易费列2.24%含VAT且取整比索；处理费每成功订单₱5、每月前50成功单豁免；境外卖家跨境佣金按另行通知。 | D9: 官方规则 | E9: 不能替代本店佣金、活动与结算费表；增长、平台运费计划等逐项确认适用。 | F9: https://help.shopee.ph/portal/4/article/77272 | G9: 2026-09-15
A10: O06 | B10: 平台整体背景 | C10: Sea披露2026Q2 Shopee整体订单42亿，同比增长27.5%；GMV383亿美元，同比增长28.4%。 | D10: 发行人一手事实 | E10: 覆盖Shopee整体经营地区，不能视为菲律宾站增速或份额。只作背景。 | F10: https://www.sec.gov/Archives/edgar/data/1703399/000119312526344596/d120948dex991.htm | G10: 2026-09-15
A11: O07 | B11: FDA监管边界 | C11: FDA有针对HUHS机构许可的官方办理材料；化学相关产品需要先判监管归类。 | D11: 官方资料/经营排除 | E11: 本次按用户约束排除化学相关；不是声称所有收纳品都需FDA许可。 | F11: https://www.fda.gov.ph/information-education-and-communication-iec-materials-relative-to-the-licensing-of-household-urban-hazardous-substances-huhs-establishments-covered-under-administrative-order-no-2019-0019-and-fd/ | G11: 2026-09-15
A12: W01 | B12: 公开店铺有限补证 | C12: Shopee Paccube公开页展示4件Packing Cubes ₱1050、5.0、239 sold；双面压缩款₱690、4.9、178 sold。 | D12: 公开页面展示值 | E12: 已售未说明时间窗；品牌本地制作，规格、配送、权利与跨境仿照不可比。不能计为30天样本；1050高于既有1000参考。 | F12: https://shopee.ph/paccube | G12: 2026-09-15
A13: L01 | B13: 现有经营基线 | C13: 非商城跨境/SLS；20,000启动资金；无销售库存；20%和15元门槛。 | D13: 工作区历史记录 | E13: 当前余额与店铺30天业绩仍缺；本次500元及60分钟要求优先。 | F13: Shopee菲律宾自动选品上架系统-主开发Prompt-v0.3.md | G13: 2026-09-15读取
A14: L02 | B14: 历史市场/货源原始文件 | C14: 220条市场观测；196个商品ID；600条供应商观测。 | D14: 本地数据审计 | E14: 采集于9月10/11日；币种、窗口及SKU报价问题未闭环。 | F14: evidence/input-manifest.json | G14: 2026-09-15审计
A15: T01 | B15: 本轮源访问状态 | C15: Sorftime一次正常查询返回额度耗尽；1688网页未读取成功，浏览器策略阻止。 | D15: 工具执行事实 | E15: 未购买额度或绕过访问限制。只能完成已有证据部分。 | F15: source-log.json | G15: 2026-09-15

Sheet 10_SOP与阈值
A1: 10 · SOP与阈值
A2: 产能目标需先有有效候选储备。首次资料建档、供应商等待与样品到货不能压缩成一小时；三天试运行后再承诺产能。
A4: 步骤 | B4: 时间目标/频率 | C4: 输入 | D4: 处理和产出 | E4: 放行条件 | F4: 失败处理
A5: 0 建档 | B5: 首次，独立计时 | C5: 店铺类别/费率/物流/税/现金；3–5家供应商 | D5: 形成有有效期的规则库与准确SKU模板 | E5: 关键口径可核实 | F5: 缺口只阻断相应结果
A6: 1 每日刷新 | B6: Agent预处理 | C6: 费用/库存/报价变更、候选历史 | D6: 收50–100条线索、不同SPU去重 | E6: 合法来源且时间可追溯 | F6: 接口失败保留旧观测日期
A7: 2 数据及合规 | B7: Agent预处理 | C7: PH商品/销售窗/权利/产品属性 | D7: 币种、期间、规格、禁限售拦截 | E7: 数据有效、合规明确 | F7: 未知补证；明确违规排除
A8: 3 需求竞争 | B8: Agent预处理 | C8: 10–20同规格竞品、价格、店铺、评论 | D8: 样本/店铺需求、CR3、到手价分位、差异验证 | E8: 至少10款/5店、300件、3店30件；CR3≤70%等 | F8: 不以全国增长/单链接累计已售替代
A9: 4 供货利润 | B9: Agent预处理 | C9: 1688逐SKU报价、包重、完整成本 | D9: 基准+压力+采购上限+500元测试预算 | E9: 20%且15元；压力≥0；测试≤500 | F9: 未核实费用不填0；不能标通过
A10: 5 组合审核 | B10: 人工5分钟 | C10: 当天现金、未决损失、候选风险 | D10: 全店累计现金/亏损核查 | E10: 应急5000；月上限4000；新增占资≤80% | F10: 冻结新增测试，不影响已有履约
A11: 6 审市场证据 | B11: 人工10分钟 | C11: Excel事实与竞争摘要 | D11: 看有效样本、价格、跨境竞争、差异 | E11: 证据足够支持小测 | F11: 抽查疑点移出批审
A12: 7 审供应成本 | B12: 人工20分钟 | C12: 22逐品/费用明细/样品证据 | D12: 审可行报价、运费、预算、有效期 | E12: 当前SKU/报价和压力通过 | F12: 不因凑10个降低阈值
A13: 8 批量人审 | B13: 人工20分钟 | C13: 证据完整的10–20不同SPU | D13: 记录批准/拒绝/补证与版本 | E13: 所有硬门槛通过 | F13: 关键输入变化旧批准失效
A14: 9 存档 | B14: 人工5分钟 | C14: 审核记录与源快照 | D14: 输出日报/Excel/待补证清单 | E14: 审阅总时长60分钟目标 | F14: 首次建库/等待报价另计
A15: 10 复盘 | B15: 7/14/28天 | C15: 曝光、点击、访问、订单、售后、结算 | D15: 验证漏斗与全队列成本；决定继续/停止 | E15: 先在500元累计上限内执行；证据足够再讨论扩测 | F15: 未成熟/零曝光不说产品无需求

Sheet 11_复盘与待补资料
A1: 11 · 复盘与待补资料
A2: 店主审核后仍需另行授权外部操作；本轮没有产生采购、广告或上架。
A4: 类型 | B4: 需要的数据 | C4: 用途/最小范围 | D4: 本轮状态 | E4: 责任/下一步
A5: P0 店铺费用 | B5: 本店类目佣金/跨境费、支付、活动、增长、运费计划、固定/预售费；有效期 | C5: 当前设置/官方通知；如有，提供3–5笔完整结算作对账 | D5: 缺失 | E5: 店主提供已有资料；不代填公共示例
A6: P0 SLS和云仓 | B6: 渠道运费表、首续重/体积系数、净运费算法、贴标/包材/仓储、时效 | C6: 只需当前用的一个仓和一个SLS渠道 | D6: 缺失 | E6: 费用和DTS/入仓截止一起核实
A7: P0 市场 | B7: PH/PHP明确的同规格10–20竞品/方向，独立店与30天窗口销量 | C7: 来源/采集时间/统计开始结束；能区分本土/跨境与SKU销量 | D7: 历史不合格 | E7: 恢复已有数据源或提供合法导出
A8: P0 1688逐SKU | B8: offer/SKU、规格件数、单件/阶梯价、MOQ/代发、库存、备货、包重、含税/运费 | C8: 每款至少1主供应商；24小时内；建议备用1家 | D8: 只有历史线索 | E8: 不把0.03或0.6等起价当套装价
A9: P0 资金和经营 | B9: 今天人民币可用余额、已付/未付承诺、当月损失、未决退件 | C9: 近30天订单/销售/广告/退款及到账日；无则明确无 | D9: 缺失 | E9: 历史2万元不替代现金核验
A10: P1 样品/权利 | B10: 测量、拉链/承重/耐用/适配等检查、商标外观/图片授权 | C10: 按候选实际用途；仅空包/被动整理用品方向 | D10: 未验证 | E10: 用于关闭合规、质量、素材门槛
A11: 复盘7天 | B11: 上架可售、索引、曝光、点击 | C11: 记录链接状态和时间，检查是否获得真实访问 | D11: 尚未测试 | E11: 零曝光时不作需求失败结论
A12: 复盘14天 | B12: 访问/订单/退款，来源拆分广告与自然 | C12: 约100有效访问零单只作试行警报，排查价格与交运 | D12: 尚未测试 | E12: 所有测试支出累计到同SPU
A13: 复盘28天 | B13: 采购到实际可用人民币的全队列对账 | C13: 成功、失败、取消、退货、待结算均保留；成熟订单建议≥20 | D13: 尚未测试 | E13: 预算不足以形成样本时，结论是未证实，不是成功

Sheet 12_流程图
A1: 12 · 流程图
A2: 完整路径：证据→市场→供应→利润→500元测试→全店现金→人审。
A4: 每日选品流程 | B4: 判定 | C4: 输出 | D4: 备注
