Workbook

Sheet 00_审核入口
A1: 00 · 审核入口
A2: 先读这一页，再看01逐品结论。蓝色为可录入区；空白=未知。冻结结论必须由更新后的证据重新生成，改单元格不等于重新批准。 | F2: 46280.667
A4: 项目 | B4: 本轮结果 | C4: 含义及限制 | D4: 建议行动
A5: 运行时间 | B5: 2026-09-15T16:00:00+08:00 | C5: 以来源自身观测日期判断新鲜度 | D5: 不可用运行时间替换历史数据日期
A6: 历史候选记录 | B6: 1 | C6: 尚待准确规格/SPU复核；不能全部视为独立已验证商品 | D6: 见01与02
A7: 证据充分可测品 | B7: 1 | C7: 当前所有正式成本缺失；真实成功盈利数也为0 | D7: 不采购、不投放、不上架
A8: 原始市场记录 | B8: 0 | C8: 原始采集并非本轮新增，币种与窗口异常 | D8: 见07与08
A9: 1688历史货源记录 | B9: 0 | C9: 起价及整条offer，不是当前同SKU报价 | D9: 见06；0价不能当免费
A10: 利润门槛 | B10: 20% 且 15元 | C10: 完全成本预计利润/商品收入；条件，不是保证 | D10: 基准、采购上限、压力三项一起审
A11: 单品测试总成本 | B11: ≤500 CNY | C11: 含采购、物流、平台费、推广、样品、售后等 | D11: 不能仅限制采购额
A12: 一分钟审一款的前提 | B12: 标准化证据已完整 | C12: 目标每日人工60分钟；首次建库与等待报价另计 | D12: 先做3天计时试跑
A13: 验收缺口 | B13: 未达到≥10个成功选品 | C13: 市场有效窗口、同SKU报价、运费费用及现金资料不全 | D13: 补齐数据后重跑；不以历史候选充数

Sheet 03_逐品成本
A1: 03 · 逐品成本
A2: 一个销售单元=确定SKU一单（可以是套装）。成本预测不是已实现利润；仅填写准确报价和04全部费用，缺项不计算。报价观测≤24h另由Skill检查。修改后需重新生成审核结论。
A4: ID | B4: 产品 | C4: 券后商品PHP | D4: 额外补贴PHP | E4: CNY每PHP | F4: SKU采购价CNY | G4: 采购数量/套 | H4: 采购联动附加率 | I4: 样品拍摄等固定测试费 | J4: 测试计划单量 | K4: SKU报价证据 | L4: 报价截止 | M4: 费用口径审核 | N4: 费用完整 | O4: 其他成本CNY | P4: 压力其他成本 | Q4: 商品收入CNY | R4: 采购成本CNY | S4: 单件完全成本 | T4: 预计利润CNY | U4: 预计利润率 | V4: 采购上限CNY | W4: 组合压力利润 | X4: 测试总成本 | Y4: 500元最多测试单量 | Z4: 成本判定
A5: TEST | B5: 隔离合成算例，非市场产品 | C5: 1000 | D5: 0 | E5: .12 | F5: 10 | G5: 1 | H5: 0 | I5: 50 | J5: 5 | K5: 隔离测试SKU | L5: 46281.667 | M5: 已核实 | N5: =IF(COUNTIF('04_费用明细'!N5:N22,"完整")=18,"完整","待补证") | O5: =IF(N5="完整",SUM('04_费用明细'!L5:L22),"") | P5: =IF(N5="完整",SUM('04_费用明细'!M5:M22),"") | Q5: =IF(AND(COUNT(C5:J5)=8,C5>0,D5>=0,E5>0,F5>=0,G5>0,G5=INT(G5),H5>=0,I5>=0,J5>0,J5=INT(J5),K5<>"",ISNUMBER(L5),L5>='00_审核入口'!$F$2,M5="已核实",N5="完整"),ROUND(ROUND((C5+D5)*E5,10),2),"") | R5: =IF(AND(COUNT(C5:J5)=8,C5>0,D5>=0,E5>0,F5>=0,G5>0,G5=INT(G5),H5>=0,I5>=0,J5>0,J5=INT(J5),K5<>"",ISNUMBER(L5),L5>='00_审核入口'!$F$2,M5="已核实",N5="完整"),ROUND(ROUND(F5*G5*(1+H5),10),2),"") | S5: =IF(AND(COUNT(C5:J5)=8,C5>0,D5>=0,E5>0,F5>=0,G5>0,G5=INT(G5),H5>=0,I5>=0,J5>0,J5=INT(J5),K5<>"",ISNUMBER(L5),L5>='00_审核入口'!$F$2,M5="已核实",N5="完整"),R5+O5,"") | T5: =IF(AND(COUNT(C5:J5)=8,C5>0,D5>=0,E5>0,F5>=0,G5>0,G5=INT(G5),H5>=0,I5>=0,J5>0,J5=INT(J5),K5<>"",ISNUMBER(L5),L5>='00_审核入口'!$F$2,M5="已核实",N5="完整"),Q5-S5,"") | U5: =IF(AND(COUNT(C5:J5)=8,C5>0,D5>=0,E5>0,F5>=0,G5>0,G5=INT(G5),H5>=0,I5>=0,J5>0,J5=INT(J5),K5<>"",ISNUMBER(L5),L5>='00_审核入口'!$F$2,M5="已核实",N5="完整"),IF(Q5>0,T5/Q5,""),"") | V5: =IF(AND(COUNT(C5:J5)=8,C5>0,D5>=0,E5>0,F5>=0,G5>0,G5=INT(G5),H5>=0,I5>=0,J5>0,J5=INT(J5),K5<>"",ISNUMBER(L5),L5>='00_审核入口'!$F$2,M5="已核实",N5="完整"),IF(Q5-O5-ROUNDUP(MAX(15,0.2*Q5),2)<0,"无非负可行采购价",ROUNDDOWN((Q5-O5-ROUNDUP(MAX(15,0.2*Q5),2)+0.005-0.0000000001)/(G5*(1+H5)),2)),"") | W5: =IF(AND(COUNT(C5:J5)=8,C5>0,D5>=0,E5>0,F5>=0,G5>0,G5=INT(G5),H5>=0,I5>=0,J5>0,J5=INT(J5),K5<>"",ISNUMBER(L5),L5>='00_审核入口'!$F$2,M5="已核实",N5="完整"),ROUND(ROUND((C5+D5)*E5*0.95,10),2)-ROUND(ROUND(F5*1.1*G5*(1+H5),10),2)-P5,"") | X5: =IF(AND(COUNT(C5:J5)=8,C5>0,D5>=0,E5>0,F5>=0,G5>0,G5=INT(G5),H5>=0,I5>=0,J5>0,J5=INT(J5),K5<>"",ISNUMBER(L5),L5>='00_审核入口'!$F$2,M5="已核实",N5="完整"),ROUND(I5+J5*S5,2),"") | Y5: =IF(AND(COUNT(C5:J5)=8,C5>0,D5>=0,E5>0,F5>=0,G5>0,G5=INT(G5),H5>=0,I5>=0,J5>0,J5=INT(J5),K5<>"",ISNUMBER(L5),L5>='00_审核入口'!$F$2,M5="已核实",N5="完整"),IF(S5>0,MAX(0,INT((500-I5)/S5)),""),"") | Z5: =IF(AND(COUNT(C5:J5)=8,C5>0,D5>=0,E5>0,F5>=0,G5>0,G5=INT(G5),H5>=0,I5>=0,J5>0,J5=INT(J5),K5<>"",ISNUMBER(L5),L5>='00_审核入口'!$F$2,M5="已核实",N5="完整"),IF(AND(T5>=15,U5>=0.2,W5>=0,X5<=500),"成本条件通过","成本条件不通过"),"待补证")

Sheet 04_费用明细
A1: 04 · 费用明细
A2: 每款18项逐项核实；0要有免费或不适用依据。交易费压力金额必须填；国内运费/仓包/SLS在压力情景再×1.15，PHP费用用汇率×0.95。广告和售后可用有依据的预算，公共费率参考不自动填成本。
A4: ID | B4: 产品 | C4: 费项键 | D4: 费项名称 | E4: 币种 | F4: 基准金额 | G4: 压力金额覆盖 | H4: 状态 | I4: 规则/基数/舍入/封顶/分摊 | J4: 依据 | K4: 有效期截止 | L4: 基准CNY | M4: 压力CNY | N4: 本行完整
A5: TEST | B5: 隔离合成算例，非市场产品 | C5: commission | D5: 适用跨境佣金 | E5: PHP | F5: 100 | H5: 已核实 | I5: 仅为算法测试，不是事实费率 | J5: 隔离合成测试 | K5: 46281.667 | L5: =IF(AND(N5="完整",ISNUMBER('03_逐品成本'!E5),'03_逐品成本'!E5>0),ROUND(ROUND(F5*IF(E5="PHP",'03_逐品成本'!E5,1),10),2),"") | M5: =IF(AND(N5="完整",ISNUMBER('03_逐品成本'!E5),'03_逐品成本'!E5>0),ROUND(ROUND(IF(ISNUMBER(G5),G5,F5)*1*IF(E5="PHP",'03_逐品成本'!E5*0.95,1),10),2),"") | N5: =IF(AND(ISNUMBER(F5),F5>=0,OR(E5="PHP",E5="CNY"),OR(H5="已核实",H5="不适用"),I5<>"",J5<>"",ISNUMBER(K5),K5>='00_审核入口'!$F$2,OR(H5<>"不适用",F5=0),OR(G5="",AND(ISNUMBER(G5),G5>=0))),"完整","待补证")
A6: TEST | B6: 隔离合成算例，非市场产品 | C6: transaction | D6: 交易费（含实际支付方式） | E6: PHP | F6: 50 | G6: 100 | H6: 已核实 | I6: 仅为算法测试，不是事实费率 | J6: 隔离合成测试 | K6: 46281.667 | L6: =IF(AND(N6="完整",ISNUMBER('03_逐品成本'!E5),'03_逐品成本'!E5>0),ROUND(ROUND(F6*IF(E6="PHP",'03_逐品成本'!E5,1),10),2),"") | M6: =IF(AND(N6="完整",ISNUMBER('03_逐品成本'!E5),'03_逐品成本'!E5>0),ROUND(ROUND(IF(ISNUMBER(G6),G6,F6)*1*IF(E6="PHP",'03_逐品成本'!E5*0.95,1),10),2),"") | N6: =IF(AND(ISNUMBER(F6),F6>=0,OR(E6="PHP",E6="CNY"),OR(H6="已核实",H6="不适用"),I6<>"",J6<>"",ISNUMBER(K6),K6>='00_审核入口'!$F$2,OR(H6<>"不适用",F6=0),OR(G6="",AND(ISNUMBER(G6),G6>=0)),ISNUMBER(G6),G6>=0),"完整","待补证")
A7: TEST | B7: 隔离合成算例，非市场产品 | C7: installment_extra | D7: 额外分期项目费 | E7: CNY | F7: 0 | H7: 已核实 | I7: 仅为算法测试，不是事实费率 | J7: 隔离合成测试 | K7: 46281.667 | L7: =IF(AND(N7="完整",ISNUMBER('03_逐品成本'!E5),'03_逐品成本'!E5>0),ROUND(ROUND(F7*IF(E7="PHP",'03_逐品成本'!E5,1),10),2),"") | M7: =IF(AND(N7="完整",ISNUMBER('03_逐品成本'!E5),'03_逐品成本'!E5>0),ROUND(ROUND(IF(ISNUMBER(G7),G7,F7)*1*IF(E7="PHP",'03_逐品成本'!E5*0.95,1),10),2),"") | N7: =IF(AND(ISNUMBER(F7),F7>=0,OR(E7="PHP",E7="CNY"),OR(H7="已核实",H7="不适用"),I7<>"",J7<>"",ISNUMBER(K7),K7>='00_审核入口'!$F$2,OR(H7<>"不适用",F7=0),OR(G7="",AND(ISNUMBER(G7),G7>=0))),"完整","待补证")
A8: TEST | B8: 隔离合成算例，非市场产品 | C8: growth | D8: 卖家增长费 | E8: CNY | F8: 0 | H8: 已核实 | I8: 仅为算法测试，不是事实费率 | J8: 隔离合成测试 | K8: 46281.667 | L8: =IF(AND(N8="完整",ISNUMBER('03_逐品成本'!E5),'03_逐品成本'!E5>0),ROUND(ROUND(F8*IF(E8="PHP",'03_逐品成本'!E5,1),10),2),"") | M8: =IF(AND(N8="完整",ISNUMBER('03_逐品成本'!E5),'03_逐品成本'!E5>0),ROUND(ROUND(IF(ISNUMBER(G8),G8,F8)*1*IF(E8="PHP",'03_逐品成本'!E5*0.95,1),10),2),"") | N8: =IF(AND(ISNUMBER(F8),F8>=0,OR(E8="PHP",E8="CNY"),OR(H8="已核实",H8="不适用"),I8<>"",J8<>"",ISNUMBER(K8),K8>='00_审核入口'!$F$2,OR(H8<>"不适用",F8=0),OR(G8="",AND(ISNUMBER(G8),G8>=0))),"完整","待补证")
A9: TEST | B9: 隔离合成算例，非市场产品 | C9: platform_shipping | D9: 平台运费计划费 | E9: CNY | F9: 0 | H9: 已核实 | I9: 仅为算法测试，不是事实费率 | J9: 隔离合成测试 | K9: 46281.667 | L9: =IF(AND(N9="完整",ISNUMBER('03_逐品成本'!E5),'03_逐品成本'!E5>0),ROUND(ROUND(F9*IF(E9="PHP",'03_逐品成本'!E5,1),10),2),"") | M9: =IF(AND(N9="完整",ISNUMBER('03_逐品成本'!E5),'03_逐品成本'!E5>0),ROUND(ROUND(IF(ISNUMBER(G9),G9,F9)*1*IF(E9="PHP",'03_逐品成本'!E5*0.95,1),10),2),"") | N9: =IF(AND(ISNUMBER(F9),F9>=0,OR(E9="PHP",E9="CNY"),OR(H9="已核实",H9="不适用"),I9<>"",J9<>"",ISNUMBER(K9),K9>='00_审核入口'!$F$2,OR(H9<>"不适用",F9=0),OR(G9="",AND(ISNUMBER(G9),G9>=0))),"完整","待补证")
A10: TEST | B10: 隔离合成算例，非市场产品 | C10: order_processing | D10: 订单处理费 | E10: CNY | F10: 0 | H10: 已核实 | I10: 仅为算法测试，不是事实费率 | J10: 隔离合成测试 | K10: 46281.667 | L10: =IF(AND(N10="完整",ISNUMBER('03_逐品成本'!E5),'03_逐品成本'!E5>0),ROUND(ROUND(F10*IF(E10="PHP",'03_逐品成本'!E5,1),10),2),"") | M10: =IF(AND(N10="完整",ISNUMBER('03_逐品成本'!E5),'03_逐品成本'!E5>0),ROUND(ROUND(IF(ISNUMBER(G10),G10,F10)*1*IF(E10="PHP",'03_逐品成本'!E5*0.95,1),10),2),"") | N10: =IF(AND(ISNUMBER(F10),F10>=0,OR(E10="PHP",E10="CNY"),OR(H10="已核实",H10="不适用"),I10<>"",J10<>"",ISNUMBER(K10),K10>='00_审核入口'!$F$2,OR(H10<>"不适用",F10=0),OR(G10="",AND(ISNUMBER(G10),G10>=0))),"完整","待补证")
A11: TEST | B11: 隔离合成算例，非市场产品 | C11: preorder | D11: 预售及其他平台服务费 | E11: CNY | F11: 0 | H11: 已核实 | I11: 仅为算法测试，不是事实费率 | J11: 隔离合成测试 | K11: 46281.667 | L11: =IF(AND(N11="完整",ISNUMBER('03_逐品成本'!E5),'03_逐品成本'!E5>0),ROUND(ROUND(F11*IF(E11="PHP",'03_逐品成本'!E5,1),10),2),"") | M11: =IF(AND(N11="完整",ISNUMBER('03_逐品成本'!E5),'03_逐品成本'!E5>0),ROUND(ROUND(IF(ISNUMBER(G11),G11,F11)*1*IF(E11="PHP",'03_逐品成本'!E5*0.95,1),10),2),"") | N11: =IF(AND(ISNUMBER(F11),F11>=0,OR(E11="PHP",E11="CNY"),OR(H11="已核实",H11="不适用"),I11<>"",J11<>"",ISNUMBER(K11),K11>='00_审核入口'!$F$2,OR(H11<>"不适用",F11=0),OR(G11="",AND(ISNUMBER(G11),G11>=0))),"完整","待补证")
A12: TEST | B12: 隔离合成算例，非市场产品 | C12: activities | D12: MDV/返币/直播等活动费 | E12: CNY | F12: 0 | H12: 已核实 | I12: 仅为算法测试，不是事实费率 | J12: 隔离合成测试 | K12: 46281.667 | L12: =IF(AND(N12="完整",ISNUMBER('03_逐品成本'!E5),'03_逐品成本'!E5>0),ROUND(ROUND(F12*IF(E12="PHP",'03_逐品成本'!E5,1),10),2),"") | M12: =IF(AND(N12="完整",ISNUMBER('03_逐品成本'!E5),'03_逐品成本'!E5>0),ROUND(ROUND(IF(ISNUMBER(G12),G12,F12)*1*IF(E12="PHP",'03_逐品成本'!E5*0.95,1),10),2),"") | N12: =IF(AND(ISNUMBER(F12),F12>=0,OR(E12="PHP",E12="CNY"),OR(H12="已核实",H12="不适用"),I12<>"",J12<>"",ISNUMBER(K12),K12>='00_审核入口'!$F$2,OR(H12<>"不适用",F12=0),OR(G12="",AND(ISNUMBER(G12),G12>=0))),"完整","待补证")
A13: TEST | B13: 隔离合成算例，非市场产品 | C13: domestic | D13: 中国境内运费 | E13: CNY | F13: 10 | H13: 已核实 | I13: 仅为算法测试，不是事实费率 | J13: 隔离合成测试 | K13: 46281.667 | L13: =IF(AND(N13="完整",ISNUMBER('03_逐品成本'!E5),'03_逐品成本'!E5>0),ROUND(ROUND(F13*IF(E13="PHP",'03_逐品成本'!E5,1),10),2),"") | M13: =IF(AND(N13="完整",ISNUMBER('03_逐品成本'!E5),'03_逐品成本'!E5>0),ROUND(ROUND(IF(ISNUMBER(G13),G13,F13)*1.15*IF(E13="PHP",'03_逐品成本'!E5*0.95,1),10),2),"") | N13: =IF(AND(ISNUMBER(F13),F13>=0,OR(E13="PHP",E13="CNY"),OR(H13="已核实",H13="不适用"),I13<>"",J13<>"",ISNUMBER(K13),K13>='00_审核入口'!$F$2,OR(H13<>"不适用",F13=0),OR(G13="",AND(ISNUMBER(G13),G13>=0))),"完整","待补证")
A14: TEST | B14: 隔离合成算例，非市场产品 | C14: warehouse_pack | D14: 云仓/验货/贴标/仓储/包材 | E14: CNY | F14: 5 | H14: 已核实 | I14: 仅为算法测试，不是事实费率 | J14: 隔离合成测试 | K14: 46281.667 | L14: =IF(AND(N14="完整",ISNUMBER('03_逐品成本'!E5),'03_逐品成本'!E5>0),ROUND(ROUND(F14*IF(E14="PHP",'03_逐品成本'!E5,1),10),2),"") | M14: =IF(AND(N14="完整",ISNUMBER('03_逐品成本'!E5),'03_逐品成本'!E5>0),ROUND(ROUND(IF(ISNUMBER(G14),G14,F14)*1.15*IF(E14="PHP",'03_逐品成本'!E5*0.95,1),10),2),"") | N14: =IF(AND(ISNUMBER(F14),F14>=0,OR(E14="PHP",E14="CNY"),OR(H14="已核实",H14="不适用"),I14<>"",J14<>"",ISNUMBER(K14),K14>='00_审核入口'!$F$2,OR(H14<>"不适用",F14=0),OR(G14="",AND(ISNUMBER(G14),G14>=0))),"完整","待补证")
A15: TEST | B15: 隔离合成算例，非市场产品 | C15: sls | D15: SLS卖家净国际物流 | E15: CNY | F15: 20 | H15: 已核实 | I15: 仅为算法测试，不是事实费率 | J15: 隔离合成测试 | K15: 46281.667 | L15: =IF(AND(N15="完整",ISNUMBER('03_逐品成本'!E5),'03_逐品成本'!E5>0),ROUND(ROUND(F15*IF(E15="PHP",'03_逐品成本'!E5,1),10),2),"") | M15: =IF(AND(N15="完整",ISNUMBER('03_逐品成本'!E5),'03_逐品成本'!E5>0),ROUND(ROUND(IF(ISNUMBER(G15),G15,F15)*1.15*IF(E15="PHP",'03_逐品成本'!E5*0.95,1),10),2),"") | N15: =IF(AND(ISNUMBER(F15),F15>=0,OR(E15="PHP",E15="CNY"),OR(H15="已核实",H15="不适用"),I15<>"",J15<>"",ISNUMBER(K15),K15>='00_审核入口'!$F$2,OR(H15<>"不适用",F15=0),OR(G15="",AND(ISNUMBER(G15),G15>=0))),"完整","待补证")
A16: TEST | B16: 隔离合成算例，非市场产品 | C16: ads | D16: 广告预算分摊 | E16: CNY | F16: 7 | H16: 已核实 | I16: 仅为算法测试，不是事实费率 | J16: 隔离合成测试 | K16: 46281.667 | L16: =IF(AND(N16="完整",ISNUMBER('03_逐品成本'!E5),'03_逐品成本'!E5>0),ROUND(ROUND(F16*IF(E16="PHP",'03_逐品成本'!E5,1),10),2),"") | M16: =IF(AND(N16="完整",ISNUMBER('03_逐品成本'!E5),'03_逐品成本'!E5>0),ROUND(ROUND(IF(ISNUMBER(G16),G16,F16)*1*IF(E16="PHP",'03_逐品成本'!E5*0.95,1),10),2),"") | N16: =IF(AND(ISNUMBER(F16),F16>=0,OR(E16="PHP",E16="CNY"),OR(H16="已核实",H16="不适用",H16="预算"),I16<>"",J16<>"",ISNUMBER(K16),K16>='00_审核入口'!$F$2,OR(H16<>"不适用",F16=0),OR(G16="",AND(ISNUMBER(G16),G16>=0))),"完整","待补证")
A17: TEST | B17: 隔离合成算例，非市场产品 | C17: affiliate | D17: 联盟/达人分摊 | E17: CNY | F17: 0 | H17: 已核实 | I17: 仅为算法测试，不是事实费率 | J17: 隔离合成测试 | K17: 46281.667 | L17: =IF(AND(N17="完整",ISNUMBER('03_逐品成本'!E5),'03_逐品成本'!E5>0),ROUND(ROUND(F17*IF(E17="PHP",'03_逐品成本'!E5,1),10),2),"") | M17: =IF(AND(N17="完整",ISNUMBER('03_逐品成本'!E5),'03_逐品成本'!E5>0),ROUND(ROUND(IF(ISNUMBER(G17),G17,F17)*1*IF(E17="PHP",'03_逐品成本'!E5*0.95,1),10),2),"") | N17: =IF(AND(ISNUMBER(F17),F17>=0,OR(E17="PHP",E17="CNY"),OR(H17="已核实",H17="不适用",H17="预算"),I17<>"",J17<>"",ISNUMBER(K17),K17>='00_审核入口'!$F$2,OR(H17<>"不适用",F17=0),OR(G17="",AND(ISNUMBER(G17),G17>=0))),"完整","待补证")
A18: TEST | B18: 隔离合成算例，非市场产品 | C18: returns | D18: 售后退款/拒收/破损净损失准备 | E18: CNY | F18: 0 | H18: 已核实 | I18: 仅为算法测试，不是事实费率 | J18: 隔离合成测试 | K18: 46281.667 | L18: =IF(AND(N18="完整",ISNUMBER('03_逐品成本'!E5),'03_逐品成本'!E5>0),ROUND(ROUND(F18*IF(E18="PHP",'03_逐品成本'!E5,1),10),2),"") | M18: =IF(AND(N18="完整",ISNUMBER('03_逐品成本'!E5),'03_逐品成本'!E5>0),ROUND(ROUND(IF(ISNUMBER(G18),G18,F18)*1*IF(E18="PHP",'03_逐品成本'!E5*0.95,1),10),2),"") | N18: =IF(AND(ISNUMBER(F18),F18>=0,OR(E18="PHP",E18="CNY"),OR(H18="已核实",H18="不适用",H18="预算"),I18<>"",J18<>"",ISNUMBER(K18),K18>='00_审核入口'!$F$2,OR(H18<>"不适用",F18=0),OR(G18="",AND(ISNUMBER(G18),G18>=0))),"完整","待补证")
A19: TEST | B19: 隔离合成算例，非市场产品 | C19: collection | D19: 收款/换汇/提现 | E19: CNY | F19: 0 | H19: 已核实 | I19: 仅为算法测试，不是事实费率 | J19: 隔离合成测试 | K19: 46281.667 | L19: =IF(AND(N19="完整",ISNUMBER('03_逐品成本'!E5),'03_逐品成本'!E5>0),ROUND(ROUND(F19*IF(E19="PHP",'03_逐品成本'!E5,1),10),2),"") | M19: =IF(AND(N19="完整",ISNUMBER('03_逐品成本'!E5),'03_逐品成本'!E5>0),ROUND(ROUND(IF(ISNUMBER(G19),G19,F19)*1*IF(E19="PHP",'03_逐品成本'!E5*0.95,1),10),2),"") | N19: =IF(AND(ISNUMBER(F19),F19>=0,OR(E19="PHP",E19="CNY"),OR(H19="已核实",H19="不适用"),I19<>"",J19<>"",ISNUMBER(K19),K19>='00_审核入口'!$F$2,OR(H19<>"不适用",F19=0),OR(G19="",AND(ISNUMBER(G19),G19>=0))),"完整","待补证")
A20: TEST | B20: 隔离合成算例，非市场产品 | C20: tax | D20: 其他不可抵扣税费 | E20: CNY | F20: 0 | H20: 已核实 | I20: 仅为算法测试，不是事实费率 | J20: 隔离合成测试 | K20: 46281.667 | L20: =IF(AND(N20="完整",ISNUMBER('03_逐品成本'!E5),'03_逐品成本'!E5>0),ROUND(ROUND(F20*IF(E20="PHP",'03_逐品成本'!E5,1),10),2),"") | M20: =IF(AND(N20="完整",ISNUMBER('03_逐品成本'!E5),'03_逐品成本'!E5>0),ROUND(ROUND(IF(ISNUMBER(G20),G20,F20)*1*IF(E20="PHP",'03_逐品成本'!E5*0.95,1),10),2),"") | N20: =IF(AND(ISNUMBER(F20),F20>=0,OR(E20="PHP",E20="CNY"),OR(H20="已核实",H20="不适用"),I20<>"",J20<>"",ISNUMBER(K20),K20>='00_审核入口'!$F$2,OR(H20<>"不适用",F20=0),OR(G20="",AND(ISNUMBER(G20),G20>=0))),"完整","待补证")
A21: TEST | B21: 隔离合成算例，非市场产品 | C21: overhead | D21: 固定运营成本分摊 | E21: CNY | F21: 0 | H21: 已核实 | I21: 仅为算法测试，不是事实费率 | J21: 隔离合成测试 | K21: 46281.667 | L21: =IF(AND(N21="完整",ISNUMBER('03_逐品成本'!E5),'03_逐品成本'!E5>0),ROUND(ROUND(F21*IF(E21="PHP",'03_逐品成本'!E5,1),10),2),"") | M21: =IF(AND(N21="完整",ISNUMBER('03_逐品成本'!E5),'03_逐品成本'!E5>0),ROUND(ROUND(IF(ISNUMBER(G21),G21,F21)*1*IF(E21="PHP",'03_逐品成本'!E5*0.95,1),10),2),"") | N21: =IF(AND(ISNUMBER(F21),F21>=0,OR(E21="PHP",E21="CNY"),OR(H21="已核实",H21="不适用",H21="预算"),I21<>"",J21<>"",ISNUMBER(K21),K21>='00_审核入口'!$F$2,OR(H21<>"不适用",F21=0),OR(G21="",AND(ISNUMBER(G21),G21>=0))),"完整","待补证")
A22: TEST | B22: 隔离合成算例，非市场产品 | C22: other | D22: 其他有说明费用 | E22: CNY | F22: 0 | H22: 已核实 | I22: 仅为算法测试，不是事实费率 | J22: 隔离合成测试 | K22: 46281.667 | L22: =IF(AND(N22="完整",ISNUMBER('03_逐品成本'!E5),'03_逐品成本'!E5>0),ROUND(ROUND(F22*IF(E22="PHP",'03_逐品成本'!E5,1),10),2),"") | M22: =IF(AND(N22="完整",ISNUMBER('03_逐品成本'!E5),'03_逐品成本'!E5>0),ROUND(ROUND(IF(ISNUMBER(G22),G22,F22)*1*IF(E22="PHP",'03_逐品成本'!E5*0.95,1),10),2),"") | N22: =IF(AND(ISNUMBER(F22),F22>=0,OR(E22="PHP",E22="CNY"),OR(H22="已核实",H22="不适用",H22="预算"),I22<>"",J22<>"",ISNUMBER(K22),K22>='00_审核入口'!$F$2,OR(H22<>"不适用",F22=0),OR(G22="",AND(ISNUMBER(G22),G22>=0))),"完整","待补证")
